Workbook

Sheet H.EV
B3: PRE INVERSION | C3: INVERSION | E3: POST INVERSION
E4: 13 años
B5: Estudio a nivel de perfil | C5: Expediente tecnico | D5: Licitacion y contratacion de obra, ejecucion de obras, implementacion de equipos, elaboracion de programa de capacitacion, supersion y liquidacion | E5: Operación y mantenimiento
H6: ACTIVIDADES | I6: PERIODO 0 (Años) | K6: OPERACIÓN Y MANTENIMIENTO (13 Años)
I7: 2024 | J7: 2025 | K7: Año 1 | L7: Año 2 | M7: Año 3 | N7: Año 4 | O7: Año 5 | P7: Año 6 | Q7: Año 7 | R7: Año 8 | S7: Año 9 | T7: Año 10 | U7: Año 11 | V7: Año 12 | W7: Año 13
H9: FASE DE INVERSION
H10: Elaboracion de expediente tecnico
H11: Licitacion y contratacion de obra
H12: Construccion de la obra
H13: Salud y seguridad de obra
H14: Plan de contingencia
H15: Mitigacion ambiental
H16: Equipamiento
H17: Supervision
H18: Liquidacion de obra
H19: FASE DE POST INVERSION
H20: Operación y mantenimiento

Sheet CART.SERVICIOS
B3: CARTERA DE SERVICIOS | C3: ACTIVIDADES
B4: Consulta ambulatoria por medico general | C4: Consultorio de medicina general | D4: atencion
B5: Teleconsulta por medico general | C5: Teleconsultamedica | D5: atencion
B6: Atención ambulatoria por enfermera | C6: Consultorio CRED | D6: atencion
C7: Sala de estimulacion temprana
C8: Sala de Inmunizaciones | D8: vacuna
B9: Atencion ambulatoria por profesional de la salud | C9: Modulo para prevencion y consejeria de TBC
C10: Consejeria y prevencion de ITS, VIH y SIDA
C11: Atencíon integral y consejeria del Adolescente
C12: Atencíon integral del Adulto Mayor
C13: Consejería y prevención de Enf. No Transmisibles
B14: Atención ambulatoria por obstetra | C14: Control Prenatal + 1/2 S.H. | D14: atencion
C15: Planificacíon Familiar | D15: sesion
C16: Consejería y prevención del Cáncer
C17: Psicoprofilaxis
B18: Atención ambulatoria por cirujano dentista general con soporte de radiología oral | C18: Consultorio de odontologia general con soporte de radiografia | D18: atencion
B19: Atencion ambulatoria por psicologo | C19: Consultorio de psicologia
B20: Atencion ambbulatoria por personal de salud capacitado en salud mental | C20: Salud mental
B21: Atencion diferenciada de pacientes COVID u otras afecciones respiratorias | C21: COVID u otras afecciones respiratorias
B22: Atencion de urgencias y emergencias por medico general | C22: Topico Urgencias y emergencias | D22: atencion
B23: Atencion de ambienye de observacion de emergencia | C23: Sala de observacion de mergencia | D23: egreso
B24: Atencion patologia clinica | C24: Laboratorio | D24: muestra
B25: Atencion de radiologia y ecografia | C25: Ecografia | D25: examen
C26: Radiografia | D26: examen
B27: Atecncion con medicamentos | C27: Farmacia | D27: receta
B28: Desinfeccion y esterilizacion | C28: Desinfeccin y esterilizacion | D28: unidad esterilizada

Sheet Hoja1
B2: EE. SS | C2: GRUPOS DE EDAD
C3: 0 | D3: 1 | E3: 2 | F3: 3 | G3: 4 | H3: 5 | I3: 6 | J3: 7 | K3: 8 | L3: 9 | M3: 10 | N3: 11 | O3: 12 | P3: 13 | Q3: 14 | R3: 15 | S3: 16 | T3: 17 | U3: 18 | V3: 19 | W3: 20 - 24 | X3: 25 - 29 | Y3: 30 - 34 | Z3: 35 - 39 | AA3: 40 - 44 | AB3: 45 - 49 | AC3: 50- 54 | AD3: 55 - 59 | AE3: 60 - 64 | AF3: 65 - 69 | AG3: 70 - 74 | AH3: 75 - 79 | AI3: 80 y mas | AJ3: TOTAL
B4: P.S. Arhuay | C4: 7 | D4: 5 | E4: 13 | F4: 15 | G4: 13 | H4: 11 | I4: 7 | J4: 7 | K4: 7 | L4: 6 | M4: 5 | N4: 8 | O4: 7 | P4: 9 | Q4: 7 | R4: 5 | S4: 6 | T4: 5 | U4: 7 | V4: 6 | W4: 41 | X4: 47 | Y4: 40 | Z4: 32 | AA4: 34 | AB4: 29 | AC4: 25 | AD4: 23 | AE4: 23 | AF4: 16 | AG4: 13 | AH4: 9 | AI4: 19 | AJ4: =SUM(C4:AI4) -> 507
B8: POBLACION POR GRUPOS ESPECIALES P.S. ARHUAY | Z8: =+SUM(V4:AI4) -> 357
B9: EE.SS | C9: NIÑOS MENORES 5 AÑOS | E9: POBLACION FEMENINA | I9: GESTANTES | K9: NACIMIENTOS | M9: DIAS ESPECIALES
E10: Total | F10: 10-14 | G10: 15-19 | H10: 20-49 | M10: 28 dias | N10: 0-5 meses | O10: 6-11 meses
B11: P.S ARHUAY | C11: =+SUM(C4:G4) -> 53 | E11: 257 | F11: 17 | G11: 14 | H11: 115 | I11: 18 | K11: 7 | M11: 3 | N11: 3 | O11: 3
B14: POBLACION PROYECTADA P.S HUANCHAY
B16: Año base (2024) | D16: 507
B17: Tasa de crecimiento* | D17: =+Hoja3!C8 -> 0.0003
B18: *INEI -
B20: AÑO | C20: POBLACION
B21: 2024 | C21: =+D16 -> 507
B22: =+B21+1 -> 2025 | C22: =ROUND(($C$21*(1+$D$17)^1),0) -> 507 | L22: =21/12 -> 1.75
B23: =+B22+1 -> 2026 | C23: =ROUND(($C$21*(1+$D$17)^2),0) -> 507
B24: =+B23+1 -> 2027 | C24: =ROUND(($C$21*(1+$D$17)^3),0) -> 507
B25: =+B24+1 -> 2028 | C25: =ROUND(($C$21*(1+$D$17)^4),0) -> 508
B26: =+B25+1 -> 2029 | C26: =ROUND(($C$21*(1+$D$17)^5),0) -> 508
B27: =+B26+1 -> 2030 | C27: =ROUND(($C$21*(1+$D$17)^6),0) -> 508
B28: =+B27+1 -> 2031 | C28: =ROUND(($C$21*(1+$D$17)^7),0) -> 508
B29: =+B28+1 -> 2032 | C29: =ROUND(($C$21*(1+$D$17)^8),0) -> 508
B30: =+B29+1 -> 2033 | C30: =ROUND(($C$21*(1+$D$17)^9),0) -> 508
B31: =+B30+1 -> 2034 | C31: =ROUND(($C$21*(1+$D$17)^10),0) -> 509
B32: =+B31+1 -> 2035 | C32: =ROUND(($C$21*(1+$D$17)^11),0) -> 509
B33: =+B32+1 -> 2036 | C33: =ROUND(($C$21*(1+$D$17)^12),0) -> 509
B34: TOTAL | C34: =SUM(C22:C33) -> 6096

Sheet Hoja3
B2: TOTAL DE LA POBLACION
B3: POBLACION DEL DISTRITO DE RAHUAPAMPA
B4: CENSO | C4: TOTAL
B5: 2017 | C5: 741
B6: 2007 | C6: 739
B7: TASA DE CRECIMIENTO DE LA POBLACION TOTAL | C7: =+(((C6/C5)^(1/(B6-B5)))-1)*100 -> 0.027030696
C8: =ROUND((C7/100),4) -> 0.0003
B11: POBLACION DE LA PROVINCIA DE HUARI
B12: CENSO | C12: POBLACION
B13: 2017 | C13: 62278
B14: 2007 | C14: 62598
B15: TASA DE CRECIMIENTO | C15: =+(((C14/C13)^(1/(B14-B13)))-1)*100 -> -0.051237822
C16: =ROUND((C15/100),4) -> -0.0005
B18: POBLACION DEL DEPARTAMENTO DE ANCASH
B19: CENSO | C19: POBLACION
B20: 2017 | C20: 1083519
B21: 2007 | C21: 1063459
B22: TASA DE CRECIMIENTO | C22: =+(((C21/C20)^(1/(B21-B20)))-1)*100 -> 0.18704746
C23: =ROUND((C22/100),4) -> 0.0019

Sheet POBLACION DE REFERENCIA
B1: POBLACION DE REFERENCIA
B2: Poblacion de referencia: Consultorio de medicina general (Numero de personas de 0 a 85 años a mas) en el año 2024 | C2: 507 x 100% = | D2: 507
B3: Poblacion de referencia: Teleconsultamedica (Numero de personas de 0 a 85 años a mas) en el año 2024 | C3: 507 x 100% = | D3: 507
B4: Poblacion de referencia: Consultorio CRED (Numero de niños menores de 11 años)en el año 2024 | C4: 107 x 100% = | D4: 107
B5: Poblacion de referencia: Estimulacion temprana (Numero de niños menores de 3 años) en el año 2024 | C5: 43 x 100 % = | D5: 43
B6: Poblacion de referencia: Inmunizaciones (Menores de 4 años, gestantes) en el año 2024 | C6: 71 x 100% = | D6: 71
B7: Poblacion de referencia: Prevencion y consejeria de TBC (Mayores a 18 a 85 años a mas) en el año 2024 | C7: 364 * 100% = | D7: 364
B8: Poblacion de referencia: Consejeria y prevencion de ITS, VIH y SIDA (mayores a 18 años) en el año 2024 | C8: 364 * 100% = | D8: 364
B9: Poblacion de referencia: Atencíon integral y consejeria del Adolescente en el año 2024 | C9: 39 * 100% = | D9: 39
B10: Poblacion de referencia: Atencíon integral del Adulto Mayor en el año 2024 | C10: 364 x 100% = | D10: 364
B11: Poblacion de referencia: Consejería y prevención de Enf. No Transmisibles (mayores a 18 años) en el año 2024 | C11: 364 x 100% = | D11: 364
B12: Poblacion de referencia: Control Prenatal + 1/2 S.H (gestantes) en el año 2024 | C12: 18 x 100% = | D12: 18
B13: Poblacion de referencia: Planificacíon Familiar (MEF DE 15 a 49 años) en el año 2024 | C13: 252 x 100% = | D13: 252
... B24: Poblacion de referencia: Desinfeccion y esterilizacion (0 a 85 años a mas) en el año 2024 | C24: 507 x 100% = | D24: 507
B28: POBLACION SUJETO DE INTERVENCION (PERSONAS EN SUS DIFERENTES ETAPAS DE VIDA) | C28: PERIODO DE INVERSION | F28: PERIODO DE POST INVERSION
C29: 0 | F29: 1 | G29: 2 | H29: 3 | I29: 4 | J29: 5 | K29: 6 | L29: 7 | M29: 8 | N29: 9 | O29: 10
C30: 2024 | D30: 2025 | E30: 2026 | F30: 2027 | G30: 2028 | H30: 2029 | I30: 2030 | J30: 2031 | K30: 2032 | L30: 2033 | M30: 2034 | N30: 2035 | O30: 2036
B31: Medicina General | C31: =+C32 -> 507 | D31: =+D32 -> 507 | E31: =+E32 -> 507 | F31: =+F32 -> 507 | G31: =+G32 -> 508 | H31: =+H32 -> 508 | I31: =+I32 -> 508 | J31: =+J32 -> 508 | ... O31: =+O32 -> 509
B32: Medicina General (0 a 85 años a mas) | C32: =+Hoja1!AJ4 -> 507 | D32: =ROUND(($C$32*(1+$A$73)^(D30-$C$30)),0) -> 507 | E32: =ROUND(($C$32*(1+$A$73)^(E30-$C$30)),0) -> 507 | F32: =ROUND(($C$32*(1+$A$73)^(F30-$C$30)),0) -> 507 | G32: =ROUND(($C$32*(1+$A$73)^(G30-$C$30)),0) -> 508 | H32: =ROUND(($C$32*(1+$A$73)^(H30-$C$30)),0) -> 508 | I32: =ROUND(($C$32*(1+$A$73)^(I30-$C$30)),0) -> 508 | J32: =ROUND(($C$32*(1+$A$73)^(J30-$C$30)),0) -> 508 | K32: =ROUND(($C$32*(1+$A$73)^(K30-$C$30)),0) -> 508 | ... O32: =ROUND(($C$32*(1+$A$73)^(O30-$C$30)),0) -> 509
B34: POBLACION SUJETO DE INTERVENCION (PERSONAS EN SUS DIFERENTES ETAPAS DE VIDA) | C34: PERIODO DE INVERSION | F34: PERIODO DE POST INVERSION
C35: 0 | F35: 1 | G35: 2 | H35: 3 | I35: 4 | J35: 5 | K35: 6 | L35: 7 | M35: 8 | N35: 9 | O35: 10
C36: 2024 | D36: 2025 | E36: 2026 | F36: 2027 | G36: 2028 | H36: 2029 | I36: 2030 | J36: 2031 | K36: 2032 | L36: 2033 | M36: 2034 | N36: 2035 | O36: 2036
B37: Teleconsulta medica | C37: =+C38 -> 507 | D37: =+D38 -> 507 | E37: =+E38 -> 507 | F37: =+F38 -> 507 | G37: =+G38 -> 508 | H37: =+H38 -> 508 | I37: =+I38 -> 508 | J37: =+J38 -> 508 | ... O37: =+O38 -> 509
B38: Medicina General (0 a 85 años a mas) | C38: =+Hoja1!AJ4 -> 507 | D38: =ROUND(($C$38*(1+$A$73)^(D36-$C$36)),0) -> 507 | E38: =ROUND(($C$38*(1+$A$73)^(E36-$C$36)),0) -> 507 | F38: =ROUND(($C$38*(1+$A$73)^(F36-$C$36)),0) -> 507 | G38: =ROUND(($C$38*(1+$A$73)^(G36-$C$36)),0) -> 508 | H38: =ROUND(($C$38*(1+$A$73)^(H36-$C$36)),0) -> 508 | I38: =ROUND(($C$38*(1+$A$73)^(I36-$C$36)),0) -> 508 | J38: =ROUND(($C$38*(1+$A$73)^(J36-$C$36)),0) -> 508 | K38: =ROUND(($C$38*(1+$A$73)^(K36-$C$36)),0) -> 508 | ... O38: =ROUND(($C$38*(1+$A$73)^(O36-$C$36)),0) -> 509
B40: POBLACION SUJETO DE INTERVENCION | C40: PERIODO DE INVERSION | F40: PERIODO DE POST INVERSION
C41: 0 | F41: 1 | G41: 2 | H41: 3 | I41: 4 | J41: 5 | K41: 6 | L41: 7 | M41: 8 | N41: 9 | O41: 10
C42: =+C36 -> 2024 | D42: =+D36 -> 2025 | E42: =+E36 -> 2026 | F42: =+F36 -> 2027 | G42: =+G36 -> 2028 | H42: =+H36 -> 2029 | I42: =+I36 -> 2030 | J42: =+J36 -> 2031 | ... O42: =+O36 -> 2036
B43: CRED (< de 11 años) | C43: =+SUM(C44:C50) -> 107 | D43: =+SUM(D44:D50) -> 107 | E43: =+SUM(E44:E50) -> 107 | F43: =+SUM(F44:F50) -> 107 | G43: =+SUM(G44:G50) -> 107 | H43: =+SUM(H44:H50) -> 107 | I43: =+SUM(I44:I50) -> 107 | J43: =+SUM(J44:J50) -> 107 | ... O43: =+SUM(O44:O50) -> 107
B44: < de 29 dias | C44: =+Hoja1!M11 -> 3 | D44: =ROUND(($C$44*(1+$A$73)^(D42-$C$42)),0) -> 3 | E44: =ROUND(($C$44*(1+$A$73)^(E42-$C$42)),0) -> 3 | F44: =ROUND(($C$44*(1+$A$73)^(F42-$C$42)),0) -> 3 | G44: =ROUND(($C$44*(1+$A$73)^(G42-$C$42)),0) -> 3 | H44: =ROUND(($C$44*(1+$A$73)^(H42-$C$42)),0) -> 3 | I44: =ROUND(($C$44*(1+$A$73)^(I42-$C$42)),0) -> 3 | J44: =ROUND(($C$44*(1+$A$73)^(J42-$C$42)),0) -> 3 | K44: =ROUND(($C$44*(1+$A$73)^(K42-$C$42)),0) -> 3 | ... O44: =ROUND(($C$44*(1+$A$73)^(O42-$C$42)),0) -> 3
B45: < de 1 año | C45: =+Hoja1!C4 -> 7 | D45: =ROUND(($C$45*(1+$A$73)^(D42-$C$42)),0) -> 7 | E45: =ROUND(($C$45*(1+$A$73)^(E42-$C$42)),0) -> 7 | F45: =ROUND(($C$45*(1+$A$73)^(F42-$C$42)),0) -> 7 | G45: =ROUND(($C$45*(1+$A$73)^(G42-$C$42)),0) -> 7 | H45: =ROUND(($C$45*(1+$A$73)^(H42-$C$42)),0) -> 7 | I45: =ROUND(($C$45*(1+$A$73)^(I42-$C$42)),0) -> 7 | J45: =ROUND(($C$45*(1+$A$73)^(J42-$C$42)),0) -> 7 | K45: =ROUND(($C$45*(1+$A$73)^(K42-$C$42)),0) -> 7 | ... O45: =ROUND(($C$45*(1+$A$73)^(O42-$C$42)),0) -> 7
B46: 1 año | C46: =+Hoja1!D4 -> 5 | D46: =ROUND(($C$46*(1+$A$73)^(D42-$C$42)),0) -> 5 | E46: =ROUND(($C$46*(1+$A$73)^(E42-$C$42)),0) -> 5 | F46: =ROUND(($C$46*(1+$A$73)^(F42-$C$42)),0) -> 5 | G46: =ROUND(($C$46*(1+$A$73)^(G42-$C$42)),0) -> 5 | H46: =ROUND(($C$46*(1+$A$73)^(H42-$C$42)),0) -> 5 | I46: =ROUND(($C$46*(1+$A$73)^(I42-$C$42)),0) -> 5 | J46: =ROUND(($C$46*(1+$A$73)^(J42-$C$42)),0) -> 5 | K46: =ROUND(($C$46*(1+$A$73)^(K42-$C$42)),0) -> 5 | ... O46: =ROUND(($C$46*(1+$A$73)^(O42-$C$42)),0) -> 5
B47: 2 años | C47: =+Hoja1!E4 -> 13 | D47: =ROUND(($C$47*(1+$A$73)^(D42-$C$42)),0) -> 13 | E47: =ROUND(($C$47*(1+$A$73)^(E42-$C$42)),0) -> 13 | F47: =ROUND(($C$47*(1+$A$73)^(F42-$C$42)),0) -> 13 | G47: =ROUND(($C$47*(1+$A$73)^(G42-$C$42)),0) -> 13 | H47: =ROUND(($C$47*(1+$A$73)^(H42-$C$42)),0) -> 13 | I47: =ROUND(($C$47*(1+$A$73)^(I42-$C$42)),0) -> 13 | J47: =ROUND(($C$47*(1+$A$73)^(J42-$C$42)),0) -> 13 | K47: =ROUND(($C$47*(1+$A$73)^(K42-$C$42)),0) -> 13 | ... O47: =ROUND(($C$47*(1+$A$73)^(O42-$C$42)),0) -> 13
B48: 3 años | C48: =+Hoja1!F4 -> 15 | D48: =ROUND(($C$48*(1+$A$73)^(D42-$C$42)),0) -> 15 | E48: =ROUND(($C$48*(1+$A$73)^(E42-$C$42)),0) -> 15 | F48: =ROUND(($C$48*(1+$A$73)^(F42-$C$42)),0) -> 15 | G48: =ROUND(($C$48*(1+$A$73)^(G42-$C$42)),0) -> 15 | H48: =ROUND(($C$48*(1+$A$73)^(H42-$C$42)),0) -> 15 | I48: =ROUND(($C$48*(1+$A$73)^(I42-$C$42)),0) -> 15 | J48: =ROUND(($C$48*(1+$A$73)^(J42-$C$42)),0) -> 15 | K48: =ROUND(($C$48*(1+$A$73)^(K42-$C$42)),0) -> 15 | ... O48: =ROUND(($C$48*(1+$A$73)^(O42-$C$42)),0) -> 15
B49: 4 años | C49: =+Hoja1!G4 -> 13 | D49: =ROUND(($C$49*(1+$A$73)^(D42-$C$42)),0) -> 13 | E49: =ROUND(($C$49*(1+$A$73)^(E42-$C$42)),0) -> 13 | F49: =ROUND(($C$49*(1+$A$73)^(F42-$C$42)),0) -> 13 | G49: =ROUND(($C$49*(1+$A$73)^(G42-$C$42)),0) -> 13 | H49: =ROUND(($C$49*(1+$A$73)^(H42-$C$42)),0) -> 13 | I49: =ROUND(($C$49*(1+$A$73)^(I42-$C$42)),0) -> 13 | J49: =ROUND(($C$49*(1+$A$73)^(J42-$C$42)),0) -> 13 | K49: =ROUND(($C$49*(1+$A$73)^(K42-$C$42)),0) -> 13 | ... O49: =ROUND(($C$49*(1+$A$73)^(O42-$C$42)),0) -> 13
B50: 5 a 11 años | C50: =+SUM(Hoja1!H4:N4) -> 51 | D50: =ROUND(($C$50*(1+$A$73)^(D42-$C$42)),0) -> 51 | E50: =ROUND(($C$50*(1+$A$73)^(E42-$C$42)),0) -> 51 | F50: =ROUND(($C$50*(1+$A$73)^(F42-$C$42)),0) -> 51 | G50: =ROUND(($C$50*(1+$A$73)^(G42-$C$42)),0) -> 51 | H50: =ROUND(($C$50*(1+$A$73)^(H42-$C$42)),0) -> 51 | I50: =ROUND(($C$50*(1+$A$73)^(I42-$C$42)),0) -> 51 | J50: =ROUND(($C$50*(1+$A$73)^(J42-$C$42)),0) -> 51 | K50: =ROUND(($C$50*(1+$A$73)^(K42-$C$42)),0) -> 51 | ... O50: =ROUND(($C$50*(1+$A$73)^(O42-$C$42)),0) -> 51
B52: POBLACION SUJETO DE INTERVENCION | C52: PERIODO DE INVERSION | F52: PERIODO DE POST INVERSION
C53: 0 | F53: 1 | G53: 2 | H53: 3 | I53: 4 | J53: 5 | K53: 6 | L53: 7 | M53: 8 | N53: 9 | O53: 10
C54: =+C42 -> 2024 | D54: =+D42 -> 2025 | E54: =+E42 -> 2026 | F54: =+F42 -> 2027 | G54: =+G42 -> 2028 | H54: =+H42 -> 2029 | I54: =+I42 -> 2030 | J54: =+J42 -> 2031 | ... O54: =+O42 -> 2036
B55: ESTIMULACION TEMPRANA (< de 3 años) | C55: =+SUM(C56:C60) -> 43 | D55: =+SUM(D56:D60) -> 43 | E55: =+SUM(E56:E60) -> 43 | F55: =+SUM(F56:F60) -> 43 | G55: =+SUM(G56:G60) -> 43 | H55: =+SUM(H56:H60) -> 43 | I55: =+SUM(I56:I60) -> 43 | J55: =+SUM(J56:J60) -> 43 | ... O55: =+SUM(O56:O60) -> 43
B56: < 29 dias | C56: =+Hoja1!M11 -> 3 | D56: =+ROUND(($C$56*(1+$A$73)^(D54-$C$54)),0) -> 3 | E56: =+ROUND(($C$56*(1+$A$73)^(E54-$C$54)),0) -> 3 | F56: =+ROUND(($C$56*(1+$A$73)^(F54-$C$54)),0) -> 3 | G56: =+ROUND(($C$56*(1+$A$73)^(G54-$C$54)),0) -> 3 | H56: =+ROUND(($C$56*(1+$A$73)^(H54-$C$54)),0) -> 3 | I56: =+ROUND(($C$56*(1+$A$73)^(I54-$C$54)),0) -> 3 | J56: =+ROUND(($C$56*(1+$A$73)^(J54-$C$54)),0) -> 3 | K56: =+ROUND(($C$56*(1+$A$73)^(K54-$C$54)),0) -> 3 | ... O56: =+ROUND(($C$56*(1+$A$73)^(O54-$C$54)),0) -> 3
B57: < 1 año | C57: =+Hoja1!C4 -> 7 | D57: =+ROUND(($C$57*(1+$A$73)^(D54-$C$54)),0) -> 7 | E57: =+ROUND(($C$57*(1+$A$73)^(E54-$C$54)),0) -> 7 | F57: =+ROUND(($C$57*(1+$A$73)^(F54-$C$54)),0) -> 7 | G57: =+ROUND(($C$57*(1+$A$73)^(G54-$C$54)),0) -> 7 | H57: =+ROUND(($C$57*(1+$A$73)^(H54-$C$54)),0) -> 7 | I57: =+ROUND(($C$57*(1+$A$73)^(I54-$C$54)),0) -> 7 | J57: =+ROUND(($C$57*(1+$A$73)^(J54-$C$54)),0) -> 7 | K57: =+ROUND(($C$57*(1+$A$73)^(K54-$C$54)),0) -> 7 | ... O57: =+ROUND(($C$57*(1+$A$73)^(O54-$C$54)),0) -> 7
B58: 1 años | C58: =+Hoja1!D4 -> 5 | D58: =+ROUND(($C$58*(1+$A$73)^(D54-$C$54)),0) -> 5 | E58: =+ROUND(($C$58*(1+$A$73)^(E54-$C$54)),0) -> 5 | F58: =+ROUND(($C$58*(1+$A$73)^(F54-$C$54)),0) -> 5 | G58: =+ROUND(($C$58*(1+$A$73)^(G54-$C$54)),0) -> 5 | H58: =+ROUND(($C$58*(1+$A$73)^(H54-$C$54)),0) -> 5 | I58: =+ROUND(($C$58*(1+$A$73)^(I54-$C$54)),0) -> 5 | J58: =+ROUND(($C$58*(1+$A$73)^(J54-$C$54)),0) -> 5 | K58: =+ROUND(($C$58*(1+$A$73)^(K54-$C$54)),0) -> 5 | ... O58: =+ROUND(($C$58*(1+$A$73)^(O54-$C$54)),0) -> 5
B59: 2 años | C59: =+Hoja1!E4 -> 13 | D59: =+ROUND(($C$59*(1+$A$73)^(D54-$C$54)),0) -> 13 | E59: =+ROUND(($C$59*(1+$A$73)^(E54-$C$54)),0) -> 13 | F59: =+ROUND(($C$59*(1+$A$73)^(F54-$C$54)),0) -> 13 | G59: =+ROUND(($C$59*(1+$A$73)^(G54-$C$54)),0) -> 13 | H59: =+ROUND(($C$59*(1+$A$73)^(H54-$C$54)),0) -> 13 | I59: =+ROUND(($C$59*(1+$A$73)^(I54-$C$54)),0) -> 13 | J59: =+ROUND(($C$59*(1+$A$73)^(J54-$C$54)),0) -> 13 | K59: =+ROUND(($C$59*(1+$A$73)^(K54-$C$54)),0) -> 13 | ... O59: =+ROUND(($C$59*(1+$A$73)^(O54-$C$54)),0) -> 13
B60: 3 años | C60: =+Hoja1!F4 -> 15 | D60: =+ROUND(($C$60*(1+$A$73)^(D54-$C$54)),0) -> 15 | E60: =+ROUND(($C$60*(1+$A$73)^(E54-$C$54)),0) -> 15 | F60: =+ROUND(($C$60*(1+$A$73)^(F54-$C$54)),0) -> 15 | G60: =+ROUND(($C$60*(1+$A$73)^(G54-$C$54)),0) -> 15 | H60: =+ROUND(($C$60*(1+$A$73)^(H54-$C$54)),0) -> 15 | I60: =+ROUND(($C$60*(1+$A$73)^(I54-$C$54)),0) -> 15 | J60: =+ROUND(($C$60*(1+$A$73)^(J54-$C$54)),0) -> 15 | K60: =+ROUND(($C$60*(1+$A$73)^(K54-$C$54)),0) -> 15 | ... O60: =+ROUND(($C$60*(1+$A$73)^(O54-$C$54)),0) -> 15
B62: POBLACION SUJETO DE INTERVENCION | C62: PERIODO DE INVERSION | F62: PERIODO DE POST INVERSION
C63: 0 | F63: 1 | G63: 2 | H63: 3 | I63: 4 | J63: 5 | K63: 6 | L63: 7 | M63: 8 | N63: 9 | O63: 10
C64: 2024 | D64: 2025 | E64: 2026 | F64: 2027 | G64: 2028 | H64: 2029 | I64: 2030 | J64: 2031 | K64: 2032 | L64: 2033 | M64: 2034 | N64: 2035 | O64: 2036
B65: INMUNIZACIONES (< de 4 años, Gestantes) | C65: =+SUM(C66:C71) -> 71 | D65: =+SUM(D66:D71) -> 71 | E65: =+SUM(E66:E71) -> 71 | F65: =+SUM(F66:F71) -> 71 | G65: =+SUM(G66:G71) -> 71 | H65: =+SUM(H66:H71) -> 71 | I65: =+SUM(I66:I71) -> 71 | J65: =+SUM(J66:J71) -> 71 | ... O65: =+SUM(O66:O71) -> 71
B66: < 1 año | C66: =+SUM(Hoja1!C4) -> 7 | D66: =+ROUND(($C$66*(1+$A$73)^(D64-$C$64)),0) -> 7 | E66: =+ROUND(($C$66*(1+$A$73)^(E64-$C$64)),0) -> 7 | F66: =+ROUND(($C$66*(1+$A$73)^(F64-$C$64)),0) -> 7 | G66: =+ROUND(($C$66*(1+$A$73)^(G64-$C$64)),0) -> 7 | H66: =+ROUND(($C$66*(1+$A$73)^(H64-$C$64)),0) -> 7 | I66: =+ROUND(($C$66*(1+$A$73)^(I64-$C$64)),0) -> 7 | J66: =+ROUND(($C$66*(1+$A$73)^(J64-$C$64)),0) -> 7 | K66: =+ROUND(($C$66*(1+$A$73)^(K64-$C$64)),0) -> 7 | ... O66: =+ROUND(($C$66*(1+$A$73)^(O64-$C$64)),0) -> 7
B67: 1 año | C67: =+Hoja1!D4 -> 5 | D67: =+ROUND(($C$67*(1+$A$73)^(D64-$C$64)),0) -> 5 | E67: =+ROUND(($C$67*(1+$A$73)^(E64-$C$64)),0) -> 5 | F67: =+ROUND(($C$67*(1+$A$73)^(F64-$C$64)),0) -> 5 | G67: =+ROUND(($C$67*(1+$A$73)^(G64-$C$64)),0) -> 5 | H67: =+ROUND(($C$67*(1+$A$73)^(H64-$C$64)),0) -> 5 | I67: =+ROUND(($C$67*(1+$A$73)^(I64-$C$64)),0) -> 5 | J67: =+ROUND(($C$67*(1+$A$73)^(J64-$C$64)),0) -> 5 | K67: =+ROUND(($C$67*(1+$A$73)^(K64-$C$64)),0) -> 5 | ... O67: =+ROUND(($C$67*(1+$A$73)^(O64-$C$64)),0) -> 5
B68: 2 años | C68: =+Hoja1!E4 -> 13 | D68: =+ROUND(($C$68*(1+$A$73)^(D64-$C$64)),0) -> 13 | E68: =+ROUND(($C$68*(1+$A$73)^(E64-$C$64)),0) -> 13 | F68: =+ROUND(($C$68*(1+$A$73)^(F64-$C$64)),0) -> 13 | G68: =+ROUND(($C$68*(1+$A$73)^(G64-$C$64)),0) -> 13 | H68: =+ROUND(($C$68*(1+$A$73)^(H64-$C$64)),0) -> 13 | I68: =+ROUND(($C$68*(1+$A$73)^(I64-$C$64)),0) -> 13 | J68: =+ROUND(($C$68*(1+$A$73)^(J64-$C$64)),0) -> 13 | K68: =+ROUND(($C$68*(1+$A$73)^(K64-$C$64)),0) -> 13 | ... O68: =+ROUND(($C$68*(1+$A$73)^(O64-$C$64)),0) -> 13
B69: 3 años | C69: =+Hoja1!F4 -> 15 | D69: =+ROUND(($C$69*(1+$A$73)^(D64-$C$64)),0) -> 15 | E69: =+ROUND(($C$69*(1+$A$73)^(E64-$C$64)),0) -> 15 | F69: =+ROUND(($C$69*(1+$A$73)^(F64-$C$64)),0) -> 15 | G69: =+ROUND(($C$69*(1+$A$73)^(G64-$C$64)),0) -> 15 | H69: =+ROUND(($C$69*(1+$A$73)^(H64-$C$64)),0) -> 15 | I69: =+ROUND(($C$69*(1+$A$73)^(I64-$C$64)),0) -> 15 | J69: =+ROUND(($C$69*(1+$A$73)^(J64-$C$64)),0) -> 15 | K69: =+ROUND(($C$69*(1+$A$73)^(K64-$C$64)),0) -> 15 | ... O69: =+ROUND(($C$69*(1+$A$73)^(O64-$C$64)),0) -> 15
B70: 4 años | C70: =+Hoja1!G4 -> 13 | D70: =+ROUND(($C$70*(1+$A$73)^(D64-$C$64)),0) -> 13 | E70: =+ROUND(($C$70*(1+$A$73)^(E64-$C$64)),0) -> 13 | F70: =+ROUND(($C$70*(1+$A$73)^(F64-$C$64)),0) -> 13 | G70: =+ROUND(($C$70*(1+$A$73)^(G64-$C$64)),0) -> 13 | H70: =+ROUND(($C$70*(1+$A$73)^(H64-$C$64)),0) -> 13 | I70: =+ROUND(($C$70*(1+$A$73)^(I64-$C$64)),0) -> 13 | J70: =+ROUND(($C$70*(1+$A$73)^(J64-$C$64)),0) -> 13 | K70: =+ROUND(($C$70*(1+$A$73)^(K64-$C$64)),0) -> 13 | ... O70: =+ROUND(($C$70*(1+$A$73)^(O64-$C$64)),0) -> 13
B71: Gestantes | C71: =+Hoja1!I11 -> 18 | D71: =+ROUND(($C$71*(1+$A$73)^(D64-$C$64)),0) -> 18 | E71: =+ROUND(($C$71*(1+$A$73)^(E64-$C$64)),0) -> 18 | F71: =+ROUND(($C$71*(1+$A$73)^(F64-$C$64)),0) -> 18 | G71: =+ROUND(($C$71*(1+$A$73)^(G64-$C$64)),0) -> 18 | H71: =+ROUND(($C$71*(1+$A$73)^(H64-$C$64)),0) -> 18 | I71: =+ROUND(($C$71*(1+$A$73)^(I64-$C$64)),0) -> 18 | J71: =+ROUND(($C$71*(1+$A$73)^(J64-$C$64)),0) -> 18 | K71: =+ROUND(($C$71*(1+$A$73)^(K64-$C$64)),0) -> 18 | ... O71: =+ROUND(($C$71*(1+$A$73)^(O64-$C$64)),0) -> 18
A73: =+Hoja3!C8 -> 0.0003 | B73: POBLACION QUE DEMANDA LOS SERVICIOS DE PROMOCION DE LA SALUD
B75: POBLACION SUJETO DE INTERVENCION (PERSONAS EN SUS DIFERENTES ETAPAS DE VIDA) | C75: PERIODO DE INVERSION | F75: PERIODO DE POST INVERSION
C76: 0 | F76: 1 | G76: 2 | H76: 3 | I76: 4 | J76: 5 | K76: 6 | L76: 7 | M76: 8 | N76: 9 | O76: 10
C77: 2024 | D77: 2025 | E77: 2026 | F77: 2027 | G77: 2028 | H77: 2029 | I77: 2030 | J77: 2031 | K77: 2032 | L77: 2033 | M77: 2034 | N77: 2035 | O77: 2036
B78: CONSEJERIA Y PREVENCION DE TBC (> 18 años) | C78: =+SUM(C79:C84) -> 364 | D78: =+SUM(D79:D84) -> 364 | E78: =+SUM(E79:E84) -> 364 | F78: =+SUM(F79:F84) -> 364 | G78: =+SUM(G79:G84) -> 364 | H78: =+SUM(H79:H84) -> 364 | I78: =+SUM(I79:I84) -> 364 | J78: =+SUM(J79:J84) -> 364 | ... O78: =+SUM(O79:O84) -> 364
B79: 18 a 24 Años | C79: =+SUM(Hoja1!U4:W4) -> 54 | D79: =ROUND(($C$79*(1+$A$73)^(D77-$C$77)),0) -> 54 | E79: =ROUND(($C$79*(1+$A$73)^(E77-$C$77)),0) -> 54 | F79: =ROUND(($C$79*(1+$A$73)^(F77-$C$77)),0) -> 54 | G79: =ROUND(($C$79*(1+$A$73)^(G77-$C$77)),0) -> 54 | H79: =ROUND(($C$79*(1+$A$73)^(H77-$C$77)),0) -> 54 | I79: =ROUND(($C$79*(1+$A$73)^(I77-$C$77)),0) -> 54 | J79: =ROUND(($C$79*(1+$A$73)^(J77-$C$77)),0) -> 54 | K79: =ROUND(($C$79*(1+$A$73)^(K77-$C$77)),0) -> 54 | ... O79: =ROUND(($C$79*(1+$A$73)^(O77-$C$77)),0) -> 54
B80: 25 a 34 Años | C80: =+SUM(Hoja1!X4:Y4) -> 87 | D80: =ROUND(($C$80*(1+$A$73)^(D77-$C$77)),0) -> 87 | E80: =ROUND(($C$80*(1+$A$73)^(E77-$C$77)),0) -> 87 | F80: =ROUND(($C$80*(1+$A$73)^(F77-$C$77)),0) -> 87 | G80: =ROUND(($C$80*(1+$A$73)^(G77-$C$77)),0) -> 87 | H80: =ROUND(($C$80*(1+$A$73)^(H77-$C$77)),0) -> 87 | I80: =ROUND(($C$80*(1+$A$73)^(I77-$C$77)),0) -> 87 | J80: =ROUND(($C$80*(1+$A$73)^(J77-$C$77)),0) -> 87 | K80: =ROUND(($C$80*(1+$A$73)^(K77-$C$77)),0) -> 87 | ... O80: =ROUND(($C$80*(1+$A$73)^(O77-$C$77)),0) -> 87
B81: 35 a 44 Años | C81: =+SUM(Hoja1!Z4:AA4) -> 66 | D81: =ROUND(($C$81*(1+$A$73)^(D77-$C$77)),0) -> 66 | E81: =ROUND(($C$81*(1+$A$73)^(E77-$C$77)),0) -> 66 | F81: =ROUND(($C$81*(1+$A$73)^(F77-$C$77)),0) -> 66 | G81: =ROUND(($C$81*(1+$A$73)^(G77-$C$77)),0) -> 66 | H81: =ROUND(($C$81*(1+$A$73)^(H77-$C$77)),0) -> 66 | I81: =ROUND(($C$81*(1+$A$73)^(I77-$C$77)),0) -> 66 | J81: =ROUND(($C$81*(1+$A$73)^(J77-$C$77)),0) -> 66 | K81: =ROUND(($C$81*(1+$A$73)^(K77-$C$77)),0) -> 66 | ... O81: =ROUND(($C$81*(1+$A$73)^(O77-$C$77)),0) -> 66
B82: 45 a 54 Años | C82: =+SUM(Hoja1!AB4:AC4) -> 54 | D82: =ROUND(($C$82*(1+$A$73)^(D77-$C$77)),0) -> 54 | E82: =ROUND(($C$82*(1+$A$73)^(E77-$C$77)),0) -> 54 | F82: =ROUND(($C$82*(1+$A$73)^(F77-$C$77)),0) -> 54 | G82: =ROUND(($C$82*(1+$A$73)^(G77-$C$77)),0) -> 54 | H82: =ROUND(($C$82*(1+$A$73)^(H77-$C$77)),0) -> 54 | I82: =ROUND(($C$82*(1+$A$73)^(I77-$C$77)),0) -> 54 | J82: =ROUND(($C$82*(1+$A$73)^(J77-$C$77)),0) -> 54 | K82: =ROUND(($C$82*(1+$A$73)^(K77-$C$77)),0) -> 54 | ... O82: =ROUND(($C$82*(1+$A$73)^(O77-$C$77)),0) -> 54
B83: 55 a 64 Años | C83: =+SUM(Hoja1!AD4:AE4) -> 46 | D83: =ROUND(($C$83*(1+$A$73)^(D77-$C$77)),0) -> 46 | E83: =ROUND(($C$83*(1+$A$73)^(E77-$C$77)),0) -> 46 | F83: =ROUND(($C$83*(1+$A$73)^(F77-$C$77)),0) -> 46 | G83: =ROUND(($C$83*(1+$A$73)^(G77-$C$77)),0) -> 46 | H83: =ROUND(($C$83*(1+$A$73)^(H77-$C$77)),0) -> 46 | I83: =ROUND(($C$83*(1+$A$73)^(I77-$C$77)),0) -> 46 | J83: =ROUND(($C$83*(1+$A$73)^(J77-$C$77)),0) -> 46 | K83: =ROUND(($C$83*(1+$A$73)^(K77-$C$77)),0) -> 46 | ... O83: =ROUND(($C$83*(1+$A$73)^(O77-$C$77)),0) -> 46
B84: > 65 Años | C84: =+SUM(Hoja1!AF4:AI4) -> 57 | D84: =ROUND(($C$84*(1+$A$73)^(D77-$C$77)),0) -> 57 | E84: =ROUND(($C$84*(1+$A$73)^(E77-$C$77)),0) -> 57 | F84: =ROUND(($C$84*(1+$A$73)^(F77-$C$77)),0) -> 57 | G84: =ROUND(($C$84*(1+$A$73)^(G77-$C$77)),0) -> 57 | H84: =ROUND(($C$84*(1+$A$73)^(H77-$C$77)),0) -> 57 | I84: =ROUND(($C$84*(1+$A$73)^(I77-$C$77)),0) -> 57 | J84: =ROUND(($C$84*(1+$A$73)^(J77-$C$77)),0) -> 57 | K84: =ROUND(($C$84*(1+$A$73)^(K77-$C$77)),0) -> 57 | ... O84: =ROUND(($C$84*(1+$A$73)^(O77-$C$77)),0) -> 57
B87: POBLACION SUJETO DE INTERVENCION (PERSONAS EN SUS DIFERENTES ETAPAS DE VIDA) | C87: PERIODO DE INVERSION | F87: PERIODO DE POST INVERSION
C88: 0 | F88: 1 | G88: 2 | H88: 3 | I88: 4 | J88: 5 | K88: 6 | L88: 7 | M88: 8 | N88: 9 | O88: 10
C89: =+C77 -> 2024 | D89: =+D77 -> 2025 | E89: =+E77 -> 2026 | F89: =+F77 -> 2027 | G89: =+G77 -> 2028 | H89: =+H77 -> 2029 | I89: =+I77 -> 2030 | J89: =+J77 -> 2031 | ... O89: =+O77 -> 2036
B90: CONSEJERIA DE ITS/VIH/SIDA (> 18 años) | C90: =+SUM(C91:C96) -> 364 | D90: =+SUM(D91:D96) -> 364 | E90: =+SUM(E91:E96) -> 364 | F90: =+SUM(F91:F96) -> 364 | G90: =+SUM(G91:G96) -> 364 | H90: =+SUM(H91:H96) -> 364 | I90: =+SUM(I91:I96) -> 364 | J90: =+SUM(J91:J96) -> 364 | ... O90: =+SUM(O91:O96) -> 364
B91: 18 a 24 Años | C91: =+SUM(Hoja1!U4:W4) -> 54 | D91: =ROUND(($C$91*(1+$A$73)^(D89-$C$89)),0) -> 54 | E91: =ROUND(($C$91*(1+$A$73)^(E89-$C$89)),0) -> 54 | F91: =ROUND(($C$91*(1+$A$73)^(F89-$C$89)),0) -> 54 | G91: =ROUND(($C$91*(1+$A$73)^(G89-$C$89)),0) -> 54 | H91: =ROUND(($C$91*(1+$A$73)^(H89-$C$89)),0) -> 54 | I91: =ROUND(($C$91*(1+$A$73)^(I89-$C$89)),0) -> 54 | J91: =ROUND(($C$91*(1+$A$73)^(J89-$C$89)),0) -> 54 | K91: =ROUND(($C$91*(1+$A$73)^(K89-$C$89)),0) -> 54 | ... O91: =ROUND(($C$91*(1+$A$73)^(O89-$C$89)),0) -> 54
B92: 25 a 34 Años | C92: =+SUM(Hoja1!X4:Y4) -> 87 | D92: =ROUND(($C$92*(1+$A$73)^(D89-$C$89)),0) -> 87 | E92: =ROUND(($C$92*(1+$A$73)^(E89-$C$89)),0) -> 87 | F92: =ROUND(($C$92*(1+$A$73)^(F89-$C$89)),0) -> 87 | G92: =ROUND(($C$92*(1+$A$73)^(G89-$C$89)),0) -> 87 | H92: =ROUND(($C$92*(1+$A$73)^(H89-$C$89)),0) -> 87 | I92: =ROUND(($C$92*(1+$A$73)^(I89-$C$89)),0) -> 87 | J92: =ROUND(($C$92*(1+$A$73)^(J89-$C$89)),0) -> 87 | K92: =ROUND(($C$92*(1+$A$73)^(K89-$C$89)),0) -> 87 | ... O92: =ROUND(($C$92*(1+$A$73)^(O89-$C$89)),0) -> 87
B93: 35 a 44 Años | C93: =+SUM(Hoja1!Z4:AA4) -> 66 | D93: =ROUND(($C$93*(1+$A$73)^(D89-$C$89)),0) -> 66 | E93: =ROUND(($C$93*(1+$A$73)^(E89-$C$89)),0) -> 66 | F93: =ROUND(($C$93*(1+$A$73)^(F89-$C$89)),0) -> 66 | G93: =ROUND(($C$93*(1+$A$73)^(G89-$C$89)),0) -> 66 | H93: =ROUND(($C$93*(1+$A$73)^(H89-$C$89)),0) -> 66 | I93: =ROUND(($C$93*(1+$A$73)^(I89-$C$89)),0) -> 66 | J93: =ROUND(($C$93*(1+$A$73)^(J89-$C$89)),0) -> 66 | K93: =ROUND(($C$93*(1+$A$73)^(K89-$C$89)),0) -> 66 | ... O93: =ROUND(($C$93*(1+$A$73)^(O89-$C$89)),0) -> 66
B94: 45 a 54 Años | C94: =+SUM(Hoja1!AB4:AC4) -> 54 | D94: =ROUND(($C$94*(1+$A$73)^(D89-$C$89)),0) -> 54 | E94: =ROUND(($C$94*(1+$A$73)^(E89-$C$89)),0) -> 54 | F94: =ROUND(($C$94*(1+$A$73)^(F89-$C$89)),0) -> 54 | G94: =ROUND(($C$94*(1+$A$73)^(G89-$C$89)),0) -> 54 | H94: =ROUND(($C$94*(1+$A$73)^(H89-$C$89)),0) -> 54 | I94: =ROUND(($C$94*(1+$A$73)^(I89-$C$89)),0) -> 54 | J94: =ROUND(($C$94*(1+$A$73)^(J89-$C$89)),0) -> 54 | K94: =ROUND(($C$94*(1+$A$73)^(K89-$C$89)),0) -> 54 | ... O94: =ROUND(($C$94*(1+$A$73)^(O89-$C$89)),0) -> 54
B95: 55 a 64 Años | C95: =+SUM(Hoja1!AD4:AE4) -> 46 | D95: =ROUND(($C$95*(1+$A$73)^(D89-$C$89)),0) -> 46 | E95: =ROUND(($C$95*(1+$A$73)^(E89-$C$89)),0) -> 46 | F95: =ROUND(($C$95*(1+$A$73)^(F89-$C$89)),0) -> 46 | G95: =ROUND(($C$95*(1+$A$73)^(G89-$C$89)),0) -> 46 | H95: =ROUND(($C$95*(1+$A$73)^(H89-$C$89)),0) -> 46 | I95: =ROUND(($C$95*(1+$A$73)^(I89-$C$89)),0) -> 46 | J95: =ROUND(($C$95*(1+$A$73)^(J89-$C$89)),0) -> 46 | K95: =ROUND(($C$95*(1+$A$73)^(K89-$C$89)),0) -> 46 | ... O95: =ROUND(($C$95*(1+$A$73)^(O89-$C$89)),0) -> 46
B96: > 65 Años | C96: =+SUM(Hoja1!AF4:AI4) -> 57 | D96: =ROUND(($C$96*(1+$A$73)^(D89-$C$89)),0) -> 57 | E96: =ROUND(($C$96*(1+$A$73)^(E89-$C$89)),0) -> 57 | F96: =ROUND(($C$96*(1+$A$73)^(F89-$C$89)),0) -> 57 | G96: =ROUND(($C$96*(1+$A$73)^(G89-$C$89)),0) -> 57 | H96: =ROUND(($C$96*(1+$A$73)^(H89-$C$89)),0) -> 57 | I96: =ROUND(($C$96*(1+$A$73)^(I89-$C$89)),0) -> 57 | J96: =ROUND(($C$96*(1+$A$73)^(J89-$C$89)),0) -> 57 | K96: =ROUND(($C$96*(1+$A$73)^(K89-$C$89)),0) -> 57 | ... O96: =ROUND(($C$96*(1+$A$73)^(O89-$C$89)),0) -> 57
B98: POBLACION SUJETO DE INTERVENCION (PERSONAS EN SUS DIFERENTES ETAPAS DE VIDA) | C98: PERIODO DE INVERSION | F98: PERIODO DE POST INVERSION
C99: 0 | F99: 1 | G99: 2 | H99: 3 | I99: 4 | J99: 5 | K99: 6 | L99: 7 | M99: 8 | N99: 9 | O99: 10
C100: =+C89 -> 2024 | D100: =+D89 -> 2025 | E100: =+E89 -> 2026 | F100: =+F89 -> 2027 | G100: =+G89 -> 2028 | H100: =+H89 -> 2029 | I100: =+I89 -> 2030 | J100: =+J89 -> 2031 | ... O100: =+O89 -> 2036
B101: CONSEJERIA DEL ADOLESCENTE ( 12 a 17 años) | C101: =+SUM(C102:C107) -> 39 | D101: =+SUM(D102:D107) -> 39 | E101: =+SUM(E102:E107) -> 39 | F101: =+SUM(F102:F107) -> 39 | G101: =+SUM(G102:G107) -> 39 | H101: =+SUM(H102:H107) -> 39 | I101: =+SUM(I102:I107) -> 39 | J101: =+SUM(J102:J107) -> 39 | ... O101: =+SUM(O102:O107) -> 39
B102: 12 años | C102: =+Hoja1!O4 -> 7 | D102: =ROUND(($C$102*(1+$A$73)^(D100-$C$100)),0) -> 7 | E102: =ROUND(($C$102*(1+$A$73)^(E100-$C$100)),0) -> 7 | F102: =ROUND(($C$102*(1+$A$73)^(F100-$C$100)),0) -> 7 | G102: =ROUND(($C$102*(1+$A$73)^(G100-$C$100)),0) -> 7 | H102: =ROUND(($C$102*(1+$A$73)^(H100-$C$100)),0) -> 7 | I102: =ROUND(($C$102*(1+$A$73)^(I100-$C$100)),0) -> 7 | J102: =ROUND(($C$102*(1+$A$73)^(J100-$C$100)),0) -> 7 | K102: =ROUND(($C$102*(1+$A$73)^(K100-$C$100)),0) -> 7 | ... O102: =ROUND(($C$102*(1+$A$73)^(O100-$C$100)),0) -> 7
B103: 13 años | C103: =+Hoja1!P4 -> 9 | D103: =ROUND(($C$103*(1+$A$73)^(D100-$C$100)),0) -> 9 | E103: =ROUND(($C$103*(1+$A$73)^(E100-$C$100)),0) -> 9 | F103: =ROUND(($C$103*(1+$A$73)^(F100-$C$100)),0) -> 9 | G103: =ROUND(($C$103*(1+$A$73)^(G100-$C$100)),0) -> 9 | H103: =ROUND(($C$103*(1+$A$73)^(H100-$C$100)),0) -> 9 | I103: =ROUND(($C$103*(1+$A$73)^(I100-$C$100)),0) -> 9 | J103: =ROUND(($C$103*(1+$A$73)^(J100-$C$100)),0) -> 9 | K103: =ROUND(($C$103*(1+$A$73)^(K100-$C$100)),0) -> 9 | ... O103: =ROUND(($C$103*(1+$A$73)^(O100-$C$100)),0) -> 9
B104: 14 años | C104: =+Hoja1!Q4 -> 7 | D104: =ROUND(($C$104*(1+$A$73)^(D100-$C$100)),0) -> 7 | E104: =ROUND(($C$104*(1+$A$73)^(E100-$C$100)),0) -> 7 | F104: =ROUND(($C$104*(1+$A$73)^(F100-$C$100)),0) -> 7 | G104: =ROUND(($C$104*(1+$A$73)^(G100-$C$100)),0) -> 7 | H104: =ROUND(($C$104*(1+$A$73)^(H100-$C$100)),0) -> 7 | I104: =ROUND(($C$104*(1+$A$73)^(I100-$C$100)),0) -> 7 | J104: =ROUND(($C$104*(1+$A$73)^(J100-$C$100)),0) -> 7 | K104: =ROUND(($C$104*(1+$A$73)^(K100-$C$100)),0) -> 7 | ... O104: =ROUND(($C$104*(1+$A$73)^(O100-$C$100)),0) -> 7
B105: 15 años | C105: =+Hoja1!R4 -> 5 | D105: =ROUND(($C$105*(1+$A$73)^(D100-$C$100)),0) -> 5 | E105: =ROUND(($C$105*(1+$A$73)^(E100-$C$100)),0) -> 5 | F105: =ROUND(($C$105*(1+$A$73)^(F100-$C$100)),0) -> 5 | G105: =ROUND(($C$105*(1+$A$73)^(G100-$C$100)),0) -> 5 | H105: =ROUND(($C$105*(1+$A$73)^(H100-$C$100)),0) -> 5 | I105: =ROUND(($C$105*(1+$A$73)^(I100-$C$100)),0) -> 5 | J105: =ROUND(($C$105*(1+$A$73)^(J100-$C$100)),0) -> 5 | K105: =ROUND(($C$105*(1+$A$73)^(K100-$C$100)),0) -> 5 | ... O105: =ROUND(($C$105*(1+$A$73)^(O100-$C$100)),0) -> 5
B106: 16 años | C106: =+Hoja1!S4 -> 6 | D106: =ROUND(($C$106*(1+$A$73)^(D100-$C$100)),0) -> 6 | E106: =ROUND(($C$106*(1+$A$73)^(E100-$C$100)),0) -> 6 | F106: =ROUND(($C$106*(1+$A$73)^(F100-$C$100)),0) -> 6 | G106: =ROUND(($C$106*(1+$A$73)^(G100-$C$100)),0) -> 6 | H106: =ROUND(($C$106*(1+$A$73)^(H100-$C$100)),0) -> 6 | I106: =ROUND(($C$106*(1+$A$73)^(I100-$C$100)),0) -> 6 | J106: =ROUND(($C$106*(1+$A$73)^(J100-$C$100)),0) -> 6 | K106: =ROUND(($C$106*(1+$A$73)^(K100-$C$100)),0) -> 6 | ... O106: =ROUND(($C$106*(1+$A$73)^(O100-$C$100)),0) -> 6
B107: 17 años | C107: =+Hoja1!T4 -> 5 | D107: =ROUND(($C$107*(1+$A$73)^(D100-$C$100)),0) -> 5 | E107: =ROUND(($C$107*(1+$A$73)^(E100-$C$100)),0) -> 5 | F107: =ROUND(($C$107*(1+$A$73)^(F100-$C$100)),0) -> 5 | G107: =ROUND(($C$107*(1+$A$73)^(G100-$C$100)),0) -> 5 | H107: =ROUND(($C$107*(1+$A$73)^(H100-$C$100)),0) -> 5 | I107: =ROUND(($C$107*(1+$A$73)^(I100-$C$100)),0) -> 5 | J107: =ROUND(($C$107*(1+$A$73)^(J100-$C$100)),0) -> 5 | K107: =ROUND(($C$107*(1+$A$73)^(K100-$C$100)),0) -> 5 | ... O107: =ROUND(($C$107*(1+$A$73)^(O100-$C$100)),0) -> 5
B109: POBLACION SUJETO DE INTERVENCION | C109: POBLACION ASIGNADA 2019 AÑO DE INVERSION | E109: PERIODO DE INVERSION | F109: PERIODO DE POST INVERSION
C110: 0 | F110: 1 | G110: 2 | H110: 3 | I110: 4 | J110: 5 | K110: 6 | L110: 7 | M110: 8 | N110: 9 | O110: 10
C111: 2024 | D111: 2025 | E111: 2026 | F111: 2027 | G111: 2028 | H111: 2029 | I111: 2030 | J111: 2031 | K111: 2032 | L111: 2033 | M111: 2034 | N111: 2035 | O111: 2036
B112: ADULTO MAYOR (> 18 años) | C112: =SUM(C113:C118) -> 364 | D112: =SUM(D113:D118) -> 364 | E112: =SUM(E113:E118) -> 364 | F112: =SUM(F113:F118) -> 364 | G112: =SUM(G113:G118) -> 364 | H112: =SUM(H113:H118) -> 364 | I112: =SUM(I113:I118) -> 364 | J112: =SUM(J113:J118) -> 364 | ... O112: =SUM(O113:O118) -> 364
B113: 18 a 24 Años | C113: =+SUM(Hoja1!U4:W4) -> 54 | D113: =+ROUND(($C$113*(1+$A$73)^(D111-$C$111)),0) -> 54 | E113: =+ROUND(($C$113*(1+$A$73)^(E111-$C$111)),0) -> 54 | F113: =+ROUND(($C$113*(1+$A$73)^(F111-$C$111)),0) -> 54 | G113: =+ROUND(($C$113*(1+$A$73)^(G111-$C$111)),0) -> 54 | H113: =+ROUND(($C$113*(1+$A$73)^(H111-$C$111)),0) -> 54 | I113: =+ROUND(($C$113*(1+$A$73)^(I111-$C$111)),0) -> 54 | J113: =+ROUND(($C$113*(1+$A$73)^(J111-$C$111)),0) -> 54 | K113: =+ROUND(($C$113*(1+$A$73)^(K111-$C$111)),0) -> 54 | ... O113: =+ROUND(($C$113*(1+$A$73)^(O111-$C$111)),0) -> 54
B114: 25 a 34 Años | C114: =+SUM(Hoja1!X4:Y4) -> 87 | D114: =+ROUND(($C$114*(1+$A$73)^(D111-$C$111)),0) -> 87 | E114: =+ROUND(($C$114*(1+$A$73)^(E111-$C$111)),0) -> 87 | F114: =+ROUND(($C$114*(1+$A$73)^(F111-$C$111)),0) -> 87 | G114: =+ROUND(($C$114*(1+$A$73)^(G111-$C$111)),0) -> 87 | H114: =+ROUND(($C$114*(1+$A$73)^(H111-$C$111)),0) -> 87 | I114: =+ROUND(($C$114*(1+$A$73)^(I111-$C$111)),0) -> 87 | J114: =+ROUND(($C$114*(1+$A$73)^(J111-$C$111)),0) -> 87 | K114: =+ROUND(($C$114*(1+$A$73)^(K111-$C$111)),0) -> 87 | ... O114: =+ROUND(($C$114*(1+$A$73)^(O111-$C$111)),0) -> 87
B115: 35 a 44 Años | C115: =+SUM(Hoja1!Z4:AA4) -> 66 | D115: =+ROUND(($C$115*(1+$A$73)^(D111-$C$111)),0) -> 66 | E115: =+ROUND(($C$115*(1+$A$73)^(E111-$C$111)),0) -> 66 | F115: =+ROUND(($C$115*(1+$A$73)^(F111-$C$111)),0) -> 66 | G115: =+ROUND(($C$115*(1+$A$73)^(G111-$C$111)),0) -> 66 | H115: =+ROUND(($C$115*(1+$A$73)^(H111-$C$111)),0) -> 66 | I115: =+ROUND(($C$115*(1+$A$73)^(I111-$C$111)),0) -> 66 | J115: =+ROUND(($C$115*(1+$A$73)^(J111-$C$111)),0) -> 66 | K115: =+ROUND(($C$115*(1+$A$73)^(K111-$C$111)),0) -> 66 | ... O115: =+ROUND(($C$115*(1+$A$73)^(O111-$C$111)),0) -> 66
B116: 45 a 54 Años | C116: =+SUM(Hoja1!AB4:AC4) -> 54 | D116: =+ROUND(($C$116*(1+$A$73)^(D111-$C$111)),0) -> 54 | E116: =+ROUND(($C$116*(1+$A$73)^(E111-$C$111)),0) -> 54 | F116: =+ROUND(($C$116*(1+$A$73)^(F111-$C$111)),0) -> 54 | G116: =+ROUND(($C$116*(1+$A$73)^(G111-$C$111)),0) -> 54 | H116: =+ROUND(($C$116*(1+$A$73)^(H111-$C$111)),0) -> 54 | I116: =+ROUND(($C$116*(1+$A$73)^(I111-$C$111)),0) -> 54 | J116: =+ROUND(($C$116*(1+$A$73)^(J111-$C$111)),0) -> 54 | K116: =+ROUND(($C$116*(1+$A$73)^(K111-$C$111)),0) -> 54 | ... O116: =+ROUND(($C$116*(1+$A$73)^(O111-$C$111)),0) -> 54
B117: 55 a 64 Años | C117: =+SUM(Hoja1!AD4:AE4) -> 46 | D117: =+ROUND(($C$117*(1+$A$73)^(D111-$C$111)),0) -> 46 | E117: =+ROUND(($C$117*(1+$A$73)^(E111-$C$111)),0) -> 46 | F117: =+ROUND(($C$117*(1+$A$73)^(F111-$C$111)),0) -> 46 | G117: =+ROUND(($C$117*(1+$A$73)^(G111-$C$111)),0) -> 46 | H117: =+ROUND(($C$117*(1+$A$73)^(H111-$C$111)),0) -> 46 | I117: =+ROUND(($C$117*(1+$A$73)^(I111-$C$111)),0) -> 46 | J117: =+ROUND(($C$117*(1+$A$73)^(J111-$C$111)),0) -> 46 | K117: =+ROUND(($C$117*(1+$A$73)^(K111-$C$111)),0) -> 46 | ... O117: =+ROUND(($C$117*(1+$A$73)^(O111-$C$111)),0) -> 46
B118: > 65 Años | C118: =+SUM(Hoja1!AF4:AI4) -> 57 | D118: =+ROUND(($C$118*(1+$A$73)^(D111-$C$111)),0) -> 57 | E118: =+ROUND(($C$118*(1+$A$73)^(E111-$C$111)),0) -> 57 | F118: =+ROUND(($C$118*(1+$A$73)^(F111-$C$111)),0) -> 57 | G118: =+ROUND(($C$118*(1+$A$73)^(G111-$C$111)),0) -> 57 | H118: =+ROUND(($C$118*(1+$A$73)^(H111-$C$111)),0) -> 57 | I118: =+ROUND(($C$118*(1+$A$73)^(I111-$C$111)),0) -> 57 | J118: =+ROUND(($C$118*(1+$A$73)^(J111-$C$111)),0) -> 57 | K118: =+ROUND(($C$118*(1+$A$73)^(K111-$C$111)),0) -> 57 | ... O118: =+ROUND(($C$118*(1+$A$73)^(O111-$C$111)),0) -> 57
B120: POBLACION SUJETO DE INTERVENCION (PERSONAS EN SUS DIFERENTES ETAPAS DE VIDA) | C120: PERIODO DE INVERSION | F120: PERIODO DE POST INVERSION
C121: 0 | F121: 1 | G121: 2 | H121: 3 | I121: 4 | J121: 5 | K121: 6 | L121: 7 | M121: 8 | N121: 9 | O121: 10
C122: =+C100 -> 2024 | D122: =+D100 -> 2025 | E122: =+E100 -> 2026 | F122: =+F100 -> 2027 | G122: =+G100 -> 2028 | H122: =+H100 -> 2029 | I122: =+I100 -> 2030 | J122: =+J100 -> 2031 | ... O122: =+O100 -> 2036
B123: CONSEJERIA Y PREVENCION DE ENFERMEDADES NO TRASMISIBLES (> 18 años) | C123: =+SUM(C124:C129) -> 364 | D123: =+SUM(D124:D129) -> 364 | E123: =+SUM(E124:E129) -> 364 | F123: =+SUM(F124:F129) -> 364 | G123: =+SUM(G124:G129) -> 364 | H123: =+SUM(H124:H129) -> 364 | I123: =+SUM(I124:I129) -> 364 | J123: =+SUM(J124:J129) -> 364 | ... O123: =+SUM(O124:O129) -> 364
B124: 18 a 24 Años | C124: =+SUM(Hoja1!U4:W4) -> 54 | D124: =+ROUND(($C$124*(1+$A$73)^(D122-$C$122)),0) -> 54 | E124: =+ROUND(($C$124*(1+$A$73)^(E122-$C$122)),0) -> 54 | F124: =+ROUND(($C$124*(1+$A$73)^(F122-$C$122)),0) -> 54 | G124: =+ROUND(($C$124*(1+$A$73)^(G122-$C$122)),0) -> 54 | H124: =+ROUND(($C$124*(1+$A$73)^(H122-$C$122)),0) -> 54 | I124: =+ROUND(($C$124*(1+$A$73)^(I122-$C$122)),0) -> 54 | J124: =+ROUND(($C$124*(1+$A$73)^(J122-$C$122)),0) -> 54 | K124: =+ROUND(($C$124*(1+$A$73)^(K122-$C$122)),0) -> 54 | ... O124: =+ROUND(($C$124*(1+$A$73)^(O122-$C$122)),0) -> 54
...

Sheet POBLACION DEMANDANTE POTENCIAL
C1: POBLACION DE REFERENCIA
C2: Poblacion de referencia: Consultorio de medicina general (Numero de personas de 0 a 85 años a mas) en el año 2024 | D2: 507 x 48 % = | E2: =507*48% -> 243.36
C3: Poblacion demandante potencial: Teleconsultamedica (Numero de personas de 0 a 85 años a mas) en el año 2024 | D3: 507 x 48% = | E3: =507*48% -> 243.36
C4: Poblacion demandante potencial: Consultorio CRED (Numero de niños menores de 11 años)en el año 2024 | D4: 107 x 100% = | E4: 107
C5: Poblacion demandante potencial: Estimulacion temprana (Numero de niños menores de 3 años) en el año 2024 | D5: 43 x 100 % = | E5: 43
C6: Poblacion demandante potencial: Inmunizaciones (Menores de 4 años, gestantes) en el año 2024 | D6: 71 x 100% = | E6: 71
C7: Poblacion demandante potencial: Prevencion y consejeria de TBC (Mayores a 18 a 85 años a mas) en el año 2024 | D7: 364 * 100% = | E7: 364
C8: Poblacion demandante potencial: Consejeria y prevencion de ITS, VIH y SIDA (mayores a 18 años) en el año 2024 | D8: 364 * 100% = | E8: 364
C9: Poblacion demandante potencial: Atencíon integral y consejeria del Adolescente en el año 2024 | D9: 39 * 100% = | E9: 39
C10: Poblacion demandante potencial: Atencíon integral del Adulto Mayor en el año 2024 | D10: 364 x 100% = | E10: 364
C11: Poblacion demandante potencial: Consejería y prevención de Enf. No Transmisibles (mayores a 18 años) en el año 2024 | D11: 364 x 100% = | E11: 364
C12: Poblacion demandante potencial: Control Prenatal + 1/2 S.H (gestantes) en el año 2024 | D12: 18 x 100% = | E12: 18
C13: Poblacion demandante potencial: Planificacíon Familiar (MEF DE 15 a 49 años) en el año 2024 | D13: 252 x 100% = | E13: 252
C14: Poblacion demandante potencial: Consejería y prevención del Cáncer (mayores a 18 años) en el año 2024 | D14: 364 x 100% = | E14: 364
C15: Poblacion demandante potencial: Psicoprofilaxis (gestantes) en el año 2024 | D15: 18 x 100% = | E15: 18
C16: Poblacion demandante potencial: Consultorio de odontologia general con soporte de radiografia (4 a 85 años a mas) en el año 2024 | D16: 467 x 48% = | E16: =467*48% -> 224.16
C17: Poblacion demandante potencial: Consultorio de psicologia (de 3 a 85 años a mas) en el año 2024 | D17: 482 x 100% | E17: 482
C18: Poblacion demandante potencial: Urgencias y emergencias (de 0 a 85 años a mas) en el año 2024 | D18: 507 x 48% = | E18: =507*48% -> 243.36
C19: Poblacion demandante potencial: Sala de observacion de emergencia (de 0 a 85 años a mas) en el año 2024 | D19: 507 x 48% = | E19: =507*48% -> 243.36
C20: Poblacion demandante potencial: Laboratorio (0 a 85 años a mas) en el año 2024 | D20: 507 x 48% = | E20: =507*48% -> 243.36
C21: Poblacion demandante potencial: Ecografia (0 a 85 años a mas) en el año 2024 | D21: 507 x 48% = | E21: =507*48% -> 243.36
C22: Poblacion demandante potencial: Radiografia (0 a 85 años a mas) en el año 2024 | D22: 507 x 48% = | E22: =507*48% -> 243.36
C23: Poblacion demandante potencial: Farmacia (0 a 85 años a mas) en el año 2024 | D23: 507 x 48% = | E23: =507*48% -> 243.36
C24: Poblacion demandante potencial: Desinfeccion y esterilizacion (0 a 85 años a mas) en el año 2024 | D24: 507 x 100% = | E24: 507
C28: POBLACION SUJETO DE INTERVENCION (PERSONAS EN SUS DIFERENTES ETAPAS DE VIDA) | D28: PERIODO DE INVERSION | G28: PERIODO DE POST INVERSION
D29: 0 | G29: 1 | H29: 2 | I29: 3 | J29: 4 | K29: 5 | L29: 6 | M29: 7 | N29: 8 | O29: 9 | P29: 10
D30: 2024 | E30: 2025 | F30: 2026 | G30: 2027 | H30: 2028 | I30: 2029 | J30: 2030 | K30: 2031 | L30: 2032 | M30: 2033 | N30: 2034 | O30: 2035 | P30: 2036
C31: Medicina General | D31: =+'POBLACION DE REFERENCIA'!C31 -> 507 | E31: =+'POBLACION DE REFERENCIA'!D31 -> 507 | F31: =+'POBLACION DE REFERENCIA'!E31 -> 507 | G31: =+'POBLACION DE REFERENCIA'!F31 -> 507 | H31: =+'POBLACION DE REFERENCIA'!G31 -> 508 | I31: =+'POBLACION DE REFERENCIA'!H31 -> 508 | J31: =+'POBLACION DE REFERENCIA'!I31 -> 508 | K31: =+'POBLACION DE REFERENCIA'!J31 -> 508 | ... P31: =+'POBLACION DE REFERENCIA'!O31 -> 509
C32: 0 a 85 años a mas | D32: =+'POBLACION DE REFERENCIA'!C32*48% -> 243.36 | E32: =ROUND(($D$32*(1+$A$73)^(E30-$D$30)),0) -> 243 | F32: =ROUND(($D$32*(1+$A$73)^(F30-$D$30)),0) -> 244 | G32: =ROUND(($D$32*(1+$A$73)^(G30-$D$30)),0) -> 244 | H32: =ROUND(($D$32*(1+$A$73)^(H30-$D$30)),0) -> 244 | I32: =ROUND(($D$32*(1+$A$73)^(I30-$D$30)),0) -> 244 | J32: =ROUND(($D$32*(1+$A$73)^(J30-$D$30)),0) -> 244 | K32: =ROUND(($D$32*(1+$A$73)^(K30-$D$30)),0) -> 244 | L32: =ROUND(($D$32*(1+$A$73)^(L30-$D$30)),0) -> 244 | ... P32: =ROUND(($D$32*(1+$A$73)^(P30-$D$30)),0) -> 244
C34: POBLACION SUJETO DE INTERVENCION (PERSONAS EN SUS DIFERENTES ETAPAS DE VIDA) | D34: PERIODO DE INVERSION | G34: PERIODO DE POST INVERSION
D35: 0 | G35: 1 | H35: 2 | I35: 3 | J35: 4 | K35: 5 | L35: 6 | M35: 7 | N35: 8 | O35: 9 | P35: 10
D36: 2024 | E36: 2025 | F36: 2026 | G36: 2027 | H36: 2028 | I36: 2029 | J36: 2030 | K36: 2031 | L36: 2032 | M36: 2033 | N36: 2034 | O36: 2035 | P36: 2036
C37: Teleconsulta medica | D37: =+D38 -> 243.36 | E37: =+E38 -> 243 | F37: =+F38 -> 244 | G37: =+G38 -> 244 | H37: =+H38 -> 244 | I37: =+I38 -> 244 | J37: =+J38 -> 244 | K37: =+K38 -> 244 | ... P37: =+P38 -> 244
C38: 0 a 85 años a mas | D38: =+'POBLACION DE REFERENCIA'!C38*48% -> 243.36 | E38: =ROUND(($D$38*(1+$A$73)^(E36-$D$36)),0) -> 243 | F38: =ROUND(($D$38*(1+$A$73)^(F36-$D$36)),0) -> 244 | G38: =ROUND(($D$38*(1+$A$73)^(G36-$D$36)),0) -> 244 | H38: =ROUND(($D$38*(1+$A$73)^(H36-$D$36)),0) -> 244 | I38: =ROUND(($D$38*(1+$A$73)^(I36-$D$36)),0) -> 244 | J38: =ROUND(($D$38*(1+$A$73)^(J36-$D$36)),0) -> 244 | K38: =ROUND(($D$38*(1+$A$73)^(K36-$D$36)),0) -> 244 | L38: =ROUND(($D$38*(1+$A$73)^(L36-$D$36)),0) -> 244 | ... P38: =ROUND(($D$38*(1+$A$73)^(P36-$D$36)),0) -> 244
C40: POBLACION SUJETO DE INTERVENCION | D40: PERIODO DE INVERSION | G40: PERIODO DE POST INVERSION
D41: 0 | G41: 1 | H41: 2 | I41: 3 | J41: 4 | K41: 5 | L41: 6 | M41: 7 | N41: 8 | O41: 9 | P41: 10
D42: =+D36 -> 2024 | E42: =+E36 -> 2025 | F42: =+F36 -> 2026 | G42: =+G36 -> 2027 | H42: =+H36 -> 2028 | I42: =+I36 -> 2029 | J42: =+J36 -> 2030 | K42: =+K36 -> 2031 | ... P42: =+P36 -> 2036
C43: CRED (< de 11 años) | D43: =+SUM(D44:D50) -> 107 | E43: =+SUM(E44:E50) -> 107 | F43: =+SUM(F44:F50) -> 107 | G43: =+SUM(G44:G50) -> 107 | H43: =+SUM(H44:H50) -> 107 | I43: =+SUM(I44:I50) -> 107 | J43: =+SUM(J44:J50) -> 107 | K43: =+SUM(K44:K50) -> 107 | ... P43: =+SUM(P44:P50) -> 107
C44: < de 29 dias | D44: =+'POBLACION DE REFERENCIA'!C44 -> 3 | E44: =+'POBLACION DE REFERENCIA'!D44 -> 3 | F44: =+'POBLACION DE REFERENCIA'!E44 -> 3 | G44: =+'POBLACION DE REFERENCIA'!F44 -> 3 | H44: =+'POBLACION DE REFERENCIA'!G44 -> 3 | I44: =+'POBLACION DE REFERENCIA'!H44 -> 3 | J44: =+'POBLACION DE REFERENCIA'!I44 -> 3 | K44: =+'POBLACION DE REFERENCIA'!J44 -> 3 | ... P44: =+'POBLACION DE REFERENCIA'!O44 -> 3
C45: < de 1 año | D45: =+'POBLACION DE REFERENCIA'!C45 -> 7 | E45: =+'POBLACION DE REFERENCIA'!D45 -> 7 | F45: =+'POBLACION DE REFERENCIA'!E45 -> 7 | G45: =+'POBLACION DE REFERENCIA'!F45 -> 7 | H45: =+'POBLACION DE REFERENCIA'!G45 -> 7 | I45: =+'POBLACION DE REFERENCIA'!H45 -> 7 | J45: =+'POBLACION DE REFERENCIA'!I45 -> 7 | K45: =+'POBLACION DE REFERENCIA'!J45 -> 7 | ... P45: =+'POBLACION DE REFERENCIA'!O45 -> 7
C46: 1 año | D46: =+'POBLACION DE REFERENCIA'!C46 -> 5 | E46: =+'POBLACION DE REFERENCIA'!D46 -> 5 | F46: =+'POBLACION DE REFERENCIA'!E46 -> 5 | G46: =+'POBLACION DE REFERENCIA'!F46 -> 5 | H46: =+'POBLACION DE REFERENCIA'!G46 -> 5 | I46: =+'POBLACION DE REFERENCIA'!H46 -> 5 | J46: =+'POBLACION DE REFERENCIA'!I46 -> 5 | K46: =+'POBLACION DE REFERENCIA'!J46 -> 5 | ... P46: =+'POBLACION DE REFERENCIA'!O46 -> 5
C47: 2 años | D47: =+'POBLACION DE REFERENCIA'!C47 -> 13 | E47: =+'POBLACION DE REFERENCIA'!D47 -> 13 | F47: =+'POBLACION DE REFERENCIA'!E47 -> 13 | G47: =+'POBLACION DE REFERENCIA'!F47 -> 13 | H47: =+'POBLACION DE REFERENCIA'!G47 -> 13 | I47: =+'POBLACION DE REFERENCIA'!H47 -> 13 | J47: =+'POBLACION DE REFERENCIA'!I47 -> 13 | K47: =+'POBLACION DE REFERENCIA'!J47 -> 13 | ... P47: =+'POBLACION DE REFERENCIA'!O47 -> 13
C48: 3 años | D48: =+'POBLACION DE REFERENCIA'!C48 -> 15 | E48: =+'POBLACION DE REFERENCIA'!D48 -> 15 | F48: =+'POBLACION DE REFERENCIA'!E48 -> 15 | G48: =+'POBLACION DE REFERENCIA'!F48 -> 15 | H48: =+'POBLACION DE REFERENCIA'!G48 -> 15 | I48: =+'POBLACION DE REFERENCIA'!H48 -> 15 | J48: =+'POBLACION DE REFERENCIA'!I48 -> 15 | K48: =+'POBLACION DE REFERENCIA'!J48 -> 15 | ... P48: =+'POBLACION DE REFERENCIA'!O48 -> 15
C49: 4 años | D49: =+'POBLACION DE REFERENCIA'!C49 -> 13 | E49: =+'POBLACION DE REFERENCIA'!D49 -> 13 | F49: =+'POBLACION DE REFERENCIA'!E49 -> 13 | G49: =+'POBLACION DE REFERENCIA'!F49 -> 13 | H49: =+'POBLACION DE REFERENCIA'!G49 -> 13 | I49: =+'POBLACION DE REFERENCIA'!H49 -> 13 | J49: =+'POBLACION DE REFERENCIA'!I49 -> 13 | K49: =+'POBLACION DE REFERENCIA'!J49 -> 13 | ... P49: =+'POBLACION DE REFERENCIA'!O49 -> 13
C50: 5 a 11 años | D50: =+'POBLACION DE REFERENCIA'!C50 -> 51 | E50: =+'POBLACION DE REFERENCIA'!D50 -> 51 | F50: =+'POBLACION DE REFERENCIA'!E50 -> 51 | G50: =+'POBLACION DE REFERENCIA'!F50 -> 51 | H50: =+'POBLACION DE REFERENCIA'!G50 -> 51 | I50: =+'POBLACION DE REFERENCIA'!H50 -> 51 | J50: =+'POBLACION DE REFERENCIA'!I50 -> 51 | K50: =+'POBLACION DE REFERENCIA'!J50 -> 51 | ... P50: =+'POBLACION DE REFERENCIA'!O50 -> 51
C52: POBLACION SUJETO DE INTERVENCION | D52: PERIODO DE INVERSION | G52: PERIODO DE POST INVERSION
D53: 0 | G53: 1 | H53: 2 | I53: 3 | J53: 4 | K53: 5 | L53: 6 | M53: 7 | N53: 8 | O53: 9 | P53: 10
D54: =+D42 -> 2024 | E54: =+E42 -> 2025 | F54: =+F42 -> 2026 | G54: =+G42 -> 2027 | H54: =+H42 -> 2028 | I54: =+I42 -> 2029 | J54: =+J42 -> 2030 | K54: =+K42 -> 2031 | ... P54: =+P42 -> 2036
C55: ESTIMULACION TEMPRANA (< de 3 años) | D55: =+SUM(D56:D60) -> 43 | E55: =+SUM(E56:E60) -> 43 | F55: =+SUM(F56:F60) -> 43 | G55: =+SUM(G56:G60) -> 43 | H55: =+SUM(H56:H60) -> 43 | I55: =+SUM(I56:I60) -> 43 | J55: =+SUM(J56:J60) -> 43 | K55: =+SUM(K56:K60) -> 43 | ... P55: =+SUM(P56:P60) -> 43
C56: < 29 dias | D56: =+'POBLACION DE REFERENCIA'!C56 -> 3 | E56: =+'POBLACION DE REFERENCIA'!D56 -> 3 | F56: =+'POBLACION DE REFERENCIA'!E56 -> 3 | G56: =+'POBLACION DE REFERENCIA'!F56 -> 3 | H56: =+'POBLACION DE REFERENCIA'!G56 -> 3 | I56: =+'POBLACION DE REFERENCIA'!H56 -> 3 | J56: =+'POBLACION DE REFERENCIA'!I56 -> 3 | K56: =+'POBLACION DE REFERENCIA'!J56 -> 3 | ... P56: =+'POBLACION DE REFERENCIA'!O56 -> 3
C57: < 1 año | D57: =+'POBLACION DE REFERENCIA'!C57 -> 7 | E57: =+'POBLACION DE REFERENCIA'!D57 -> 7 | F57: =+'POBLACION DE REFERENCIA'!E57 -> 7 | G57: =+'POBLACION DE REFERENCIA'!F57 -> 7 | H57: =+'POBLACION DE REFERENCIA'!G57 -> 7 | I57: =+'POBLACION DE REFERENCIA'!H57 -> 7 | J57: =+'POBLACION DE REFERENCIA'!I57 -> 7 | K57: =+'POBLACION DE REFERENCIA'!J57 -> 7 | ... P57: =+'POBLACION DE REFERENCIA'!O57 -> 7
C58: 1 años | D58: =+'POBLACION DE REFERENCIA'!C58 -> 5 | E58: =+'POBLACION DE REFERENCIA'!D58 -> 5 | F58: =+'POBLACION DE REFERENCIA'!E58 -> 5 | G58: =+'POBLACION DE REFERENCIA'!F58 -> 5 | H58: =+'POBLACION DE REFERENCIA'!G58 -> 5 | I58: =+'POBLACION DE REFERENCIA'!H58 -> 5 | J58: =+'POBLACION DE REFERENCIA'!I58 -> 5 | K58: =+'POBLACION DE REFERENCIA'!J58 -> 5 | ... P58: =+'POBLACION DE REFERENCIA'!O58 -> 5
C59: 2 años | D59: =+'POBLACION DE REFERENCIA'!C59 -> 13 | E59: =+'POBLACION DE REFERENCIA'!D59 -> 13 | F59: =+'POBLACION DE REFERENCIA'!E59 -> 13 | G59: =+'POBLACION DE REFERENCIA'!F59 -> 13 | H59: =+'POBLACION DE REFERENCIA'!G59 -> 13 | I59: =+'POBLACION DE REFERENCIA'!H59 -> 13 | J59: =+'POBLACION DE REFERENCIA'!I59 -> 13 | K59: =+'POBLACION DE REFERENCIA'!J59 -> 13 | ... P59: =+'POBLACION DE REFERENCIA'!O59 -> 13
C60: 3 años | D60: =+'POBLACION DE REFERENCIA'!C60 -> 15 | E60: =+'POBLACION DE REFERENCIA'!D60 -> 15 | F60: =+'POBLACION DE REFERENCIA'!E60 -> 15 | G60: =+'POBLACION DE REFERENCIA'!F60 -> 15 | H60: =+'POBLACION DE REFERENCIA'!G60 -> 15 | I60: =+'POBLACION DE REFERENCIA'!H60 -> 15 | J60: =+'POBLACION DE REFERENCIA'!I60 -> 15 | K60: =+'POBLACION DE REFERENCIA'!J60 -> 15 | ... P60: =+'POBLACION DE REFERENCIA'!O60 -> 15
C62: POBLACION SUJETO DE INTERVENCION | D62: PERIODO DE INVERSION | G62: PERIODO DE POST INVERSION
D63: 0 | G63: 1 | H63: 2 | I63: 3 | J63: 4 | K63: 5 | L63: 6 | M63: 7 | N63: 8 | O63: 9 | P63: 10
D64: 2024 | E64: 2025 | F64: 2026 | G64: 2027 | H64: 2028 | I64: 2029 | J64: 2030 | K64: 2031 | L64: 2032 | M64: 2033 | N64: 2034 | O64: 2035 | P64: 2036
C65: INMUNIZACIONES (< de 4 años, Gestantes) | D65: =+SUM(D66:D71) -> 71 | E65: =+SUM(E66:E71) -> 71 | F65: =+SUM(F66:F71) -> 71 | G65: =+SUM(G66:G71) -> 71 | H65: =+SUM(H66:H71) -> 71 | I65: =+SUM(I66:I71) -> 71 | J65: =+SUM(J66:J71) -> 71 | K65: =+SUM(K66:K71) -> 71 | ... P65: =+SUM(P66:P71) -> 71
C66: < 1 año | D66: =+'POBLACION DE REFERENCIA'!C66 -> 7 | E66: =+'POBLACION DE REFERENCIA'!D66 -> 7 | F66: =+'POBLACION DE REFERENCIA'!E66 -> 7 | G66: =+'POBLACION DE REFERENCIA'!F66 -> 7 | H66: =+'POBLACION DE REFERENCIA'!G66 -> 7 | I66: =+'POBLACION DE REFERENCIA'!H66 -> 7 | J66: =+'POBLACION DE REFERENCIA'!I66 -> 7 | K66: =+'POBLACION DE REFERENCIA'!J66 -> 7 | ... P66: =+'POBLACION DE REFERENCIA'!O66 -> 7
C67: 1 año | D67: =+'POBLACION DE REFERENCIA'!C67 -> 5 | E67: =+'POBLACION DE REFERENCIA'!D67 -> 5 | F67: =+'POBLACION DE REFERENCIA'!E67 -> 5 | G67: =+'POBLACION DE REFERENCIA'!F67 -> 5 | H67: =+'POBLACION DE REFERENCIA'!G67 -> 5 | I67: =+'POBLACION DE REFERENCIA'!H67 -> 5 | J67: =+'POBLACION DE REFERENCIA'!I67 -> 5 | K67: =+'POBLACION DE REFERENCIA'!J67 -> 5 | ... P67: =+'POBLACION DE REFERENCIA'!O67 -> 5
C68: 2 años | D68: =+'POBLACION DE REFERENCIA'!C68 -> 13 | E68: =+'POBLACION DE REFERENCIA'!D68 -> 13 | F68: =+'POBLACION DE REFERENCIA'!E68 -> 13 | G68: =+'POBLACION DE REFERENCIA'!F68 -> 13 | H68: =+'POBLACION DE REFERENCIA'!G68 -> 13 | I68: =+'POBLACION DE REFERENCIA'!H68 -> 13 | J68: =+'POBLACION DE REFERENCIA'!I68 -> 13 | K68: =+'POBLACION DE REFERENCIA'!J68 -> 13 | ... P68: =+'POBLACION DE REFERENCIA'!O68 -> 13
C69: 3 años | D69: =+'POBLACION DE REFERENCIA'!C69 -> 15 | E69: =+'POBLACION DE REFERENCIA'!D69 -> 15 | F69: =+'POBLACION DE REFERENCIA'!E69 -> 15 | G69: =+'POBLACION DE REFERENCIA'!F69 -> 15 | H69: =+'POBLACION DE REFERENCIA'!G69 -> 15 | I69: =+'POBLACION DE REFERENCIA'!H69 -> 15 | J69: =+'POBLACION DE REFERENCIA'!I69 -> 15 | K69: =+'POBLACION DE REFERENCIA'!J69 -> 15 | ... P69: =+'POBLACION DE REFERENCIA'!O69 -> 15
C70: 4 años | D70: =+'POBLACION DE REFERENCIA'!C70 -> 13 | E70: =+'POBLACION DE REFERENCIA'!D70 -> 13 | F70: =+'POBLACION DE REFERENCIA'!E70 -> 13 | G70: =+'POBLACION DE REFERENCIA'!F70 -> 13 | H70: =+'POBLACION DE REFERENCIA'!G70 -> 13 | I70: =+'POBLACION DE REFERENCIA'!H70 -> 13 | J70: =+'POBLACION DE REFERENCIA'!I70 -> 13 | K70: =+'POBLACION DE REFERENCIA'!J70 -> 13 | ... P70: =+'POBLACION DE REFERENCIA'!O70 -> 13
C71: Gestantes | D71: =+'POBLACION DE REFERENCIA'!C71 -> 18 | E71: =+'POBLACION DE REFERENCIA'!D71 -> 18 | F71: =+'POBLACION DE REFERENCIA'!E71 -> 18 | G71: =+'POBLACION DE REFERENCIA'!F71 -> 18 | H71: =+'POBLACION DE REFERENCIA'!G71 -> 18 | I71: =+'POBLACION DE REFERENCIA'!H71 -> 18 | J71: =+'POBLACION DE REFERENCIA'!I71 -> 18 | K71: =+'POBLACION DE REFERENCIA'!J71 -> 18 | ... P71: =+'POBLACION DE REFERENCIA'!O71 -> 18
A73: =+Hoja1!D17 -> 0.0003 | B73: =+Hoja3!D8 -> 0 | C73: POBLACION QUE DEMANDA LOS SERVICIOS DE PROMOCION DE LA SALUD
C75: POBLACION SUJETO DE INTERVENCION (PERSONAS EN SUS DIFERENTES ETAPAS DE VIDA) | D75: PERIODO DE INVERSION | G75: PERIODO DE POST INVERSION
D76: 0 | G76: 1 | H76: 2 | I76: 3 | J76: 4 | K76: 5 | L76: 6 | M76: 7 | N76: 8 | O76: 9 | P76: 10
D77: 2024 | E77: 2025 | F77: 2026 | G77: 2027 | H77: 2028 | I77: 2029 | J77: 2030 | K77: 2031 | L77: 2032 | M77: 2033 | N77: 2034 | O77: 2035 | P77: 2036
C78: CONSEJERIA Y PREVENCION DE TBC (> 18 años) | D78: =+SUM(D79:D84) -> 364 | E78: =+SUM(E79:E84) -> 364 | F78: =+SUM(F79:F84) -> 364 | G78: =+SUM(G79:G84) -> 364 | H78: =+SUM(H79:H84) -> 364 | I78: =+SUM(I79:I84) -> 364 | J78: =+SUM(J79:J84) -> 364 | K78: =+SUM(K79:K84) -> 364 | ... P78: =+SUM(P79:P84) -> 364
C79: 18 a 24 Años | D79: =+'POBLACION DE REFERENCIA'!C79 -> 54 | E79: =+'POBLACION DE REFERENCIA'!D79 -> 54 | F79: =+'POBLACION DE REFERENCIA'!E79 -> 54 | G79: =+'POBLACION DE REFERENCIA'!F79 -> 54 | H79: =+'POBLACION DE REFERENCIA'!G79 -> 54 | I79: =+'POBLACION DE REFERENCIA'!H79 -> 54 | J79: =+'POBLACION DE REFERENCIA'!I79 -> 54 | K79: =+'POBLACION DE REFERENCIA'!J79 -> 54 | ... P79: =+'POBLACION DE REFERENCIA'!O79 -> 54
C80: 25 a 34 Años | D80: =+'POBLACION DE REFERENCIA'!C80 -> 87 | E80: =+'POBLACION DE REFERENCIA'!D80 -> 87 | F80: =+'POBLACION DE REFERENCIA'!E80 -> 87 | G80: =+'POBLACION DE REFERENCIA'!F80 -> 87 | H80: =+'POBLACION DE REFERENCIA'!G80 -> 87 | I80: =+'POBLACION DE REFERENCIA'!H80 -> 87 | J80: =+'POBLACION DE REFERENCIA'!I80 -> 87 | K80: =+'POBLACION DE REFERENCIA'!J80 -> 87 | ... P80: =+'POBLACION DE REFERENCIA'!O80 -> 87
C81: 35 a 44 Años | D81: =+'POBLACION DE REFERENCIA'!C81 -> 66 | E81: =+'POBLACION DE REFERENCIA'!D81 -> 66 | F81: =+'POBLACION DE REFERENCIA'!E81 -> 66 | G81: =+'POBLACION DE REFERENCIA'!F81 -> 66 | H81: =+'POBLACION DE REFERENCIA'!G81 -> 66 | I81: =+'POBLACION DE REFERENCIA'!H81 -> 66 | J81: =+'POBLACION DE REFERENCIA'!I81 -> 66 | K81: =+'POBLACION DE REFERENCIA'!J81 -> 66 | ... P81: =+'POBLACION DE REFERENCIA'!O81 -> 66
C82: 45 a 54 Años | D82: =+'POBLACION DE REFERENCIA'!C82 -> 54 | E82: =+'POBLACION DE REFERENCIA'!D82 -> 54 | F82: =+'POBLACION DE REFERENCIA'!E82 -> 54 | G82: =+'POBLACION DE REFERENCIA'!F82 -> 54 | H82: =+'POBLACION DE REFERENCIA'!G82 -> 54 | I82: =+'POBLACION DE REFERENCIA'!H82 -> 54 | J82: =+'POBLACION DE REFERENCIA'!I82 -> 54 | K82: =+'POBLACION DE REFERENCIA'!J82 -> 54 | ... P82: =+'POBLACION DE REFERENCIA'!O82 -> 54
C83: 55 a 64 Años | D83: =+'POBLACION DE REFERENCIA'!C83 -> 46 | E83: =+'POBLACION DE REFERENCIA'!D83 -> 46 | F83: =+'POBLACION DE REFERENCIA'!E83 -> 46 | G83: =+'POBLACION DE REFERENCIA'!F83 -> 46 | H83: =+'POBLACION DE REFERENCIA'!G83 -> 46 | I83: =+'POBLACION DE REFERENCIA'!H83 -> 46 | J83: =+'POBLACION DE REFERENCIA'!I83 -> 46 | K83: =+'POBLACION DE REFERENCIA'!J83 -> 46 | ... P83: =+'POBLACION DE REFERENCIA'!O83 -> 46
C84: > 65 Años | D84: =+'POBLACION DE REFERENCIA'!C84 -> 57 | E84: =+'POBLACION DE REFERENCIA'!D84 -> 57 | F84: =+'POBLACION DE REFERENCIA'!E84 -> 57 | G84: =+'POBLACION DE REFERENCIA'!F84 -> 57 | H84: =+'POBLACION DE REFERENCIA'!G84 -> 57 | I84: =+'POBLACION DE REFERENCIA'!H84 -> 57 | J84: =+'POBLACION DE REFERENCIA'!I84 -> 57 | K84: =+'POBLACION DE REFERENCIA'!J84 -> 57 | ... P84: =+'POBLACION DE REFERENCIA'!O84 -> 57
C87: POBLACION SUJETO DE INTERVENCION (PERSONAS EN SUS DIFERENTES ETAPAS DE VIDA) | D87: PERIODO DE INVERSION | G87: PERIODO DE POST INVERSION
D88: 0 | G88: 1 | H88: 2 | I88: 3 | J88: 4 | K88: 5 | L88: 6 | M88: 7 | N88: 8 | O88: 9 | P88: 10
D89: =+D77 -> 2024 | E89: =+E77 -> 2025 | F89: =+F77 -> 2026 | G89: =+G77 -> 2027 | H89: =+H77 -> 2028 | I89: =+I77 -> 2029 | J89: =+J77 -> 2030 | K89: =+K77 -> 2031 | ... P89: =+P77 -> 2036
C90: CONSEJERIA DE ITS/VIH/SIDA (> 18 años) | D90: =+SUM(D91:D96) -> 364 | E90: =+SUM(E91:E96) -> 364 | F90: =+SUM(F91:F96) -> 364 | G90: =+SUM(G91:G96) -> 364 | H90: =+SUM(H91:H96) -> 364 | I90: =+SUM(I91:I96) -> 364 | J90: =+SUM(J91:J96) -> 364 | K90: =+SUM(K91:K96) -> 364 | ... P90: =+SUM(P91:P96) -> 364
C91: 18 a 24 Años | D91: =+'POBLACION DE REFERENCIA'!C91 -> 54 | E91: =+'POBLACION DE REFERENCIA'!D91 -> 54 | F91: =+'POBLACION DE REFERENCIA'!E91 -> 54 | G91: =+'POBLACION DE REFERENCIA'!F91 -> 54 | H91: =+'POBLACION DE REFERENCIA'!G91 -> 54 | I91: =+'POBLACION DE REFERENCIA'!H91 -> 54 | J91: =+'POBLACION DE REFERENCIA'!I91 -> 54 | K91: =+'POBLACION DE REFERENCIA'!J91 -> 54 | ... P91: =+'POBLACION DE REFERENCIA'!O91 -> 54
C92: 25 a 34 Años | D92: =+'POBLACION DE REFERENCIA'!C92 -> 87 | E92: =+'POBLACION DE REFERENCIA'!D92 -> 87 | F92: =+'POBLACION DE REFERENCIA'!E92 -> 87 | G92: =+'POBLACION DE REFERENCIA'!F92 -> 87 | H92: =+'POBLACION DE REFERENCIA'!G92 -> 87 | I92: =+'POBLACION DE REFERENCIA'!H92 -> 87 | J92: =+'POBLACION DE REFERENCIA'!I92 -> 87 | K92: =+'POBLACION DE REFERENCIA'!J92 -> 87 | ... P92: =+'POBLACION DE REFERENCIA'!O92 -> 87
C93: 35 a 44 Años | D93: =+'POBLACION DE REFERENCIA'!C93 -> 66 | E93: =+'POBLACION DE REFERENCIA'!D93 -> 66 | F93: =+'POBLACION DE REFERENCIA'!E93 -> 66 | G93: =+'POBLACION DE REFERENCIA'!F93 -> 66 | H93: =+'POBLACION DE REFERENCIA'!G93 -> 66 | I93: =+'POBLACION DE REFERENCIA'!H93 -> 66 | J93: =+'POBLACION DE REFERENCIA'!I93 -> 66 | K93: =+'POBLACION DE REFERENCIA'!J93 -> 66 | ... P93: =+'POBLACION DE REFERENCIA'!O93 -> 66
C94: 45 a 54 Años | D94: =+'POBLACION DE REFERENCIA'!C94 -> 54 | E94: =+'POBLACION DE REFERENCIA'!D94 -> 54 | F94: =+'POBLACION DE REFERENCIA'!E94 -> 54 | G94: =+'POBLACION DE REFERENCIA'!F94 -> 54 | H94: =+'POBLACION DE REFERENCIA'!G94 -> 54 | I94: =+'POBLACION DE REFERENCIA'!H94 -> 54 | J94: =+'POBLACION DE REFERENCIA'!I94 -> 54 | K94: =+'POBLACION DE REFERENCIA'!J94 -> 54 | ... P94: =+'POBLACION DE REFERENCIA'!O94 -> 54
C95: 55 a 64 Años | D95: =+'POBLACION DE REFERENCIA'!C95 -> 46 | E95: =+'POBLACION DE REFERENCIA'!D95 -> 46 | F95: =+'POBLACION DE REFERENCIA'!E95 -> 46 | G95: =+'POBLACION DE REFERENCIA'!F95 -> 46 | H95: =+'POBLACION DE REFERENCIA'!G95 -> 46 | I95: =+'POBLACION DE REFERENCIA'!H95 -> 46 | J95: =+'POBLACION DE REFERENCIA'!I95 -> 46 | K95: =+'POBLACION DE REFERENCIA'!J95 -> 46 | ... P95: =+'POBLACION DE REFERENCIA'!O95 -> 46
C96: > 65 Años | D96: =+'POBLACION DE REFERENCIA'!C96 -> 57 | E96: =+'POBLACION DE REFERENCIA'!D96 -> 57 | F96: =+'POBLACION DE REFERENCIA'!E96 -> 57 | G96: =+'POBLACION DE REFERENCIA'!F96 -> 57 | H96: =+'POBLACION DE REFERENCIA'!G96 -> 57 | I96: =+'POBLACION DE REFERENCIA'!H96 -> 57 | J96: =+'POBLACION DE REFERENCIA'!I96 -> 57 | K96: =+'POBLACION DE REFERENCIA'!J96 -> 57 | ... P96: =+'POBLACION DE REFERENCIA'!O96 -> 57
C98: POBLACION SUJETO DE INTERVENCION (PERSONAS EN SUS DIFERENTES ETAPAS DE VIDA) | D98: PERIODO DE INVERSION | G98: PERIODO DE POST INVERSION
D99: 0 | G99: 1 | H99: 2 | I99: 3 | J99: 4 | K99: 5 | L99: 6 | M99: 7 | N99: 8 | O99: 9 | P99: 10
D100: =+D89 -> 2024 | E100: =+E89 -> 2025 | F100: =+F89 -> 2026 | G100: =+G89 -> 2027 | H100: =+H89 -> 2028 | I100: =+I89 -> 2029 | J100: =+J89 -> 2030 | K100: =+K89 -> 2031 | ... P100: =+P89 -> 2036
C101: CONSEJERIA DEL ADOLESCENTE ( 12 a 17 años) | D101: =+SUM(D102:D107) -> 39 | E101: =+SUM(E102:E107) -> 39 | F101: =+SUM(F102:F107) -> 39 | G101: =+SUM(G102:G107) -> 39 | H101: =+SUM(H102:H107) -> 39 | I101: =+SUM(I102:I107) -> 39 | J101: =+SUM(J102:J107) -> 39 | K101: =+SUM(K102:K107) -> 39 | ... P101: =+SUM(P102:P107) -> 39
C102: 12 años | D102: =+'POBLACION DE REFERENCIA'!C102 -> 7 | E102: =+'POBLACION DE REFERENCIA'!D102 -> 7 | F102: =+'POBLACION DE REFERENCIA'!E102 -> 7 | G102: =+'POBLACION DE REFERENCIA'!F102 -> 7 | H102: =+'POBLACION DE REFERENCIA'!G102 -> 7 | I102: =+'POBLACION DE REFERENCIA'!H102 -> 7 | J102: =+'POBLACION DE REFERENCIA'!I102 -> 7 | K102: =+'POBLACION DE REFERENCIA'!J102 -> 7 | ... P102: =+'POBLACION DE REFERENCIA'!O102 -> 7
C103: 13 años | D103: =+'POBLACION DE REFERENCIA'!C103 -> 9 | E103: =+'POBLACION DE REFERENCIA'!D103 -> 9 | F103: =+'POBLACION DE REFERENCIA'!E103 -> 9 | G103: =+'POBLACION DE REFERENCIA'!F103 -> 9 | H103: =+'POBLACION DE REFERENCIA'!G103 -> 9 | I103: =+'POBLACION DE REFERENCIA'!H103 -> 9 | J103: =+'POBLACION DE REFERENCIA'!I103 -> 9 | K103: =+'POBLACION DE REFERENCIA'!J103 -> 9 | ... P103: =+'POBLACION DE REFERENCIA'!O103 -> 9
C104: 14 años | D104: =+'POBLACION DE REFERENCIA'!C104 -> 7 | E104: =+'POBLACION DE REFERENCIA'!D104 -> 7 | F104: =+'POBLACION DE REFERENCIA'!E104 -> 7 | G104: =+'POBLACION DE REFERENCIA'!F104 -> 7 | H104: =+'POBLACION DE REFERENCIA'!G104 -> 7 | I104: =+'POBLACION DE REFERENCIA'!H104 -> 7 | J104: =+'POBLACION DE REFERENCIA'!I104 -> 7 | K104: =+'POBLACION DE REFERENCIA'!J104 -> 7 | ... P104: =+'POBLACION DE REFERENCIA'!O104 -> 7
C105: 15 años | D105: =+'POBLACION DE REFERENCIA'!C105 -> 5 | E105: =+'POBLACION DE REFERENCIA'!D105 -> 5 | F105: =+'POBLACION DE REFERENCIA'!E105 -> 5 | G105: =+'POBLACION DE REFERENCIA'!F105 -> 5 | H105: =+'POBLACION DE REFERENCIA'!G105 -> 5 | I105: =+'POBLACION DE REFERENCIA'!H105 -> 5 | J105: =+'POBLACION DE REFERENCIA'!I105 -> 5 | K105: =+'POBLACION DE REFERENCIA'!J105 -> 5 | ... P105: =+'POBLACION DE REFERENCIA'!O105 -> 5
C106: 16 años | D106: =+'POBLACION DE REFERENCIA'!C106 -> 6 | E106: =+'POBLACION DE REFERENCIA'!D106 -> 6 | F106: =+'POBLACION DE REFERENCIA'!E106 -> 6 | G106: =+'POBLACION DE REFERENCIA'!F106 -> 6 | H106: =+'POBLACION DE REFERENCIA'!G106 -> 6 | I106: =+'POBLACION DE REFERENCIA'!H106 -> 6 | J106: =+'POBLACION DE REFERENCIA'!I106 -> 6 | K106: =+'POBLACION DE REFERENCIA'!J106 -> 6 | ... P106: =+'POBLACION DE REFERENCIA'!O106 -> 6
C107: 17 años | D107: =+'POBLACION DE REFERENCIA'!C107 -> 5 | E107: =+'POBLACION DE REFERENCIA'!D107 -> 5 | F107: =+'POBLACION DE REFERENCIA'!E107 -> 5 | G107: =+'POBLACION DE REFERENCIA'!F107 -> 5 | H107: =+'POBLACION DE REFERENCIA'!G107 -> 5 | I107: =+'POBLACION DE REFERENCIA'!H107 -> 5 | J107: =+'POBLACION DE REFERENCIA'!I107 -> 5 | K107: =+'POBLACION DE REFERENCIA'!J107 -> 5 | ... P107: =+'POBLACION DE REFERENCIA'!O107 -> 5
C109: POBLACION SUJETO DE INTERVENCION | D109: PERIODO DE INVERSION | G109: PERIODO DE POST INVERSION
D110: 0 | G110: 1 | H110: 2 | I110: 3 | J110: 4 | K110: 5 | L110: 6 | M110: 7 | N110: 8 | O110: 9 | P110: 10
D111: 2024 | E111: 2025 | F111: 2026 | G111: 2027 | H111: 2028 | I111: 2029 | J111: 2030 | K111: 2031 | L111: 2032 | M111: 2033 | N111: 2034 | O111: 2035 | P111: 2036
C112: ADULTO MAYOR (> 18 años) | D112: =SUM(D113:D118) -> 364 | E112: =SUM(E113:E118) -> 364 | F112: =SUM(F113:F118) -> 364 | G112: =SUM(G113:G118) -> 364 | H112: =SUM(H113:H118) -> 364 | I112: =SUM(I113:I118) -> 364 | J112: =SUM(J113:J118) -> 364 | K112: =SUM(K113:K118) -> 364 | ... P112: =SUM(P113:P118) -> 364
C113: 18 a 24 Años | D113: =+'POBLACION DE REFERENCIA'!C113 -> 54 | E113: =+'POBLACION DE REFERENCIA'!D113 -> 54 | F113: =+'POBLACION DE REFERENCIA'!E113 -> 54 | G113: =+'POBLACION DE REFERENCIA'!F113 -> 54 | H113: =+'POBLACION DE REFERENCIA'!G113 -> 54 | I113: =+'POBLACION DE REFERENCIA'!H113 -> 54 | J113: =+'POBLACION DE REFERENCIA'!I113 -> 54 | K113: =+'POBLACION DE REFERENCIA'!J113 -> 54 | ... P113: =+'POBLACION DE REFERENCIA'!O113 -> 54
...

Sheet POBLACION DEMANDANTE EFECTIVA
C5: POBLACION SUJETO DE INTERVENCION (PERSONAS EN SUS DIFERENTES ETAPAS DE VIDA) | D5: PERIODO DE INVERSION | G5: PERIODO DE POST INVERSION
D6: 0 | G6: 1 | H6: 2 | I6: 3 | J6: 4 | K6: 5 | L6: 6 | M6: 7 | N6: 8 | O6: 9 | P6: 10
A7: =+Hoja1!D17 -> 0.0003 | D7: 2024 | E7: 2025 | F7: 2026 | G7: 2027 | H7: 2028 | I7: 2029 | J7: 2030 | K7: 2031 | L7: 2032 | M7: 2033 | N7: 2034 | O7: 2035 | P7: 2036
C8: Medicina General | D8: =+D9 -> 170.352 | E8: =+E9 -> 170 | F8: =+F9 -> 170 | G8: =+G9 -> 171 | H8: =+H9 -> 171 | I8: =+I9 -> 171 | J8: =+J9 -> 171 | K8: =+K9 -> 171 | ... P8: =+P9 -> 171
C9: 0 a 85 años a mas | D9: =+'POBLACION DEMANDANTE POTENCIAL'!D32*70% -> 170.352 | E9: =ROUND(($D$9*(1+$A$7)^(E7-$D$7)),0) -> 170 | F9: =ROUND(($D$9*(1+$A$7)^(F7-$D$7)),0) -> 170 | G9: =ROUND(($D$9*(1+$A$7)^(G7-$D$7)),0) -> 171 | H9: =ROUND(($D$9*(1+$A$7)^(H7-$D$7)),0) -> 171 | I9: =ROUND(($D$9*(1+$A$7)^(I7-$D$7)),0) -> 171 | J9: =ROUND(($D$9*(1+$A$7)^(J7-$D$7)),0) -> 171 | K9: =ROUND(($D$9*(1+$A$7)^(K7-$D$7)),0) -> 171 | L9: =ROUND(($D$9*(1+$A$7)^(L7-$D$7)),0) -> 171 | ... P9: =ROUND(($D$9*(1+$A$7)^(P7-$D$7)),0) -> 171
C11: POBLACION SUJETO DE INTERVENCION (PERSONAS EN SUS DIFERENTES ETAPAS DE VIDA) | D11: PERIODO DE INVERSION | G11: PERIODO DE POST INVERSION
D12: 0 | G12: 1 | H12: 2 | I12: 3 | J12: 4 | K12: 5 | L12: 6 | M12: 7 | N12: 8 | O12: 9 | P12: 10
D13: 2024 | E13: 2025 | F13: 2026 | G13: 2027 | H13: 2028 | I13: 2029 | J13: 2030 | K13: 2031 | L13: 2032 | M13: 2033 | N13: 2034 | O13: 2035 | P13: 2036
C14: Teleconsulta medica | D14: =+D15 -> 170.352 | E14: =+E15 -> 170 | F14: =+F15 -> 170 | G14: =+G15 -> 171 | H14: =+H15 -> 171 | I14: =+I15 -> 171 | J14: =+J15 -> 171 | K14: =+K15 -> 171 | ... P14: =+P15 -> 171
C15: 0 a 85 años a mas | D15: =+'POBLACION DEMANDANTE POTENCIAL'!D38*70% -> 170.352 | E15: =ROUND(($D$15*(1+$A$7)^(E13-$D$13)),0) -> 170 | F15: =ROUND(($D$15*(1+$A$7)^(F13-$D$13)),0) -> 170 | G15: =ROUND(($D$15*(1+$A$7)^(G13-$D$13)),0) -> 171 | H15: =ROUND(($D$15*(1+$A$7)^(H13-$D$13)),0) -> 171 | I15: =ROUND(($D$15*(1+$A$7)^(I13-$D$13)),0) -> 171 | J15: =ROUND(($D$15*(1+$A$7)^(J13-$D$13)),0) -> 171 | K15: =ROUND(($D$15*(1+$A$7)^(K13-$D$13)),0) -> 171 | L15: =ROUND(($D$15*(1+$A$7)^(L13-$D$13)),0) -> 171 | ... P15: =ROUND(($D$15*(1+$A$7)^(P13-$D$13)),0) -> 171
C17: POBLACION SUJETO DE INTERVENCION | D17: PERIODO DE INVERSION | G17: PERIODO DE POST INVERSION
D18: 0 | G18: 1 | H18: 2 | I18: 3 | J18: 4 | K18: 5 | L18: 6 | M18: 7 | N18: 8 | O18: 9 | P18: 10
D19: =+D13 -> 2024 | E19: =+E13 -> 2025 | F19: =+F13 -> 2026 | G19: =+G13 -> 2027 | H19: =+H13 -> 2028 | I19: =+I13 -> 2029 | J19: =+J13 -> 2030 | K19: =+K13 -> 2031 | ... P19: =+P13 -> 2036
C20: CRED (< de 11 años) | D20: =+SUM(D21:D27) -> 85.6 | E20: =+SUM(E21:E27) -> 85 | F20: =+SUM(F21:F27) -> 85 | G20: =+SUM(G21:G27) -> 85 | H20: =+SUM(H21:H27) -> 85 | I20: =+SUM(I21:I27) -> 85 | J20: =+SUM(J21:J27) -> 85 | K20: =+SUM(K21:K27) -> 85 | ... P20: =+SUM(P21:P27) -> 85
C21: < de 29 dias | D21: =+'POBLACION DEMANDANTE POTENCIAL'!D44*80% -> 2.4 | E21: =ROUND(($D$21*(1+$A$7)^(E19-$D$19)),0) -> 2 | F21: =ROUND(($D$21*(1+$A$7)^(F19-$D$19)),0) -> 2 | G21: =ROUND(($D$21*(1+$A$7)^(G19-$D$19)),0) -> 2 | H21: =ROUND(($D$21*(1+$A$7)^(H19-$D$19)),0) -> 2 | I21: =ROUND(($D$21*(1+$A$7)^(I19-$D$19)),0) -> 2 | J21: =ROUND(($D$21*(1+$A$7)^(J19-$D$19)),0) -> 2 | K21: =ROUND(($D$21*(1+$A$7)^(K19-$D$19)),0) -> 2 | L21: =ROUND(($D$21*(1+$A$7)^(L19-$D$19)),0) -> 2 | ... P21: =ROUND(($D$21*(1+$A$7)^(P19-$D$19)),0) -> 2
C22: < de 1 año | D22: =+'POBLACION DEMANDANTE POTENCIAL'!D45*80% -> 5.6 | E22: =ROUND(($D$22*(1+$A$7)^(E19-$D$19)),0) -> 6 | F22: =ROUND(($D$22*(1+$A$7)^(F19-$D$19)),0) -> 6 | G22: =ROUND(($D$22*(1+$A$7)^(G19-$D$19)),0) -> 6 | H22: =ROUND(($D$22*(1+$A$7)^(H19-$D$19)),0) -> 6 | I22: =ROUND(($D$22*(1+$A$7)^(I19-$D$19)),0) -> 6 | J22: =ROUND(($D$22*(1+$A$7)^(J19-$D$19)),0) -> 6 | K22: =ROUND(($D$22*(1+$A$7)^(K19-$D$19)),0) -> 6 | L22: =ROUND(($D$22*(1+$A$7)^(L19-$D$19)),0) -> 6 | ... P22: =ROUND(($D$22*(1+$A$7)^(P19-$D$19)),0) -> 6
C23: 1 año | D23: =+'POBLACION DEMANDANTE POTENCIAL'!D46*80% -> 4 | E23: =ROUND(($D$23*(1+$A$7)^(E19-$D$19)),0) -> 4 | F23: =ROUND(($D$23*(1+$A$7)^(F19-$D$19)),0) -> 4 | G23: =ROUND(($D$23*(1+$A$7)^(G19-$D$19)),0) -> 4 | H23: =ROUND(($D$23*(1+$A$7)^(H19-$D$19)),0) -> 4 | I23: =ROUND(($D$23*(1+$A$7)^(I19-$D$19)),0) -> 4 | J23: =ROUND(($D$23*(1+$A$7)^(J19-$D$19)),0) -> 4 | K23: =ROUND(($D$23*(1+$A$7)^(K19-$D$19)),0) -> 4 | L23: =ROUND(($D$23*(1+$A$7)^(L19-$D$19)),0) -> 4 | ... P23: =ROUND(($D$23*(1+$A$7)^(P19-$D$19)),0) -> 4
C24: 2 años | D24: =+'POBLACION DEMANDANTE POTENCIAL'!D47*80% -> 10.4 | E24: =ROUND(($D$24*(1+$A$7)^(E19-$D$19)),0) -> 10 | F24: =ROUND(($D$24*(1+$A$7)^(F19-$D$19)),0) -> 10 | G24: =ROUND(($D$24*(1+$A$7)^(G19-$D$19)),0) -> 10 | H24: =ROUND(($D$24*(1+$A$7)^(H19-$D$19)),0) -> 10 | I24: =ROUND(($D$24*(1+$A$7)^(I19-$D$19)),0) -> 10 | J24: =ROUND(($D$24*(1+$A$7)^(J19-$D$19)),0) -> 10 | K24: =ROUND(($D$24*(1+$A$7)^(K19-$D$19)),0) -> 10 | L24: =ROUND(($D$24*(1+$A$7)^(L19-$D$19)),0) -> 10 | ... P24: =ROUND(($D$24*(1+$A$7)^(P19-$D$19)),0) -> 10
C25: 3 años | D25: =+'POBLACION DEMANDANTE POTENCIAL'!D48*80% -> 12 | E25: =ROUND(($D$25*(1+$A$7)^(E19-$D$19)),0) -> 12 | F25: =ROUND(($D$25*(1+$A$7)^(F19-$D$19)),0) -> 12 | G25: =ROUND(($D$25*(1+$A$7)^(G19-$D$19)),0) -> 12 | H25: =ROUND(($D$25*(1+$A$7)^(H19-$D$19)),0) -> 12 | I25: =ROUND(($D$25*(1+$A$7)^(I19-$D$19)),0) -> 12 | J25: =ROUND(($D$25*(1+$A$7)^(J19-$D$19)),0) -> 12 | K25: =ROUND(($D$25*(1+$A$7)^(K19-$D$19)),0) -> 12 | L25: =ROUND(($D$25*(1+$A$7)^(L19-$D$19)),0) -> 12 | ... P25: =ROUND(($D$25*(1+$A$7)^(P19-$D$19)),0) -> 12
C26: 4 años | D26: =+'POBLACION DEMANDANTE POTENCIAL'!D49*80% -> 10.4 | E26: =ROUND(($D$26*(1+$A$7)^(E19-$D$19)),0) -> 10 | F26: =ROUND(($D$26*(1+$A$7)^(F19-$D$19)),0) -> 10 | G26: =ROUND(($D$26*(1+$A$7)^(G19-$D$19)),0) -> 10 | H26: =ROUND(($D$26*(1+$A$7)^(H19-$D$19)),0) -> 10 | I26: =ROUND(($D$26*(1+$A$7)^(I19-$D$19)),0) -> 10 | J26: =ROUND(($D$26*(1+$A$7)^(J19-$D$19)),0) -> 10 | K26: =ROUND(($D$26*(1+$A$7)^(K19-$D$19)),0) -> 10 | L26: =ROUND(($D$26*(1+$A$7)^(L19-$D$19)),0) -> 10 | ... P26: =ROUND(($D$26*(1+$A$7)^(P19-$D$19)),0) -> 10
C27: 5 a 11 años | D27: =+'POBLACION DEMANDANTE POTENCIAL'!D50*80% -> 40.8 | E27: =ROUND(($D$27*(1+$A$7)^(E19-$D$19)),0) -> 41 | F27: =ROUND(($D$27*(1+$A$7)^(F19-$D$19)),0) -> 41 | G27: =ROUND(($D$27*(1+$A$7)^(G19-$D$19)),0) -> 41 | H27: =ROUND(($D$27*(1+$A$7)^(H19-$D$19)),0) -> 41 | I27: =ROUND(($D$27*(1+$A$7)^(I19-$D$19)),0) -> 41 | J27: =ROUND(($D$27*(1+$A$7)^(J19-$D$19)),0) -> 41 | K27: =ROUND(($D$27*(1+$A$7)^(K19-$D$19)),0) -> 41 | L27: =ROUND(($D$27*(1+$A$7)^(L19-$D$19)),0) -> 41 | ... P27: =ROUND(($D$27*(1+$A$7)^(P19-$D$19)),0) -> 41
C29: POBLACION SUJETO DE INTERVENCION | D29: PERIODO DE INVERSION | G29: PERIODO DE POST INVERSION
D30: 0 | G30: 1 | H30: 2 | I30: 3 | J30: 4 | K30: 5 | L30: 6 | M30: 7 | N30: 8 | O30: 9 | P30: 10
D31: =+D19 -> 2024 | E31: =+E19 -> 2025 | F31: =+F19 -> 2026 | G31: =+G19 -> 2027 | H31: =+H19 -> 2028 | I31: =+I19 -> 2029 | J31: =+J19 -> 2030 | K31: =+K19 -> 2031 | ... P31: =+P19 -> 2036
C32: ESTIMULACION TEMPRANA (< de 3 años) | D32: =+SUM(D33:D37) -> 34.4 | E32: =+SUM(E33:E37) -> 34 | F32: =+SUM(F33:F37) -> 34 | G32: =+SUM(G33:G37) -> 34 | H32: =+SUM(H33:H37) -> 34 | I32: =+SUM(I33:I37) -> 34 | J32: =+SUM(J33:J37) -> 34 | K32: =+SUM(K33:K37) -> 34 | ... P32: =+SUM(P33:P37) -> 34
C33: < 29 dias | D33: =+'POBLACION DEMANDANTE POTENCIAL'!D56*80% -> 2.4 | E33: =ROUND(($D$33*(1+$A$7)^(E31-$D$31)),0) -> 2 | F33: =ROUND(($D$33*(1+$A$7)^(F31-$D$31)),0) -> 2 | G33: =ROUND(($D$33*(1+$A$7)^(G31-$D$31)),0) -> 2 | H33: =ROUND(($D$33*(1+$A$7)^(H31-$D$31)),0) -> 2 | I33: =ROUND(($D$33*(1+$A$7)^(I31-$D$31)),0) -> 2 | J33: =ROUND(($D$33*(1+$A$7)^(J31-$D$31)),0) -> 2 | K33: =ROUND(($D$33*(1+$A$7)^(K31-$D$31)),0) -> 2 | L33: =ROUND(($D$33*(1+$A$7)^(L31-$D$31)),0) -> 2 | ... P33: =ROUND(($D$33*(1+$A$7)^(P31-$D$31)),0) -> 2
C34: < 1 año | D34: =+'POBLACION DEMANDANTE POTENCIAL'!D57*80% -> 5.6 | E34: =ROUND(($D$34*(1+$A$7)^(E31-$D$31)),0) -> 6 | F34: =ROUND(($D$34*(1+$A$7)^(F31-$D$31)),0) -> 6 | G34: =ROUND(($D$34*(1+$A$7)^(G31-$D$31)),0) -> 6 | H34: =ROUND(($D$34*(1+$A$7)^(H31-$D$31)),0) -> 6 | I34: =ROUND(($D$34*(1+$A$7)^(I31-$D$31)),0) -> 6 | J34: =ROUND(($D$34*(1+$A$7)^(J31-$D$31)),0) -> 6 | K34: =ROUND(($D$34*(1+$A$7)^(K31-$D$31)),0) -> 6 | L34: =ROUND(($D$34*(1+$A$7)^(L31-$D$31)),0) -> 6 | ... P34: =ROUND(($D$34*(1+$A$7)^(P31-$D$31)),0) -> 6
C35: 1 años | D35: =+'POBLACION DEMANDANTE POTENCIAL'!D58*80% -> 4 | E35: =ROUND(($D$35*(1+$A$7)^(E31-$D$31)),0) -> 4 | F35: =ROUND(($D$35*(1+$A$7)^(F31-$D$31)),0) -> 4 | G35: =ROUND(($D$35*(1+$A$7)^(G31-$D$31)),0) -> 4 | H35: =ROUND(($D$35*(1+$A$7)^(H31-$D$31)),0) -> 4 | I35: =ROUND(($D$35*(1+$A$7)^(I31-$D$31)),0) -> 4 | J35: =ROUND(($D$35*(1+$A$7)^(J31-$D$31)),0) -> 4 | K35: =ROUND(($D$35*(1+$A$7)^(K31-$D$31)),0) -> 4 | L35: =ROUND(($D$35*(1+$A$7)^(L31-$D$31)),0) -> 4 | ... P35: =ROUND(($D$35*(1+$A$7)^(P31-$D$31)),0) -> 4
C36: 2 años | D36: =+'POBLACION DEMANDANTE POTENCIAL'!D59*80% -> 10.4 | E36: =ROUND((D36*(1+$A$7)^(E31-$D$31)),0) -> 10 | F36: =ROUND((E36*(1+$A$7)^(F31-$D$31)),0) -> 10 | G36: =ROUND((F36*(1+$A$7)^(G31-$D$31)),0) -> 10 | H36: =ROUND((G36*(1+$A$7)^(H31-$D$31)),0) -> 10 | I36: =ROUND((H36*(1+$A$7)^(I31-$D$31)),0) -> 10 | J36: =ROUND((I36*(1+$A$7)^(J31-$D$31)),0) -> 10 | K36: =ROUND((J36*(1+$A$7)^(K31-$D$31)),0) -> 10 | L36: =ROUND((K36*(1+$A$7)^(L31-$D$31)),0) -> 10 | ... P36: =ROUND((O36*(1+$A$7)^(P31-$D$31)),0) -> 10
C37: 3 años | D37: =+'POBLACION DEMANDANTE POTENCIAL'!D60*80% -> 12 | E37: =ROUND((D37*(1+$A$7)^(E31-$D$31)),0) -> 12 | F37: =ROUND((E37*(1+$A$7)^(F31-$D$31)),0) -> 12 | G37: =ROUND((F37*(1+$A$7)^(G31-$D$31)),0) -> 12 | H37: =ROUND((G37*(1+$A$7)^(H31-$D$31)),0) -> 12 | I37: =ROUND((H37*(1+$A$7)^(I31-$D$31)),0) -> 12 | J37: =ROUND((I37*(1+$A$7)^(J31-$D$31)),0) -> 12 | K37: =ROUND((J37*(1+$A$7)^(K31-$D$31)),0) -> 12 | L37: =ROUND((K37*(1+$A$7)^(L31-$D$31)),0) -> 12 | ... P37: =ROUND((O37*(1+$A$7)^(P31-$D$31)),0) -> 12
C39: POBLACION SUJETO DE INTERVENCION | D39: PERIODO DE INVERSION | G39: PERIODO DE POST INVERSION
D40: 0 | G40: 1 | H40: 2 | I40: 3 | J40: 4 | K40: 5 | L40: 6 | M40: 7 | N40: 8 | O40: 9 | P40: 10
D41: 2024 | E41: 2025 | F41: 2026 | G41: 2027 | H41: 2028 | I41: 2029 | J41: 2030 | K41: 2031 | L41: 2032 | M41: 2033 | N41: 2034 | O41: 2035 | P41: 2036
C42: INMUNIZACIONES (< de 4 años, Gestantes) | D42: =+SUM(D43:D48) -> 56.8 | E42: =+SUM(E43:E48) -> 56 | F42: =+SUM(F43:F48) -> 56 | G42: =+SUM(G43:G48) -> 56 | H42: =+SUM(H43:H48) -> 56 | I42: =+SUM(I43:I48) -> 56 | J42: =+SUM(J43:J48) -> 56 | K42: =+SUM(K43:K48) -> 56 | ... P42: =+SUM(P43:P48) -> 56
C43: < 1 año | D43: =+'POBLACION DEMANDANTE POTENCIAL'!D66*80% -> 5.6 | E43: =ROUND(($D$43*(1+$A$7)^(E41-$D$41)),0) -> 6 | F43: =ROUND(($D$43*(1+$A$7)^(F41-$D$41)),0) -> 6 | G43: =ROUND(($D$43*(1+$A$7)^(G41-$D$41)),0) -> 6 | H43: =ROUND(($D$43*(1+$A$7)^(H41-$D$41)),0) -> 6 | I43: =ROUND(($D$43*(1+$A$7)^(I41-$D$41)),0) -> 6 | J43: =ROUND(($D$43*(1+$A$7)^(J41-$D$41)),0) -> 6 | K43: =ROUND(($D$43*(1+$A$7)^(K41-$D$41)),0) -> 6 | L43: =ROUND(($D$43*(1+$A$7)^(L41-$D$41)),0) -> 6 | ... P43: =ROUND(($D$43*(1+$A$7)^(P41-$D$41)),0) -> 6
C44: 1 año | D44: =+'POBLACION DEMANDANTE POTENCIAL'!D67*80% -> 4 | E44: =ROUND(($D$44*(1+$A$7)^(E41-$D$41)),0) -> 4 | F44: =ROUND(($D$44*(1+$A$7)^(F41-$D$41)),0) -> 4 | G44: =ROUND(($D$44*(1+$A$7)^(G41-$D$41)),0) -> 4 | H44: =ROUND(($D$44*(1+$A$7)^(H41-$D$41)),0) -> 4 | I44: =ROUND(($D$44*(1+$A$7)^(I41-$D$41)),0) -> 4 | J44: =ROUND(($D$44*(1+$A$7)^(J41-$D$41)),0) -> 4 | K44: =ROUND(($D$44*(1+$A$7)^(K41-$D$41)),0) -> 4 | L44: =ROUND(($D$44*(1+$A$7)^(L41-$D$41)),0) -> 4 | ... P44: =ROUND(($D$44*(1+$A$7)^(P41-$D$41)),0) -> 4
C45: 2 años | D45: =+'POBLACION DEMANDANTE POTENCIAL'!D68*80% -> 10.4 | E45: =ROUND(($D$45*(1+$A$7)^(E41-$D$41)),0) -> 10 | F45: =ROUND(($D$45*(1+$A$7)^(F41-$D$41)),0) -> 10 | G45: =ROUND(($D$45*(1+$A$7)^(G41-$D$41)),0) -> 10 | H45: =ROUND(($D$45*(1+$A$7)^(H41-$D$41)),0) -> 10 | I45: =ROUND(($D$45*(1+$A$7)^(I41-$D$41)),0) -> 10 | J45: =ROUND(($D$45*(1+$A$7)^(J41-$D$41)),0) -> 10 | K45: =ROUND(($D$45*(1+$A$7)^(K41-$D$41)),0) -> 10 | L45: =ROUND(($D$45*(1+$A$7)^(L41-$D$41)),0) -> 10 | ... P45: =ROUND(($D$45*(1+$A$7)^(P41-$D$41)),0) -> 10
C46: 3 años | D46: =+'POBLACION DEMANDANTE POTENCIAL'!D69*80% -> 12 | E46: =ROUND(($D$46*(1+$A$7)^(E41-$D$41)),0) -> 12 | F46: =ROUND(($D$46*(1+$A$7)^(F41-$D$41)),0) -> 12 | G46: =ROUND(($D$46*(1+$A$7)^(G41-$D$41)),0) -> 12 | H46: =ROUND(($D$46*(1+$A$7)^(H41-$D$41)),0) -> 12 | I46: =ROUND(($D$46*(1+$A$7)^(I41-$D$41)),0) -> 12 | J46: =ROUND(($D$46*(1+$A$7)^(J41-$D$41)),0) -> 12 | K46: =ROUND(($D$46*(1+$A$7)^(K41-$D$41)),0) -> 12 | L46: =ROUND(($D$46*(1+$A$7)^(L41-$D$41)),0) -> 12 | ... P46: =ROUND(($D$46*(1+$A$7)^(P41-$D$41)),0) -> 12
C47: 4 años | D47: =+'POBLACION DEMANDANTE POTENCIAL'!D70*80% -> 10.4 | E47: =ROUND(($D$47*(1+$A$7)^(E41-$D$41)),0) -> 10 | F47: =ROUND(($D$47*(1+$A$7)^(F41-$D$41)),0) -> 10 | G47: =ROUND(($D$47*(1+$A$7)^(G41-$D$41)),0) -> 10 | H47: =ROUND(($D$47*(1+$A$7)^(H41-$D$41)),0) -> 10 | I47: =ROUND(($D$47*(1+$A$7)^(I41-$D$41)),0) -> 10 | J47: =ROUND(($D$47*(1+$A$7)^(J41-$D$41)),0) -> 10 | K47: =ROUND(($D$47*(1+$A$7)^(K41-$D$41)),0) -> 10 | L47: =ROUND(($D$47*(1+$A$7)^(L41-$D$41)),0) -> 10 | ... P47: =ROUND(($D$47*(1+$A$7)^(P41-$D$41)),0) -> 10
C48: Gestantes | D48: =+'POBLACION DEMANDANTE POTENCIAL'!D71*80% -> 14.4 | E48: =ROUND(($D$48*(1+$A$7)^(E41-$D$41)),0) -> 14 | F48: =ROUND(($D$48*(1+$A$7)^(F41-$D$41)),0) -> 14 | G48: =ROUND(($D$48*(1+$A$7)^(G41-$D$41)),0) -> 14 | H48: =ROUND(($D$48*(1+$A$7)^(H41-$D$41)),0) -> 14 | I48: =ROUND(($D$48*(1+$A$7)^(I41-$D$41)),0) -> 14 | J48: =ROUND(($D$48*(1+$A$7)^(J41-$D$41)),0) -> 14 | K48: =ROUND(($D$48*(1+$A$7)^(K41-$D$41)),0) -> 14 | L48: =ROUND(($D$48*(1+$A$7)^(L41-$D$41)),0) -> 14 | ... P48: =ROUND(($D$48*(1+$A$7)^(P41-$D$41)),0) -> 14
A50: =+Hoja1!D16 -> 507 | B50: =+Hoja3!D7 -> 0 | C50: POBLACION QUE DEMANDA LOS SERVICIOS DE PROMOCION DE LA SALUD
C52: POBLACION SUJETO DE INTERVENCION (PERSONAS EN SUS DIFERENTES ETAPAS DE VIDA) | D52: PERIODO DE INVERSION | G52: PERIODO DE POST INVERSION
D53: 0 | G53: 1 | H53: 2 | I53: 3 | J53: 4 | K53: 5 | L53: 6 | M53: 7 | N53: 8 | O53: 9 | P53: 10
D54: 2024 | E54: 2025 | F54: 2026 | G54: 2027 | H54: 2028 | I54: 2029 | J54: 2030 | K54: 2031 | L54: 2032 | M54: 2033 | N54: 2034 | O54: 2035 | P54: 2036
C55: CONSEJERIA Y PREVENCION DE TBC (> 18 años) | D55: =+SUM(D56:D61) -> 291.2 | E55: =+SUM(E56:E61) -> 292 | F55: =+SUM(F56:F61) -> 292 | G55: =+SUM(G56:G61) -> 292 | H55: =+SUM(H56:H61) -> 292 | I55: =+SUM(I56:I61) -> 292 | J55: =+SUM(J56:J61) -> 292 | K55: =+SUM(K56:K61) -> 292 | ... P55: =+SUM(P56:P61) -> 292
C56: 18 a 24 Años | D56: =+'POBLACION DEMANDANTE POTENCIAL'!D79*80% -> 43.2 | E56: =ROUND(($D$56*(1+$A$7)^(E54-$D$54)),0) -> 43 | F56: =ROUND(($D$56*(1+$A$7)^(F54-$D$54)),0) -> 43 | G56: =ROUND(($D$56*(1+$A$7)^(G54-$D$54)),0) -> 43 | H56: =ROUND(($D$56*(1+$A$7)^(H54-$D$54)),0) -> 43 | I56: =ROUND(($D$56*(1+$A$7)^(I54-$D$54)),0) -> 43 | J56: =ROUND(($D$56*(1+$A$7)^(J54-$D$54)),0) -> 43 | K56: =ROUND(($D$56*(1+$A$7)^(K54-$D$54)),0) -> 43 | L56: =ROUND(($D$56*(1+$A$7)^(L54-$D$54)),0) -> 43 | ... P56: =ROUND(($D$56*(1+$A$7)^(P54-$D$54)),0) -> 43
C57: 25 a 34 Años | D57: =+'POBLACION DEMANDANTE POTENCIAL'!D80*80% -> 69.6 | E57: =ROUND(($D$57*(1+$A$7)^(E54-$D$54)),0) -> 70 | F57: =ROUND(($D$57*(1+$A$7)^(F54-$D$54)),0) -> 70 | G57: =ROUND(($D$57*(1+$A$7)^(G54-$D$54)),0) -> 70 | H57: =ROUND(($D$57*(1+$A$7)^(H54-$D$54)),0) -> 70 | I57: =ROUND(($D$57*(1+$A$7)^(I54-$D$54)),0) -> 70 | J57: =ROUND(($D$57*(1+$A$7)^(J54-$D$54)),0) -> 70 | K57: =ROUND(($D$57*(1+$A$7)^(K54-$D$54)),0) -> 70 | L57: =ROUND(($D$57*(1+$A$7)^(L54-$D$54)),0) -> 70 | ... P57: =ROUND(($D$57*(1+$A$7)^(P54-$D$54)),0) -> 70
C58: 35 a 44 Años | D58: =+'POBLACION DEMANDANTE POTENCIAL'!D81*80% -> 52.8 | E58: =ROUND(($D$58*(1+$A$7)^(E54-$D$54)),0) -> 53 | F58: =ROUND(($D$58*(1+$A$7)^(F54-$D$54)),0) -> 53 | G58: =ROUND(($D$58*(1+$A$7)^(G54-$D$54)),0) -> 53 | H58: =ROUND(($D$58*(1+$A$7)^(H54-$D$54)),0) -> 53 | I58: =ROUND(($D$58*(1+$A$7)^(I54-$D$54)),0) -> 53 | J58: =ROUND(($D$58*(1+$A$7)^(J54-$D$54)),0) -> 53 | K58: =ROUND(($D$58*(1+$A$7)^(K54-$D$54)),0) -> 53 | L58: =ROUND(($D$58*(1+$A$7)^(L54-$D$54)),0) -> 53 | ... P58: =ROUND(($D$58*(1+$A$7)^(P54-$D$54)),0) -> 53
C59: 45 a 54 Años | D59: =+'POBLACION DEMANDANTE POTENCIAL'!D82*80% -> 43.2 | E59: =ROUND(($D$59*(1+$A$7)^(E54-$D$54)),0) -> 43 | F59: =ROUND(($D$59*(1+$A$7)^(F54-$D$54)),0) -> 43 | G59: =ROUND(($D$59*(1+$A$7)^(G54-$D$54)),0) -> 43 | H59: =ROUND(($D$59*(1+$A$7)^(H54-$D$54)),0) -> 43 | I59: =ROUND(($D$59*(1+$A$7)^(I54-$D$54)),0) -> 43 | J59: =ROUND(($D$59*(1+$A$7)^(J54-$D$54)),0) -> 43 | K59: =ROUND(($D$59*(1+$A$7)^(K54-$D$54)),0) -> 43 | L59: =ROUND(($D$59*(1+$A$7)^(L54-$D$54)),0) -> 43 | ... P59: =ROUND(($D$59*(1+$A$7)^(P54-$D$54)),0) -> 43
C60: 55 a 64 Años | D60: =+'POBLACION DEMANDANTE POTENCIAL'!D83*80% -> 36.8 | E60: =ROUND(($D$60*(1+$A$7)^(E54-$D$54)),0) -> 37 | F60: =ROUND(($D$60*(1+$A$7)^(F54-$D$54)),0) -> 37 | G60: =ROUND(($D$60*(1+$A$7)^(G54-$D$54)),0) -> 37 | H60: =ROUND(($D$60*(1+$A$7)^(H54-$D$54)),0) -> 37 | I60: =ROUND(($D$60*(1+$A$7)^(I54-$D$54)),0) -> 37 | J60: =ROUND(($D$60*(1+$A$7)^(J54-$D$54)),0) -> 37 | K60: =ROUND(($D$60*(1+$A$7)^(K54-$D$54)),0) -> 37 | L60: =ROUND(($D$60*(1+$A$7)^(L54-$D$54)),0) -> 37 | ... P60: =ROUND(($D$60*(1+$A$7)^(P54-$D$54)),0) -> 37
C61: > 65 Años | D61: =+'POBLACION DEMANDANTE POTENCIAL'!D84*80% -> 45.6 | E61: =ROUND(($D$61*(1+$A$7)^(E54-$D$54)),0) -> 46 | F61: =ROUND(($D$61*(1+$A$7)^(F54-$D$54)),0) -> 46 | G61: =ROUND(($D$61*(1+$A$7)^(G54-$D$54)),0) -> 46 | H61: =ROUND(($D$61*(1+$A$7)^(H54-$D$54)),0) -> 46 | I61: =ROUND(($D$61*(1+$A$7)^(I54-$D$54)),0) -> 46 | J61: =ROUND(($D$61*(1+$A$7)^(J54-$D$54)),0) -> 46 | K61: =ROUND(($D$61*(1+$A$7)^(K54-$D$54)),0) -> 46 | L61: =ROUND(($D$61*(1+$A$7)^(L54-$D$54)),0) -> 46 | ... P61: =ROUND(($D$61*(1+$A$7)^(P54-$D$54)),0) -> 46
C64: POBLACION SUJETO DE INTERVENCION (PERSONAS EN SUS DIFERENTES ETAPAS DE VIDA) | D64: PERIODO DE INVERSION | G64: PERIODO DE POST INVERSION
D65: 0 | G65: 1 | H65: 2 | I65: 3 | J65: 4 | K65: 5 | L65: 6 | M65: 7 | N65: 8 | O65: 9 | P65: 10
D66: =+D54 -> 2024 | E66: =+E54 -> 2025 | F66: =+F54 -> 2026 | G66: =+G54 -> 2027 | H66: =+H54 -> 2028 | I66: =+I54 -> 2029 | J66: =+J54 -> 2030 | K66: =+K54 -> 2031 | ... P66: =+P54 -> 2036
C67: CONSEJERIA DE ITS/VIH/SIDA (> 18 años) | D67: =+SUM(D68:D73) -> 291.2 | E67: =+SUM(E68:E73) -> 292 | F67: =+SUM(F68:F73) -> 292 | G67: =+SUM(G68:G73) -> 292 | H67: =+SUM(H68:H73) -> 292 | I67: =+SUM(I68:I73) -> 292 | J67: =+SUM(J68:J73) -> 292 | K67: =+SUM(K68:K73) -> 292 | ... P67: =+SUM(P68:P73) -> 292
C68: 18 a 24 Años | D68: =+'POBLACION DEMANDANTE POTENCIAL'!D91*80% -> 43.2 | E68: =ROUND(($D$68*(1+$A$7)^(E66-$D$66)),0) -> 43 | F68: =ROUND(($D$68*(1+$A$7)^(F66-$D$66)),0) -> 43 | G68: =ROUND(($D$68*(1+$A$7)^(G66-$D$66)),0) -> 43 | H68: =ROUND(($D$68*(1+$A$7)^(H66-$D$66)),0) -> 43 | I68: =ROUND(($D$68*(1+$A$7)^(I66-$D$66)),0) -> 43 | J68: =ROUND(($D$68*(1+$A$7)^(J66-$D$66)),0) -> 43 | K68: =ROUND(($D$68*(1+$A$7)^(K66-$D$66)),0) -> 43 | L68: =ROUND(($D$68*(1+$A$7)^(L66-$D$66)),0) -> 43 | ... P68: =ROUND(($D$68*(1+$A$7)^(P66-$D$66)),0) -> 43
C69: 25 a 34 Años | D69: =+'POBLACION DEMANDANTE POTENCIAL'!D92*80% -> 69.6 | E69: =ROUND(($D$69*(1+$A$7)^(E66-$D$66)),0) -> 70 | F69: =ROUND(($D$69*(1+$A$7)^(F66-$D$66)),0) -> 70 | G69: =ROUND(($D$69*(1+$A$7)^(G66-$D$66)),0) -> 70 | H69: =ROUND(($D$69*(1+$A$7)^(H66-$D$66)),0) -> 70 | I69: =ROUND(($D$69*(1+$A$7)^(I66-$D$66)),0) -> 70 | J69: =ROUND(($D$69*(1+$A$7)^(J66-$D$66)),0) -> 70 | K69: =ROUND(($D$69*(1+$A$7)^(K66-$D$66)),0) -> 70 | L69: =ROUND(($D$69*(1+$A$7)^(L66-$D$66)),0) -> 70 | ... P69: =ROUND(($D$69*(1+$A$7)^(P66-$D$66)),0) -> 70
C70: 35 a 44 Años | D70: =+'POBLACION DEMANDANTE POTENCIAL'!D93*80% -> 52.8 | E70: =ROUND(($D$70*(1+$A$7)^(E66-$D$66)),0) -> 53 | F70: =ROUND(($D$70*(1+$A$7)^(F66-$D$66)),0) -> 53 | G70: =ROUND(($D$70*(1+$A$7)^(G66-$D$66)),0) -> 53 | H70: =ROUND(($D$70*(1+$A$7)^(H66-$D$66)),0) -> 53 | I70: =ROUND(($D$70*(1+$A$7)^(I66-$D$66)),0) -> 53 | J70: =ROUND(($D$70*(1+$A$7)^(J66-$D$66)),0) -> 53 | K70: =ROUND(($D$70*(1+$A$7)^(K66-$D$66)),0) -> 53 | L70: =ROUND(($D$70*(1+$A$7)^(L66-$D$66)),0) -> 53 | ... P70: =ROUND(($D$70*(1+$A$7)^(P66-$D$66)),0) -> 53
C71: 45 a 54 Años | D71: =+'POBLACION DEMANDANTE POTENCIAL'!D94*80% -> 43.2 | E71: =ROUND(($D$71*(1+$A$7)^(E66-$D$66)),0) -> 43 | F71: =ROUND(($D$71*(1+$A$7)^(F66-$D$66)),0) -> 43 | G71: =ROUND(($D$71*(1+$A$7)^(G66-$D$66)),0) -> 43 | H71: =ROUND(($D$71*(1+$A$7)^(H66-$D$66)),0) -> 43 | I71: =ROUND(($D$71*(1+$A$7)^(I66-$D$66)),0) -> 43 | J71: =ROUND(($D$71*(1+$A$7)^(J66-$D$66)),0) -> 43 | K71: =ROUND(($D$71*(1+$A$7)^(K66-$D$66)),0) -> 43 | L71: =ROUND(($D$71*(1+$A$7)^(L66-$D$66)),0) -> 43 | ... P71: =ROUND(($D$71*(1+$A$7)^(P66-$D$66)),0) -> 43
C72: 55 a 64 Años | D72: =+'POBLACION DEMANDANTE POTENCIAL'!D95*80% -> 36.8 | E72: =ROUND(($D$72*(1+$A$7)^(E66-$D$66)),0) -> 37 | F72: =ROUND(($D$72*(1+$A$7)^(F66-$D$66)),0) -> 37 | G72: =ROUND(($D$72*(1+$A$7)^(G66-$D$66)),0) -> 37 | H72: =ROUND(($D$72*(1+$A$7)^(H66-$D$66)),0) -> 37 | I72: =ROUND(($D$72*(1+$A$7)^(I66-$D$66)),0) -> 37 | J72: =ROUND(($D$72*(1+$A$7)^(J66-$D$66)),0) -> 37 | K72: =ROUND(($D$72*(1+$A$7)^(K66-$D$66)),0) -> 37 | L72: =ROUND(($D$72*(1+$A$7)^(L66-$D$66)),0) -> 37 | ... P72: =ROUND(($D$72*(1+$A$7)^(P66-$D$66)),0) -> 37
C73: > 65 Años | D73: =+'POBLACION DEMANDANTE POTENCIAL'!D96*80% -> 45.6 | E73: =ROUND(($D$73*(1+$A$7)^(E66-$D$66)),0) -> 46 | F73: =ROUND(($D$73*(1+$A$7)^(F66-$D$66)),0) -> 46 | G73: =ROUND(($D$73*(1+$A$7)^(G66-$D$66)),0) -> 46 | H73: =ROUND(($D$73*(1+$A$7)^(H66-$D$66)),0) -> 46 | I73: =ROUND(($D$73*(1+$A$7)^(I66-$D$66)),0) -> 46 | J73: =ROUND(($D$73*(1+$A$7)^(J66-$D$66)),0) -> 46 | K73: =ROUND(($D$73*(1+$A$7)^(K66-$D$66)),0) -> 46 | L73: =ROUND(($D$73*(1+$A$7)^(L66-$D$66)),0) -> 46 | ... P73: =ROUND(($D$73*(1+$A$7)^(P66-$D$66)),0) -> 46
C75: POBLACION SUJETO DE INTERVENCION (PERSONAS EN SUS DIFERENTES ETAPAS DE VIDA) | D75: PERIODO DE INVERSION | G75: PERIODO DE POST INVERSION
D76: 0 | G76: 1 | H76: 2 | I76: 3 | J76: 4 | K76: 5 | L76: 6 | M76: 7 | N76: 8 | O76: 9 | P76: 10
D77: =+D66 -> 2024 | E77: =+E66 -> 2025 | F77: =+F66 -> 2026 | G77: =+G66 -> 2027 | H77: =+H66 -> 2028 | I77: =+I66 -> 2029 | J77: =+J66 -> 2030 | K77: =+K66 -> 2031 | ... P77: =+P66 -> 2036
C78: CONSEJERIA DEL ADOLESCENTE ( 12 a 17 años) | D78: =+SUM(D79:D84) -> 31.2 | E78: =+SUM(E79:E84) -> 32 | F78: =+SUM(F79:F84) -> 32 | G78: =+SUM(G79:G84) -> 32 | H78: =+SUM(H79:H84) -> 32 | I78: =+SUM(I79:I84) -> 32 | J78: =+SUM(J79:J84) -> 32 | K78: =+SUM(K79:K84) -> 32 | ... P78: =+SUM(P79:P84) -> 32
C79: 12 años | D79: =+'POBLACION DEMANDANTE POTENCIAL'!D102*80% -> 5.6 | E79: =ROUND(($D$79*(1+$A$7)^(E77-$D$77)),0) -> 6 | F79: =ROUND(($D$79*(1+$A$7)^(F77-$D$77)),0) -> 6 | G79: =ROUND(($D$79*(1+$A$7)^(G77-$D$77)),0) -> 6 | H79: =ROUND(($D$79*(1+$A$7)^(H77-$D$77)),0) -> 6 | I79: =ROUND(($D$79*(1+$A$7)^(I77-$D$77)),0) -> 6 | J79: =ROUND(($D$79*(1+$A$7)^(J77-$D$77)),0) -> 6 | K79: =ROUND(($D$79*(1+$A$7)^(K77-$D$77)),0) -> 6 | L79: =ROUND(($D$79*(1+$A$7)^(L77-$D$77)),0) -> 6 | ... P79: =ROUND(($D$79*(1+$A$7)^(P77-$D$77)),0) -> 6
C80: 13 años | D80: =+'POBLACION DEMANDANTE POTENCIAL'!D103*80% -> 7.2 | E80: =ROUND(($D$80*(1+$A$7)^(E77-$D$77)),0) -> 7 | F80: =ROUND(($D$80*(1+$A$7)^(F77-$D$77)),0) -> 7 | G80: =ROUND(($D$80*(1+$A$7)^(G77-$D$77)),0) -> 7 | H80: =ROUND(($D$80*(1+$A$7)^(H77-$D$77)),0) -> 7 | I80: =ROUND(($D$80*(1+$A$7)^(I77-$D$77)),0) -> 7 | J80: =ROUND(($D$80*(1+$A$7)^(J77-$D$77)),0) -> 7 | K80: =ROUND(($D$80*(1+$A$7)^(K77-$D$77)),0) -> 7 | L80: =ROUND(($D$80*(1+$A$7)^(L77-$D$77)),0) -> 7 | ... P80: =ROUND(($D$80*(1+$A$7)^(P77-$D$77)),0) -> 7
C81: 14 años | D81: =+'POBLACION DEMANDANTE POTENCIAL'!D104*80% -> 5.6 | E81: =ROUND(($D$81*(1+$A$7)^(E77-$D$77)),0) -> 6 | F81: =ROUND(($D$81*(1+$A$7)^(F77-$D$77)),0) -> 6 | G81: =ROUND(($D$81*(1+$A$7)^(G77-$D$77)),0) -> 6 | H81: =ROUND(($D$81*(1+$A$7)^(H77-$D$77)),0) -> 6 | I81: =ROUND(($D$81*(1+$A$7)^(I77-$D$77)),0) -> 6 | J81: =ROUND(($D$81*(1+$A$7)^(J77-$D$77)),0) -> 6 | K81: =ROUND(($D$81*(1+$A$7)^(K77-$D$77)),0) -> 6 | L81: =ROUND(($D$81*(1+$A$7)^(L77-$D$77)),0) -> 6 | ... P81: =ROUND(($D$81*(1+$A$7)^(P77-$D$77)),0) -> 6
C82: 15 años | D82: =+'POBLACION DEMANDANTE POTENCIAL'!D105*80% -> 4 | E82: =ROUND(($D$82*(1+$A$7)^(E77-$D$77)),0) -> 4 | F82: =ROUND(($D$82*(1+$A$7)^(F77-$D$77)),0) -> 4 | G82: =ROUND(($D$82*(1+$A$7)^(G77-$D$77)),0) -> 4 | H82: =ROUND(($D$82*(1+$A$7)^(H77-$D$77)),0) -> 4 | I82: =ROUND(($D$82*(1+$A$7)^(I77-$D$77)),0) -> 4 | J82: =ROUND(($D$82*(1+$A$7)^(J77-$D$77)),0) -> 4 | K82: =ROUND(($D$82*(1+$A$7)^(K77-$D$77)),0) -> 4 | L82: =ROUND(($D$82*(1+$A$7)^(L77-$D$77)),0) -> 4 | ... P82: =ROUND(($D$82*(1+$A$7)^(P77-$D$77)),0) -> 4
C83: 16 años | D83: =+'POBLACION DEMANDANTE POTENCIAL'!D106*80% -> 4.8 | E83: =ROUND(($D$83*(1+$A$7)^(E77-$D$77)),0) -> 5 | F83: =ROUND(($D$83*(1+$A$7)^(F77-$D$77)),0) -> 5 | G83: =ROUND(($D$83*(1+$A$7)^(G77-$D$77)),0) -> 5 | H83: =ROUND(($D$83*(1+$A$7)^(H77-$D$77)),0) -> 5 | I83: =ROUND(($D$83*(1+$A$7)^(I77-$D$77)),0) -> 5 | J83: =ROUND(($D$83*(1+$A$7)^(J77-$D$77)),0) -> 5 | K83: =ROUND(($D$83*(1+$A$7)^(K77-$D$77)),0) -> 5 | L83: =ROUND(($D$83*(1+$A$7)^(L77-$D$77)),0) -> 5 | ... P83: =ROUND(($D$83*(1+$A$7)^(P77-$D$77)),0) -> 5
C84: 17 años | D84: =+'POBLACION DEMANDANTE POTENCIAL'!D107*80% -> 4 | E84: =ROUND(($D$84*(1+$A$7)^(E77-$D$77)),0) -> 4 | F84: =ROUND(($D$84*(1+$A$7)^(F77-$D$77)),0) -> 4 | G84: =ROUND(($D$84*(1+$A$7)^(G77-$D$77)),0) -> 4 | H84: =ROUND(($D$84*(1+$A$7)^(H77-$D$77)),0) -> 4 | I84: =ROUND(($D$84*(1+$A$7)^(I77-$D$77)),0) -> 4 | J84: =ROUND(($D$84*(1+$A$7)^(J77-$D$77)),0) -> 4 | K84: =ROUND(($D$84*(1+$A$7)^(K77-$D$77)),0) -> 4 | L84: =ROUND(($D$84*(1+$A$7)^(L77-$D$77)),0) -> 4 | ... P84: =ROUND(($D$84*(1+$A$7)^(P77-$D$77)),0) -> 4
C86: POBLACION SUJETO DE INTERVENCION | D86: PERIODO DE INVERSION | G86: PERIODO DE POST INVERSION
D87: 0 | G87: 1 | H87: 2 | I87: 3 | J87: 4 | K87: 5 | L87: 6 | M87: 7 | N87: 8 | O87: 9 | P87: 10
D88: 2024 | E88: 2025 | F88: 2026 | G88: 2027 | H88: 2028 | I88: 2029 | J88: 2030 | K88: 2031 | L88: 2032 | M88: 2033 | N88: 2034 | O88: 2035 | P88: 2036
C89: ADULTO MAYOR (> 18 años) | D89: =SUM(D90:D95) -> 291.2 | E89: =SUM(E90:E95) -> 292 | F89: =SUM(F90:F95) -> 292 | G89: =SUM(G90:G95) -> 292 | H89: =SUM(H90:H95) -> 292 | I89: =SUM(I90:I95) -> 292 | J89: =SUM(J90:J95) -> 292 | K89: =SUM(K90:K95) -> 292 | ... P89: =SUM(P90:P95) -> 292
C90: 18 a 24 Años | D90: =+'POBLACION DEMANDANTE POTENCIAL'!D113*80% -> 43.2 | E90: =ROUND(($D$90*(1+$A$7)^(E88-$D$88)),0) -> 43 | F90: =ROUND(($D$90*(1+$A$7)^(F88-$D$88)),0) -> 43 | G90: =ROUND(($D$90*(1+$A$7)^(G88-$D$88)),0) -> 43 | H90: =ROUND(($D$90*(1+$A$7)^(H88-$D$88)),0) -> 43 | I90: =ROUND(($D$90*(1+$A$7)^(I88-$D$88)),0) -> 43 | J90: =ROUND(($D$90*(1+$A$7)^(J88-$D$88)),0) -> 43 | K90: =ROUND(($D$90*(1+$A$7)^(K88-$D$88)),0) -> 43 | L90: =ROUND(($D$90*(1+$A$7)^(L88-$D$88)),0) -> 43 | ... P90: =ROUND(($D$90*(1+$A$7)^(P88-$D$88)),0) -> 43
C91: 25 a 34 Años | D91: =+'POBLACION DEMANDANTE POTENCIAL'!D114*80% -> 69.6 | E91: =ROUND(($D$91*(1+$A$7)^(E88-$D$88)),0) -> 70 | F91: =ROUND(($D$91*(1+$A$7)^(F88-$D$88)),0) -> 70 | G91: =ROUND(($D$91*(1+$A$7)^(G88-$D$88)),0) -> 70 | H91: =ROUND(($D$91*(1+$A$7)^(H88-$D$88)),0) -> 70 | I91: =ROUND(($D$91*(1+$A$7)^(I88-$D$88)),0) -> 70 | J91: =ROUND(($D$91*(1+$A$7)^(J88-$D$88)),0) -> 70 | K91: =ROUND(($D$91*(1+$A$7)^(K88-$D$88)),0) -> 70 | L91: =ROUND(($D$91*(1+$A$7)^(L88-$D$88)),0) -> 70 | ... P91: =ROUND(($D$91*(1+$A$7)^(P88-$D$88)),0) -> 70
C92: 35 a 44 Años | D92: =+'POBLACION DEMANDANTE POTENCIAL'!D115*80% -> 52.8 | E92: =ROUND(($D$92*(1+$A$7)^(E88-$D$88)),0) -> 53 | F92: =ROUND(($D$92*(1+$A$7)^(F88-$D$88)),0) -> 53 | G92: =ROUND(($D$92*(1+$A$7)^(G88-$D$88)),0) -> 53 | H92: =ROUND(($D$92*(1+$A$7)^(H88-$D$88)),0) -> 53 | I92: =ROUND(($D$92*(1+$A$7)^(I88-$D$88)),0) -> 53 | J92: =ROUND(($D$92*(1+$A$7)^(J88-$D$88)),0) -> 53 | K92: =ROUND(($D$92*(1+$A$7)^(K88-$D$88)),0) -> 53 | L92: =ROUND(($D$92*(1+$A$7)^(L88-$D$88)),0) -> 53 | ... P92: =ROUND(($D$92*(1+$A$7)^(P88-$D$88)),0) -> 53
C93: 45 a 54 Años | D93: =+'POBLACION DEMANDANTE POTENCIAL'!D116*80% -> 43.2 | E93: =ROUND(($D$93*(1+$A$7)^(E88-$D$88)),0) -> 43 | F93: =ROUND(($D$93*(1+$A$7)^(F88-$D$88)),0) -> 43 | G93: =ROUND(($D$93*(1+$A$7)^(G88-$D$88)),0) -> 43 | H93: =ROUND(($D$93*(1+$A$7)^(H88-$D$88)),0) -> 43 | I93: =ROUND(($D$93*(1+$A$7)^(I88-$D$88)),0) -> 43 | J93: =ROUND(($D$93*(1+$A$7)^(J88-$D$88)),0) -> 43 | K93: =ROUND(($D$93*(1+$A$7)^(K88-$D$88)),0) -> 43 | L93: =ROUND(($D$93*(1+$A$7)^(L88-$D$88)),0) -> 43 | ... P93: =ROUND(($D$93*(1+$A$7)^(P88-$D$88)),0) -> 43
C94: 55 a 64 Años | D94: =+'POBLACION DEMANDANTE POTENCIAL'!D117*80% -> 36.8 | E94: =ROUND(($D$94*(1+$A$7)^(E88-$D$88)),0) -> 37 | F94: =ROUND(($D$94*(1+$A$7)^(F88-$D$88)),0) -> 37 | G94: =ROUND(($D$94*(1+$A$7)^(G88-$D$88)),0) -> 37 | H94: =ROUND(($D$94*(1+$A$7)^(H88-$D$88)),0) -> 37 | I94: =ROUND(($D$94*(1+$A$7)^(I88-$D$88)),0) -> 37 | J94: =ROUND(($D$94*(1+$A$7)^(J88-$D$88)),0) -> 37 | K94: =ROUND(($D$94*(1+$A$7)^(K88-$D$88)),0) -> 37 | L94: =ROUND(($D$94*(1+$A$7)^(L88-$D$88)),0) -> 37 | ... P94: =ROUND(($D$94*(1+$A$7)^(P88-$D$88)),0) -> 37
C95: > 65 Años | D95: =+'POBLACION DEMANDANTE POTENCIAL'!D118*80% -> 45.6 | E95: =ROUND(($D$95*(1+$A$7)^(E88-$D$88)),0) -> 46 | F95: =ROUND(($D$95*(1+$A$7)^(F88-$D$88)),0) -> 46 | G95: =ROUND(($D$95*(1+$A$7)^(G88-$D$88)),0) -> 46 | H95: =ROUND(($D$95*(1+$A$7)^(H88-$D$88)),0) -> 46 | I95: =ROUND(($D$95*(1+$A$7)^(I88-$D$88)),0) -> 46 | J95: =ROUND(($D$95*(1+$A$7)^(J88-$D$88)),0) -> 46 | K95: =ROUND(($D$95*(1+$A$7)^(K88-$D$88)),0) -> 46 | L95: =ROUND(($D$95*(1+$A$7)^(L88-$D$88)),0) -> 46 | ... P95: =ROUND(($D$95*(1+$A$7)^(P88-$D$88)),0) -> 46
C97: POBLACION SUJETO DE INTERVENCION (PERSONAS EN SUS DIFERENTES ETAPAS DE VIDA) | D97: PERIODO DE INVERSION | G97: PERIODO DE POST INVERSION
D98: 0 | G98: 1 | H98: 2 | I98: 3 | J98: 4 | K98: 5 | L98: 6 | M98: 7 | N98: 8 | O98: 9 | P98: 10
D99: =+D77 -> 2024 | E99: =+E77 -> 2025 | F99: =+F77 -> 2026 | G99: =+G77 -> 2027 | H99: =+H77 -> 2028 | I99: =+I77 -> 2029 | J99: =+J77 -> 2030 | K99: =+K77 -> 2031 | ... P99: =+P77 -> 2036
C100: CONSEJERIA Y PREVENCION DE ENFERMEDADES NO TRASMISIBLES (> 18 años) | D100: =+SUM(D101:D106) -> 291.2 | E100: =+SUM(E101:E106) -> 292 | F100: =+SUM(F101:F106) -> 292 | G100: =+SUM(G101:G106) -> 292 | H100: =+SUM(H101:H106) -> 292 | I100: =+SUM(I101:I106) -> 292 | J100: =+SUM(J101:J106) -> 292 | K100: =+SUM(K101:K106) -> 292 | ... P100: =+SUM(P101:P106) -> 292
C101: 18 a 24 Años | D101: =+'POBLACION DEMANDANTE POTENCIAL'!D124*80% -> 43.2 | E101: =ROUND(($D$101*(1+$A$7)^(E99-$D$99)),0) -> 43 | F101: =ROUND(($D$101*(1+$A$7)^(F99-$D$99)),0) -> 43 | G101: =ROUND(($D$101*(1+$A$7)^(G99-$D$99)),0) -> 43 | H101: =ROUND(($D$101*(1+$A$7)^(H99-$D$99)),0) -> 43 | I101: =ROUND(($D$101*(1+$A$7)^(I99-$D$99)),0) -> 43 | J101: =ROUND(($D$101*(1+$A$7)^(J99-$D$99)),0) -> 43 | K101: =ROUND(($D$101*(1+$A$7)^(K99-$D$99)),0) -> 43 | L101: =ROUND(($D$101*(1+$A$7)^(L99-$D$99)),0) -> 43 | ... P101: =ROUND(($D$101*(1+$A$7)^(P99-$D$99)),0) -> 43
C102: 25 a 34 Años | D102: =+'POBLACION DEMANDANTE POTENCIAL'!D125*80% -> 69.6 | E102: =ROUND(($D$102*(1+$A$7)^(E99-$D$99)),0) -> 70 | F102: =ROUND(($D$102*(1+$A$7)^(F99-$D$99)),0) -> 70 | G102: =ROUND(($D$102*(1+$A$7)^(G99-$D$99)),0) -> 70 | H102: =ROUND(($D$102*(1+$A$7)^(H99-$D$99)),0) -> 70 | I102: =ROUND(($D$102*(1+$A$7)^(I99-$D$99)),0) -> 70 | J102: =ROUND(($D$102*(1+$A$7)^(J99-$D$99)),0) -> 70 | K102: =ROUND(($D$102*(1+$A$7)^(K99-$D$99)),0) -> 70 | L102: =ROUND(($D$102*(1+$A$7)^(L99-$D$99)),0) -> 70 | ... P102: =ROUND(($D$102*(1+$A$7)^(P99-$D$99)),0) -> 70
C103: 35 a 44 Años | D103: =+'POBLACION DEMANDANTE POTENCIAL'!D126*80% -> 52.8 | E103: =ROUND(($D$103*(1+$A$7)^(E99-$D$99)),0) -> 53 | F103: =ROUND(($D$103*(1+$A$7)^(F99-$D$99)),0) -> 53 | G103: =ROUND(($D$103*(1+$A$7)^(G99-$D$99)),0) -> 53 | H103: =ROUND(($D$103*(1+$A$7)^(H99-$D$99)),0) -> 53 | I103: =ROUND(($D$103*(1+$A$7)^(I99-$D$99)),0) -> 53 | J103: =ROUND(($D$103*(1+$A$7)^(J99-$D$99)),0) -> 53 | K103: =ROUND(($D$103*(1+$A$7)^(K99-$D$99)),0) -> 53 | L103: =ROUND(($D$103*(1+$A$7)^(L99-$D$99)),0) -> 53 | ... P103: =ROUND(($D$103*(1+$A$7)^(P99-$D$99)),0) -> 53
C104: 45 a 54 Años | D104: =+'POBLACION DEMANDANTE POTENCIAL'!D127*80% -> 43.2 | E104: =ROUND(($D$104*(1+$A$7)^(E99-$D$99)),0) -> 43 | F104: =ROUND(($D$104*(1+$A$7)^(F99-$D$99)),0) -> 43 | G104: =ROUND(($D$104*(1+$A$7)^(G99-$D$99)),0) -> 43 | H104: =ROUND(($D$104*(1+$A$7)^(H99-$D$99)),0) -> 43 | I104: =ROUND(($D$104*(1+$A$7)^(I99-$D$99)),0) -> 43 | J104: =ROUND(($D$104*(1+$A$7)^(J99-$D$99)),0) -> 43 | K104: =ROUND(($D$104*(1+$A$7)^(K99-$D$99)),0) -> 43 | L104: =ROUND(($D$104*(1+$A$7)^(L99-$D$99)),0) -> 43 | ... P104: =ROUND(($D$104*(1+$A$7)^(P99-$D$99)),0) -> 43
C105: 55 a 64 Años | D105: =+'POBLACION DEMANDANTE POTENCIAL'!D128*80% -> 36.8 | E105: =ROUND(($D$105*(1+$A$7)^(E99-$D$99)),0) -> 37 | F105: =ROUND(($D$105*(1+$A$7)^(F99-$D$99)),0) -> 37 | G105: =ROUND(($D$105*(1+$A$7)^(G99-$D$99)),0) -> 37 | H105: =ROUND(($D$105*(1+$A$7)^(H99-$D$99)),0) -> 37 | I105: =ROUND(($D$105*(1+$A$7)^(I99-$D$99)),0) -> 37 | J105: =ROUND(($D$105*(1+$A$7)^(J99-$D$99)),0) -> 37 | K105: =ROUND(($D$105*(1+$A$7)^(K99-$D$99)),0) -> 37 | L105: =ROUND(($D$105*(1+$A$7)^(L99-$D$99)),0) -> 37 | ... P105: =ROUND(($D$105*(1+$A$7)^(P99-$D$99)),0) -> 37
C106: > 65 Años | D106: =+'POBLACION DEMANDANTE POTENCIAL'!D129*80% -> 45.6 | E106: =ROUND(($D$106*(1+$A$7)^(E99-$D$99)),0) -> 46 | F106: =ROUND(($D$106*(1+$A$7)^(F99-$D$99)),0) -> 46 | G106: =ROUND(($D$106*(1+$A$7)^(G99-$D$99)),0) -> 46 | H106: =ROUND(($D$106*(1+$A$7)^(H99-$D$99)),0) -> 46 | I106: =ROUND(($D$106*(1+$A$7)^(I99-$D$99)),0) -> 46 | J106: =ROUND(($D$106*(1+$A$7)^(J99-$D$99)),0) -> 46 | K106: =ROUND(($D$106*(1+$A$7)^(K99-$D$99)),0) -> 46 | L106: =ROUND(($D$106*(1+$A$7)^(L99-$D$99)),0) -> 46 | ... P106: =ROUND(($D$106*(1+$A$7)^(P99-$D$99)),0) -> 46
C108: POBLACION SUJETO DE INTERVENCION | D108: PERIODO DE INVERSION | G108: PERIODO DE POST INVERSION
D109: 0 | G109: 1 | H109: 2 | I109: 3 | J109: 4 | K109: 5 | L109: 6 | M109: 7 | N109: 8 | O109: 9 | P109: 10
D110: 2024 | E110: 2025 | F110: 2026 | G110: 2027 | H110: 2028 | I110: 2029 | J110: 2030 | K110: 2031 | L110: 2032 | M110: 2033 | N110: 2034 | O110: 2035 | P110: 2036
C111: CONTROL PRE NATAL | D111: =SUM(D112:D112) -> 14.4 | E111: =SUM(E112:E112) -> 14 | F111: =SUM(F112:F112) -> 14 | G111: =SUM(G112:G112) -> 14 | H111: =SUM(H112:H112) -> 14 | I111: =SUM(I112:I112) -> 14 | J111: =SUM(J112:J112) -> 14 | K111: =SUM(K112:K112) -> 14 | ... P111: =SUM(P112:P112) -> 14
C112: Gestantes | D112: =+'POBLACION DEMANDANTE POTENCIAL'!D135*80% -> 14.4 | E112: =ROUND(($D$112*(1+$A$7)^(E110-$D$110)),0) -> 14 | F112: =ROUND(($D$112*(1+$A$7)^(F110-$D$110)),0) -> 14 | G112: =ROUND(($D$112*(1+$A$7)^(G110-$D$110)),0) -> 14 | H112: =ROUND(($D$112*(1+$A$7)^(H110-$D$110)),0) -> 14 | I112: =ROUND(($D$112*(1+$A$7)^(I110-$D$110)),0) -> 14 | J112: =ROUND(($D$112*(1+$A$7)^(J110-$D$110)),0) -> 14 | K112: =ROUND(($D$112*(1+$A$7)^(K110-$D$110)),0) -> 14 | L112: =ROUND(($D$112*(1+$A$7)^(L110-$D$110)),0) -> 14 | ... P112: =ROUND(($D$112*(1+$A$7)^(P110-$D$110)),0) -> 14
C114: POBLACION SUJETO DE INTERVENCION | D114: PERIODO DE INVERSION | G114: PERIODO DE POST INVERSION
D115: 0 | G115: 1 | H115: 2 | I115: 3 | J115: 4 | K115: 5 | L115: 6 | M115: 7 | N115: 8 | O115: 9 | P115: 10
D116: 2024 | E116: 2025 | F116: 2026 | G116: 2027 | H116: 2028 | I116: 2029 | J116: 2030 | K116: 2031 | L116: 2032 | M116: 2033 | N116: 2034 | O116: 2035 | P116: 2036
C117: PLANIFICACION FAMILIAR (MEF DE 15 a 49 años) | D117: =SUM(D118:D119) -> 201.6 | E117: =SUM(E118:E119) -> 201 | F117: =SUM(F118:F119) -> 202 | G117: =SUM(G118:G119) -> 202 | H117: =SUM(H118:H119) -> 202 | I117: =SUM(I118:I119) -> 202 | J117: =SUM(J118:J119) -> 202 | K117: =SUM(K118:K119) -> 202 | ... P117: =SUM(P118:P119) -> 202
...

Sheet DEMANDA SERV. DE SALUD SN PY
A1: =+Hoja3!C23 -> 0.0019 | B1: DEMANDA DE LOS SERVICIOS DE SALUD: ATENCIONES DE PROMOCION (SIN PROYECTO)
C3: RATIO DE CONCENTRACION
C4: ATENCIONES PREVENTIVAS | D4: GRUPOS | E4: CONCENTRACION (DE ATENCION/PERSONA) SIN PROYECTO
C5: MEDICINA GENERAL | D5: =+C11 -> 0 a 85 años a mas | E5: 2
C7: POBLACION SUJETO DE INTERVENCION (PERSONAS EN SUS DIFERENTES ETAPAS DE VIDA) | D7: PERIODO DE INVERSION | G7: PERIODO DE POST INVERSION
D8: 0 | G8: 1 | H8: 2 | I8: 3 | J8: 4 | K8: 5 | L8: 6 | M8: 7 | N8: 8 | O8: 9 | P8: 10
A9: =+'POBLACION DEMANDANTE EFECTIVA'!A7 -> 0.0003 | D9: 2024 | E9: 2025 | F9: 2026 | G9: 2027 | H9: 2028 | I9: 2029 | J9: 2030 | K9: 2031 | L9: 2032 | M9: 2033 | N9: 2034 | O9: 2035 | P9: 2036
C10: Medicina General | D10: =+D11 -> 340.704 | E10: =+E11 -> 341 | F10: =+F11 -> 341 | G10: =+G11 -> 341 | H10: =+H11 -> 341 | I10: =+I11 -> 341 | J10: =+J11 -> 341 | K10: =+K11 -> 341 | ... P10: =+P11 -> 342
C11: 0 a 85 años a mas | D11: =+'POBLACION DEMANDANTE EFECTIVA'!D9*E5 -> 340.704 | E11: =ROUND(($D$11*(1+$A$9)^(E9-$D$9)),0) -> 341 | F11: =ROUND(($D$11*(1+$A$9)^(F9-$D$9)),0) -> 341 | G11: =ROUND(($D$11*(1+$A$9)^(G9-$D$9)),0) -> 341 | H11: =ROUND(($D$11*(1+$A$9)^(H9-$D$9)),0) -> 341 | I11: =ROUND(($D$11*(1+$A$9)^(I9-$D$9)),0) -> 341 | J11: =ROUND(($D$11*(1+$A$9)^(J9-$D$9)),0) -> 341 | K11: =ROUND(($D$11*(1+$A$9)^(K9-$D$9)),0) -> 341 | L11: =ROUND(($D$11*(1+$A$9)^(L9-$D$9)),0) -> 342 | ... P11: =ROUND(($D$11*(1+$A$9)^(P9-$D$9)),0) -> 342
C13: RATIO DE CONCENTRACION
C14: ATENCIONES PREVENTIVAS | D14: GRUPOS | E14: CONCENTRACION (DE ATENCION/PERSONA) SIN PROYECTO
C15: TELECONSULTA MEDICA | D15: =+C21 -> 0 a 85 años a mas | E15: 1
C17: POBLACION SUJETO DE INTERVENCION (PERSONAS EN SUS DIFERENTES ETAPAS DE VIDA) | D17: PERIODO DE INVERSION | G17: PERIODO DE POST INVERSION
D18: 0 | G18: 1 | H18: 2 | I18: 3 | J18: 4 | K18: 5 | L18: 6 | M18: 7 | N18: 8 | O18: 9 | P18: 10
D19: 2024 | E19: 2025 | F19: 2026 | G19: 2027 | H19: 2028 | I19: 2029 | J19: 2030 | K19: 2031 | L19: 2032 | M19: 2033 | N19: 2034 | O19: 2035 | P19: 2036
C20: Teleconsulta medica | D20: =+D21 -> 170.352 | E20: =+E21 -> 170 | F20: =+F21 -> 170 | G20: =+G21 -> 171 | H20: =+H21 -> 171 | I20: =+I21 -> 171 | J20: =+J21 -> 171 | K20: =+K21 -> 171 | ... P20: =+P21 -> 171
C21: 0 a 85 años a mas | D21: =+'POBLACION DEMANDANTE EFECTIVA'!D15*E15 -> 170.352 | E21: =ROUND(($D$21*(1+$A$9)^(E19-$D$19)),0) -> 170 | F21: =ROUND(($D$21*(1+$A$9)^(F19-$D$19)),0) -> 170 | G21: =ROUND(($D$21*(1+$A$9)^(G19-$D$19)),0) -> 171 | H21: =ROUND(($D$21*(1+$A$9)^(H19-$D$19)),0) -> 171 | I21: =ROUND(($D$21*(1+$A$9)^(I19-$D$19)),0) -> 171 | J21: =ROUND(($D$21*(1+$A$9)^(J19-$D$19)),0) -> 171 | K21: =ROUND(($D$21*(1+$A$9)^(K19-$D$19)),0) -> 171 | L21: =ROUND(($D$21*(1+$A$9)^(L19-$D$19)),0) -> 171 | ... P21: =ROUND(($D$21*(1+$A$9)^(P19-$D$19)),0) -> 171
C23: RATIO DE CONCENTRACION
C24: ATENCIONES PREVENTIVAS | D24: GRUPOS | E24: CONCENTRACION (DE ATENCION/PERSONA) SIN PROYECTO
C25: CONTROLES DE CRECIMIENTO Y DESARROLLO (CRED) | D25: < de 29 dias | E25: 2
D26: < de 1 año | E26: 6
D27: 1 año | E27: 4
D28: 2 años | E28: 2
D29: 3 años | E29: 2
D30: 4 años | E30: 2
D31: 5 a 11 años | E31: 1
C33: POBLACION SUJETO DE INTERVENCION | D33: PERIODO DE INVERSION | G33: PERIODO DE POST INVERSION
D34: 0 | G34: 1 | H34: 2 | I34: 3 | J34: 4 | K34: 5 | L34: 6 | M34: 7 | N34: 8 | O34: 9 | P34: 10
D35: =+D19 -> 2024 | E35: =+E19 -> 2025 | F35: =+F19 -> 2026 | G35: =+G19 -> 2027 | H35: =+H19 -> 2028 | I35: =+I19 -> 2029 | J35: =+J19 -> 2030 | K35: =+K19 -> 2031 | ... P35: =+P19 -> 2036
C36: CRED (< de 11 años) | D36: =+SUM(D37:D43) -> 160.8 | E36: =+SUM(E37:E43) -> 162 | F36: =+SUM(F37:F43) -> 162 | G36: =+SUM(G37:G43) -> 162 | H36: =+SUM(H37:H43) -> 162 | I36: =+SUM(I37:I43) -> 162 | J36: =+SUM(J37:J43) -> 162 | K36: =+SUM(K37:K43) -> 162 | ... P36: =+SUM(P37:P43) -> 162
C37: < de 29 dias | D37: =+'POBLACION DEMANDANTE EFECTIVA'!D21*E25 -> 4.8 | E37: =ROUND(($D$37*(1+$A$9)^(E35-$D$35)),0) -> 5 | F37: =ROUND(($D$37*(1+$A$9)^(F35-$D$35)),0) -> 5 | G37: =ROUND(($D$37*(1+$A$9)^(G35-$D$35)),0) -> 5 | H37: =ROUND(($D$37*(1+$A$9)^(H35-$D$35)),0) -> 5 | I37: =ROUND(($D$37*(1+$A$9)^(I35-$D$35)),0) -> 5 | J37: =ROUND(($D$37*(1+$A$9)^(J35-$D$35)),0) -> 5 | K37: =ROUND(($D$37*(1+$A$9)^(K35-$D$35)),0) -> 5 | L37: =ROUND(($D$37*(1+$A$9)^(L35-$D$35)),0) -> 5 | ... P37: =ROUND(($D$37*(1+$A$9)^(P35-$D$35)),0) -> 5
C38: < de 1 año | D38: =+'POBLACION DEMANDANTE EFECTIVA'!D22*E26 -> 33.6 | E38: =ROUND(($D$38*(1+$A$9)^(E35-$D$35)),0) -> 34 | F38: =ROUND(($D$38*(1+$A$9)^(F35-$D$35)),0) -> 34 | G38: =ROUND(($D$38*(1+$A$9)^(G35-$D$35)),0) -> 34 | H38: =ROUND(($D$38*(1+$A$9)^(H35-$D$35)),0) -> 34 | I38: =ROUND(($D$38*(1+$A$9)^(I35-$D$35)),0) -> 34 | J38: =ROUND(($D$38*(1+$A$9)^(J35-$D$35)),0) -> 34 | K38: =ROUND(($D$38*(1+$A$9)^(K35-$D$35)),0) -> 34 | L38: =ROUND(($D$38*(1+$A$9)^(L35-$D$35)),0) -> 34 | ... P38: =ROUND(($D$38*(1+$A$9)^(P35-$D$35)),0) -> 34
C39: 1 año | D39: =+'POBLACION DEMANDANTE EFECTIVA'!D23*E27 -> 16 | E39: =ROUND(($D$39*(1+$A$9)^(E35-$D$35)),0) -> 16 | F39: =ROUND(($D$39*(1+$A$9)^(F35-$D$35)),0) -> 16 | G39: =ROUND(($D$39*(1+$A$9)^(G35-$D$35)),0) -> 16 | H39: =ROUND(($D$39*(1+$A$9)^(H35-$D$35)),0) -> 16 | I39: =ROUND(($D$39*(1+$A$9)^(I35-$D$35)),0) -> 16 | J39: =ROUND(($D$39*(1+$A$9)^(J35-$D$35)),0) -> 16 | K39: =ROUND(($D$39*(1+$A$9)^(K35-$D$35)),0) -> 16 | L39: =ROUND(($D$39*(1+$A$9)^(L35-$D$35)),0) -> 16 | ... P39: =ROUND(($D$39*(1+$A$9)^(P35-$D$35)),0) -> 16
C40: 2 años | D40: =+'POBLACION DEMANDANTE EFECTIVA'!D24*E28 -> 20.8 | E40: =ROUND(($D$40*(1+$A$9)^(E35-$D$35)),0) -> 21 | F40: =ROUND(($D$40*(1+$A$9)^(F35-$D$35)),0) -> 21 | G40: =ROUND(($D$40*(1+$A$9)^(G35-$D$35)),0) -> 21 | H40: =ROUND(($D$40*(1+$A$9)^(H35-$D$35)),0) -> 21 | I40: =ROUND(($D$40*(1+$A$9)^(I35-$D$35)),0) -> 21 | J40: =ROUND(($D$40*(1+$A$9)^(J35-$D$35)),0) -> 21 | K40: =ROUND(($D$40*(1+$A$9)^(K35-$D$35)),0) -> 21 | L40: =ROUND(($D$40*(1+$A$9)^(L35-$D$35)),0) -> 21 | ... P40: =ROUND(($D$40*(1+$A$9)^(P35-$D$35)),0) -> 21
C41: 3 años | D41: =+'POBLACION DEMANDANTE EFECTIVA'!D25*E29 -> 24 | E41: =ROUND(($D$41*(1+$A$9)^(E35-$D$35)),0) -> 24 | F41: =ROUND(($D$41*(1+$A$9)^(F35-$D$35)),0) -> 24 | G41: =ROUND(($D$41*(1+$A$9)^(G35-$D$35)),0) -> 24 | H41: =ROUND(($D$41*(1+$A$9)^(H35-$D$35)),0) -> 24 | I41: =ROUND(($D$41*(1+$A$9)^(I35-$D$35)),0) -> 24 | J41: =ROUND(($D$41*(1+$A$9)^(J35-$D$35)),0) -> 24 | K41: =ROUND(($D$41*(1+$A$9)^(K35-$D$35)),0) -> 24 | L41: =ROUND(($D$41*(1+$A$9)^(L35-$D$35)),0) -> 24 | ... P41: =ROUND(($D$41*(1+$A$9)^(P35-$D$35)),0) -> 24
C42: 4 años | D42: =+'POBLACION DEMANDANTE EFECTIVA'!D26*E30 -> 20.8 | E42: =ROUND(($D$42*(1+$A$9)^(E35-$D$35)),0) -> 21 | F42: =ROUND(($D$42*(1+$A$9)^(F35-$D$35)),0) -> 21 | G42: =ROUND(($D$42*(1+$A$9)^(G35-$D$35)),0) -> 21 | H42: =ROUND(($D$42*(1+$A$9)^(H35-$D$35)),0) -> 21 | I42: =ROUND(($D$42*(1+$A$9)^(I35-$D$35)),0) -> 21 | J42: =ROUND(($D$42*(1+$A$9)^(J35-$D$35)),0) -> 21 | K42: =ROUND(($D$42*(1+$A$9)^(K35-$D$35)),0) -> 21 | L42: =ROUND(($D$42*(1+$A$9)^(L35-$D$35)),0) -> 21 | ... P42: =ROUND(($D$42*(1+$A$9)^(P35-$D$35)),0) -> 21
C43: 5 a 11 años | D43: =+'POBLACION DEMANDANTE EFECTIVA'!D27*E31 -> 40.8 | E43: =ROUND(($D$43*(1+$A$9)^(E35-$D$35)),0) -> 41 | F43: =ROUND(($D$43*(1+$A$9)^(F35-$D$35)),0) -> 41 | G43: =ROUND(($D$43*(1+$A$9)^(G35-$D$35)),0) -> 41 | H43: =ROUND(($D$43*(1+$A$9)^(H35-$D$35)),0) -> 41 | I43: =ROUND(($D$43*(1+$A$9)^(I35-$D$35)),0) -> 41 | J43: =ROUND(($D$43*(1+$A$9)^(J35-$D$35)),0) -> 41 | K43: =ROUND(($D$43*(1+$A$9)^(K35-$D$35)),0) -> 41 | L43: =ROUND(($D$43*(1+$A$9)^(L35-$D$35)),0) -> 41 | ... P43: =ROUND(($D$43*(1+$A$9)^(P35-$D$35)),0) -> 41
C45: RATIO DE CONCENTRACION
C46: ATENCIONES PREVENTIVAS | D46: GRUPOS | E46: CONCENTRACION (DE ATENCION/PERSONA) SIN PROYECTO
C47: ESTIMULACION TEMPRANA | D47: =+C57 -> < 29 dias | E47: 1
D48: =+C58 -> < 1 año | E48: 3
D49: =+C59 -> 1 años | E49: 2
D50: =+C60 -> 2 años | E50: 1
D51: =+C61 -> 3 años | E51: 1
C53: POBLACION SUJETO DE INTERVENCION | D53: PERIODO DE INVERSION | G53: PERIODO DE POST INVERSION
D54: 0 | G54: 1 | H54: 2 | I54: 3 | J54: 4 | K54: 5 | L54: 6 | M54: 7 | N54: 8 | O54: 9 | P54: 10
D55: =+D35 -> 2024 | E55: =+E35 -> 2025 | F55: =+F35 -> 2026 | G55: =+G35 -> 2027 | H55: =+H35 -> 2028 | I55: =+I35 -> 2029 | J55: =+J35 -> 2030 | K55: =+K35 -> 2031 | ... P55: =+P35 -> 2036
C56: ESTIMULACION TEMPRANA (< de 3 años) | D56: =+SUM(D57:D61) -> 49.6 | E56: =+SUM(E57:E61) -> 49 | F56: =+SUM(F57:F61) -> 49 | G56: =+SUM(G57:G61) -> 49 | H56: =+SUM(H57:H61) -> 49 | I56: =+SUM(I57:I61) -> 49 | J56: =+SUM(J57:J61) -> 49 | K56: =+SUM(K57:K61) -> 49 | ... P56: =+SUM(P57:P61) -> 49
C57: < 29 dias | D57: =+'POBLACION DEMANDANTE EFECTIVA'!D33*E47 -> 2.4 | E57: =ROUND(($D$57*(1+$A$9)^(E55-$D$55)),0) -> 2 | F57: =ROUND(($D$57*(1+$A$9)^(F55-$D$55)),0) -> 2 | G57: =ROUND(($D$57*(1+$A$9)^(G55-$D$55)),0) -> 2 | H57: =ROUND(($D$57*(1+$A$9)^(H55-$D$55)),0) -> 2 | I57: =ROUND(($D$57*(1+$A$9)^(I55-$D$55)),0) -> 2 | J57: =ROUND(($D$57*(1+$A$9)^(J55-$D$55)),0) -> 2 | K57: =ROUND(($D$57*(1+$A$9)^(K55-$D$55)),0) -> 2 | L57: =ROUND(($D$57*(1+$A$9)^(L55-$D$55)),0) -> 2 | ... P57: =ROUND(($D$57*(1+$A$9)^(P55-$D$55)),0) -> 2
C58: < 1 año | D58: =+'POBLACION DEMANDANTE EFECTIVA'!D34*E48 -> 16.8 | E58: =ROUND(($D$58*(1+$A$9)^(E55-$D$55)),0) -> 17 | F58: =ROUND(($D$58*(1+$A$9)^(F55-$D$55)),0) -> 17 | G58: =ROUND(($D$58*(1+$A$9)^(G55-$D$55)),0) -> 17 | H58: =ROUND(($D$58*(1+$A$9)^(H55-$D$55)),0) -> 17 | I58: =ROUND(($D$58*(1+$A$9)^(I55-$D$55)),0) -> 17 | J58: =ROUND(($D$58*(1+$A$9)^(J55-$D$55)),0) -> 17 | K58: =ROUND(($D$58*(1+$A$9)^(K55-$D$55)),0) -> 17 | L58: =ROUND(($D$58*(1+$A$9)^(L55-$D$55)),0) -> 17 | ... P58: =ROUND(($D$58*(1+$A$9)^(P55-$D$55)),0) -> 17
C59: 1 años | D59: =+'POBLACION DEMANDANTE EFECTIVA'!D35*E49 -> 8 | E59: =ROUND(($D$59*(1+$A$9)^(E55-$D$55)),0) -> 8 | F59: =ROUND(($D$59*(1+$A$9)^(F55-$D$55)),0) -> 8 | G59: =ROUND(($D$59*(1+$A$9)^(G55-$D$55)),0) -> 8 | H59: =ROUND(($D$59*(1+$A$9)^(H55-$D$55)),0) -> 8 | I59: =ROUND(($D$59*(1+$A$9)^(I55-$D$55)),0) -> 8 | J59: =ROUND(($D$59*(1+$A$9)^(J55-$D$55)),0) -> 8 | K59: =ROUND(($D$59*(1+$A$9)^(K55-$D$55)),0) -> 8 | L59: =ROUND(($D$59*(1+$A$9)^(L55-$D$55)),0) -> 8 | ... P59: =ROUND(($D$59*(1+$A$9)^(P55-$D$55)),0) -> 8
C60: 2 años | D60: =+'POBLACION DEMANDANTE EFECTIVA'!D36*E50 -> 10.4 | E60: =ROUND(($D$60*(1+$A$9)^(E55-$D$55)),0) -> 10 | F60: =ROUND(($D$60*(1+$A$9)^(F55-$D$55)),0) -> 10 | G60: =ROUND(($D$60*(1+$A$9)^(G55-$D$55)),0) -> 10 | H60: =ROUND(($D$60*(1+$A$9)^(H55-$D$55)),0) -> 10 | I60: =ROUND(($D$60*(1+$A$9)^(I55-$D$55)),0) -> 10 | J60: =ROUND(($D$60*(1+$A$9)^(J55-$D$55)),0) -> 10 | K60: =ROUND(($D$60*(1+$A$9)^(K55-$D$55)),0) -> 10 | L60: =ROUND(($D$60*(1+$A$9)^(L55-$D$55)),0) -> 10 | ... P60: =ROUND(($D$60*(1+$A$9)^(P55-$D$55)),0) -> 10
C61: 3 años | D61: =+'POBLACION DEMANDANTE EFECTIVA'!D37*E51 -> 12 | E61: =ROUND(($D$61*(1+$A$9)^(E55-$D$55)),0) -> 12 | F61: =ROUND(($D$61*(1+$A$9)^(F55-$D$55)),0) -> 12 | G61: =ROUND(($D$61*(1+$A$9)^(G55-$D$55)),0) -> 12 | H61: =ROUND(($D$61*(1+$A$9)^(H55-$D$55)),0) -> 12 | I61: =ROUND(($D$61*(1+$A$9)^(I55-$D$55)),0) -> 12 | J61: =ROUND(($D$61*(1+$A$9)^(J55-$D$55)),0) -> 12 | K61: =ROUND(($D$61*(1+$A$9)^(K55-$D$55)),0) -> 12 | L61: =ROUND(($D$61*(1+$A$9)^(L55-$D$55)),0) -> 12 | ... P61: =ROUND(($D$61*(1+$A$9)^(P55-$D$55)),0) -> 12
C63: RATIO DE CONCENTRACION
C64: ATENCIONES PREVENTIVAS | D64: GRUPOS | E64: CONCENTRACION (VACUNAS/PERSONA) SIN PROYECTO
C65: INMUNIZACIONES | D65: < de 1 año | E65: 3
D66: 1 año | E66: 3
D67: 2 años | E67: 1
D68: 3 años | E68: 1
D69: 4 años | E69: 1
D70: Gestantes | E70: 2
C72: POBLACION SUJETO DE INTERVENCION | D72: PERIODO DE INVERSION | G72: PERIODO DE POST INVERSION
D73: 0 | G73: 1 | H73: 2 | I73: 3 | J73: 4 | K73: 5 | L73: 6 | M73: 7 | N73: 8 | O73: 9 | P73: 10
D74: 2024 | E74: 2025 | F74: 2026 | G74: 2027 | H74: 2028 | I74: 2029 | J74: 2030 | K74: 2031 | L74: 2032 | M74: 2033 | N74: 2034 | O74: 2035 | P74: 2036
C75: INMUNIZACIONES (< de 4 años, Gestantes) | D75: =+SUM(D76:D81) -> 90.4 | E75: =+SUM(E76:E81) -> 90 | F75: =+SUM(F76:F81) -> 90 | G75: =+SUM(G76:G81) -> 90 | H75: =+SUM(H76:H81) -> 90 | I75: =+SUM(I76:I81) -> 90 | J75: =+SUM(J76:J81) -> 90 | K75: =+SUM(K76:K81) -> 90 | ... P75: =+SUM(P76:P81) -> 90
C76: < 1 año | D76: =+'POBLACION DEMANDANTE EFECTIVA'!D43*E65 -> 16.8 | E76: =ROUND(($D$76*(1+$A$9)^(E74-$D$74)),0) -> 17 | F76: =ROUND(($D$76*(1+$A$9)^(F74-$D$74)),0) -> 17 | G76: =ROUND(($D$76*(1+$A$9)^(G74-$D$74)),0) -> 17 | H76: =ROUND(($D$76*(1+$A$9)^(H74-$D$74)),0) -> 17 | I76: =ROUND(($D$76*(1+$A$9)^(I74-$D$74)),0) -> 17 | J76: =ROUND(($D$76*(1+$A$9)^(J74-$D$74)),0) -> 17 | K76: =ROUND(($D$76*(1+$A$9)^(K74-$D$74)),0) -> 17 | L76: =ROUND(($D$76*(1+$A$9)^(L74-$D$74)),0) -> 17 | ... P76: =ROUND(($D$76*(1+$A$9)^(P74-$D$74)),0) -> 17
C77: 1 año | D77: =+'POBLACION DEMANDANTE EFECTIVA'!D44*E66 -> 12 | E77: =ROUND(($D$77*(1+$A$9)^(E74-$D$74)),0) -> 12 | F77: =ROUND(($D$77*(1+$A$9)^(F74-$D$74)),0) -> 12 | G77: =ROUND(($D$77*(1+$A$9)^(G74-$D$74)),0) -> 12 | H77: =ROUND(($D$77*(1+$A$9)^(H74-$D$74)),0) -> 12 | I77: =ROUND(($D$77*(1+$A$9)^(I74-$D$74)),0) -> 12 | J77: =ROUND(($D$77*(1+$A$9)^(J74-$D$74)),0) -> 12 | K77: =ROUND(($D$77*(1+$A$9)^(K74-$D$74)),0) -> 12 | L77: =ROUND(($D$77*(1+$A$9)^(L74-$D$74)),0) -> 12 | ... P77: =ROUND(($D$77*(1+$A$9)^(P74-$D$74)),0) -> 12
C78: 2 años | D78: =+'POBLACION DEMANDANTE EFECTIVA'!D45*E67 -> 10.4 | E78: =ROUND(($D$78*(1+$A$9)^(E74-$D$74)),0) -> 10 | F78: =ROUND(($D$78*(1+$A$9)^(F74-$D$74)),0) -> 10 | G78: =ROUND(($D$78*(1+$A$9)^(G74-$D$74)),0) -> 10 | H78: =ROUND(($D$78*(1+$A$9)^(H74-$D$74)),0) -> 10 | I78: =ROUND(($D$78*(1+$A$9)^(I74-$D$74)),0) -> 10 | J78: =ROUND(($D$78*(1+$A$9)^(J74-$D$74)),0) -> 10 | K78: =ROUND(($D$78*(1+$A$9)^(K74-$D$74)),0) -> 10 | L78: =ROUND(($D$78*(1+$A$9)^(L74-$D$74)),0) -> 10 | ... P78: =ROUND(($D$78*(1+$A$9)^(P74-$D$74)),0) -> 10
C79: 3 años | D79: =+'POBLACION DEMANDANTE EFECTIVA'!D46*E68 -> 12 | E79: =ROUND(($D$79*(1+$A$9)^(E74-$D$74)),0) -> 12 | F79: =ROUND(($D$79*(1+$A$9)^(F74-$D$74)),0) -> 12 | G79: =ROUND(($D$79*(1+$A$9)^(G74-$D$74)),0) -> 12 | H79: =ROUND(($D$79*(1+$A$9)^(H74-$D$74)),0) -> 12 | I79: =ROUND(($D$79*(1+$A$9)^(I74-$D$74)),0) -> 12 | J79: =ROUND(($D$79*(1+$A$9)^(J74-$D$74)),0) -> 12 | K79: =ROUND(($D$79*(1+$A$9)^(K74-$D$74)),0) -> 12 | L79: =ROUND(($D$79*(1+$A$9)^(L74-$D$74)),0) -> 12 | ... P79: =ROUND(($D$79*(1+$A$9)^(P74-$D$74)),0) -> 12
C80: 4 años | D80: =+'POBLACION DEMANDANTE EFECTIVA'!D47*E69 -> 10.4 | E80: =ROUND(($D$80*(1+$A$9)^(E74-$D$74)),0) -> 10 | F80: =ROUND(($D$80*(1+$A$9)^(F74-$D$74)),0) -> 10 | G80: =ROUND(($D$80*(1+$A$9)^(G74-$D$74)),0) -> 10 | H80: =ROUND(($D$80*(1+$A$9)^(H74-$D$74)),0) -> 10 | I80: =ROUND(($D$80*(1+$A$9)^(I74-$D$74)),0) -> 10 | J80: =ROUND(($D$80*(1+$A$9)^(J74-$D$74)),0) -> 10 | K80: =ROUND(($D$80*(1+$A$9)^(K74-$D$74)),0) -> 10 | L80: =ROUND(($D$80*(1+$A$9)^(L74-$D$74)),0) -> 10 | ... P80: =ROUND(($D$80*(1+$A$9)^(P74-$D$74)),0) -> 10
C81: Gestantes | D81: =+'POBLACION DEMANDANTE EFECTIVA'!D48*E70 -> 28.8 | E81: =ROUND(($D$81*(1+$A$9)^(E74-$D$74)),0) -> 29 | F81: =ROUND(($D$81*(1+$A$9)^(F74-$D$74)),0) -> 29 | G81: =ROUND(($D$81*(1+$A$9)^(G74-$D$74)),0) -> 29 | H81: =ROUND(($D$81*(1+$A$9)^(H74-$D$74)),0) -> 29 | I81: =ROUND(($D$81*(1+$A$9)^(I74-$D$74)),0) -> 29 | J81: =ROUND(($D$81*(1+$A$9)^(J74-$D$74)),0) -> 29 | K81: =ROUND(($D$81*(1+$A$9)^(K74-$D$74)),0) -> 29 | L81: =ROUND(($D$81*(1+$A$9)^(L74-$D$74)),0) -> 29 | ... P81: =ROUND(($D$81*(1+$A$9)^(P74-$D$74)),0) -> 29
C83: RATIO DE CONCENTRACION
C84: ATENCIONES DE PROMOCION DE LA SALUD | D84: GRUPOS | E84: CONCENTRACION (DE ATENCION/PERSONA) SIN PROYECTO
C85: CONSEJERIA DE TBC | D85: 18 a 24 Años | E85: 1
D86: 25 a 34 Años | E86: 1
D87: 35 a 44 Años | E87: 1
D88: 45 a 54 Años | E88: 1
D89: 55 a 64 Años | E89: 1
D90: > 65 Años | E90: 1
C92: POBLACION SUJETO DE INTERVENCION (PERSONAS EN SUS DIFERENTES ETAPAS DE VIDA) | D92: PERIODO DE INVERSION | G92: PERIODO DE POST INVERSION
D93: 0 | G93: 1 | H93: 2 | I93: 3 | J93: 4 | K93: 5 | L93: 6 | M93: 7 | N93: 8 | O93: 9 | P93: 10
D94: 2024 | E94: 2025 | F94: 2026 | G94: 2027 | H94: 2028 | I94: 2029 | J94: 2030 | K94: 2031 | L94: 2032 | M94: 2033 | N94: 2034 | O94: 2035 | P94: 2036
C95: CONSEJERIA Y PREVENCION DE TBC (> 18 años) | D95: =+SUM(D96:D101) -> 291.2 | E95: =+SUM(E96:E101) -> 292 | F95: =+SUM(F96:F101) -> 292 | G95: =+SUM(G96:G101) -> 292 | H95: =+SUM(H96:H101) -> 292 | I95: =+SUM(I96:I101) -> 292 | J95: =+SUM(J96:J101) -> 292 | K95: =+SUM(K96:K101) -> 292 | ... P95: =+SUM(P96:P101) -> 292
C96: 18 a 24 Años | D96: =+'POBLACION DEMANDANTE EFECTIVA'!D56*E85 -> 43.2 | E96: =ROUND(($D$96*(1+$A$9)^(E94-D94)),0) -> 43 | F96: =ROUND(($D$96*(1+$A$9)^(F94-E94)),0) -> 43 | G96: =ROUND(($D$96*(1+$A$9)^(G94-F94)),0) -> 43 | H96: =ROUND(($D$96*(1+$A$9)^(H94-G94)),0) -> 43 | I96: =ROUND(($D$96*(1+$A$9)^(I94-H94)),0) -> 43 | J96: =ROUND(($D$96*(1+$A$9)^(J94-I94)),0) -> 43 | K96: =ROUND(($D$96*(1+$A$9)^(K94-J94)),0) -> 43 | L96: =ROUND(($D$96*(1+$A$9)^(L94-K94)),0) -> 43 | ... P96: =ROUND(($D$96*(1+$A$9)^(P94-O94)),0) -> 43
C97: 25 a 34 Años | D97: =+'POBLACION DEMANDANTE EFECTIVA'!D57*E86 -> 69.6 | E97: =ROUND(($D$97*(1+$A$9)^(E94-D94)),0) -> 70 | F97: =ROUND(($D$97*(1+$A$9)^(F94-E94)),0) -> 70 | G97: =ROUND(($D$97*(1+$A$9)^(G94-F94)),0) -> 70 | H97: =ROUND(($D$97*(1+$A$9)^(H94-G94)),0) -> 70 | I97: =ROUND(($D$97*(1+$A$9)^(I94-H94)),0) -> 70 | J97: =ROUND(($D$97*(1+$A$9)^(J94-I94)),0) -> 70 | K97: =ROUND(($D$97*(1+$A$9)^(K94-J94)),0) -> 70 | L97: =ROUND(($D$97*(1+$A$9)^(L94-K94)),0) -> 70 | ... P97: =ROUND(($D$97*(1+$A$9)^(P94-O94)),0) -> 70
C98: 35 a 44 Años | D98: =+'POBLACION DEMANDANTE EFECTIVA'!D58*E87 -> 52.8 | E98: =ROUND(($D$98*(1+$A$9)^(E94-D94)),0) -> 53 | F98: =ROUND(($D$98*(1+$A$9)^(F94-E94)),0) -> 53 | G98: =ROUND(($D$98*(1+$A$9)^(G94-F94)),0) -> 53 | H98: =ROUND(($D$98*(1+$A$9)^(H94-G94)),0) -> 53 | I98: =ROUND(($D$98*(1+$A$9)^(I94-H94)),0) -> 53 | J98: =ROUND(($D$98*(1+$A$9)^(J94-I94)),0) -> 53 | K98: =ROUND(($D$98*(1+$A$9)^(K94-J94)),0) -> 53 | L98: =ROUND(($D$98*(1+$A$9)^(L94-K94)),0) -> 53 | ... P98: =ROUND(($D$98*(1+$A$9)^(P94-O94)),0) -> 53
C99: 45 a 54 Años | D99: =+'POBLACION DEMANDANTE EFECTIVA'!D59*E88 -> 43.2 | E99: =ROUND(($D$99*(1+$A$9)^(E94-D94)),0) -> 43 | F99: =ROUND(($D$99*(1+$A$9)^(F94-E94)),0) -> 43 | G99: =ROUND(($D$99*(1+$A$9)^(G94-F94)),0) -> 43 | H99: =ROUND(($D$99*(1+$A$9)^(H94-G94)),0) -> 43 | I99: =ROUND(($D$99*(1+$A$9)^(I94-H94)),0) -> 43 | J99: =ROUND(($D$99*(1+$A$9)^(J94-I94)),0) -> 43 | K99: =ROUND(($D$99*(1+$A$9)^(K94-J94)),0) -> 43 | L99: =ROUND(($D$99*(1+$A$9)^(L94-K94)),0) -> 43 | ... P99: =ROUND(($D$99*(1+$A$9)^(P94-O94)),0) -> 43
C100: 55 a 64 Años | D100: =+'POBLACION DEMANDANTE EFECTIVA'!D60*E89 -> 36.8 | E100: =ROUND(($D$100*(1+$A$9)^(E94-D94)),0) -> 37 | F100: =ROUND(($D$100*(1+$A$9)^(F94-E94)),0) -> 37 | G100: =ROUND(($D$100*(1+$A$9)^(G94-F94)),0) -> 37 | H100: =ROUND(($D$100*(1+$A$9)^(H94-G94)),0) -> 37 | I100: =ROUND(($D$100*(1+$A$9)^(I94-H94)),0) -> 37 | J100: =ROUND(($D$100*(1+$A$9)^(J94-I94)),0) -> 37 | K100: =ROUND(($D$100*(1+$A$9)^(K94-J94)),0) -> 37 | L100: =ROUND(($D$100*(1+$A$9)^(L94-K94)),0) -> 37 | ... P100: =ROUND(($D$100*(1+$A$9)^(P94-O94)),0) -> 37
C101: > 65 Años | D101: =+'POBLACION DEMANDANTE EFECTIVA'!D61*E90 -> 45.6 | E101: =ROUND(($D$101*(1+$A$9)^(E94-D94)),0) -> 46 | F101: =ROUND(($D$101*(1+$A$9)^(F94-E94)),0) -> 46 | G101: =ROUND(($D$101*(1+$A$9)^(G94-F94)),0) -> 46 | H101: =ROUND(($D$101*(1+$A$9)^(H94-G94)),0) -> 46 | I101: =ROUND(($D$101*(1+$A$9)^(I94-H94)),0) -> 46 | J101: =ROUND(($D$101*(1+$A$9)^(J94-I94)),0) -> 46 | K101: =ROUND(($D$101*(1+$A$9)^(K94-J94)),0) -> 46 | L101: =ROUND(($D$101*(1+$A$9)^(L94-K94)),0) -> 46 | ... P101: =ROUND(($D$101*(1+$A$9)^(P94-O94)),0) -> 46
C103: RATIO DE CONCENTRACION
C104: ATENCIONES DE PROMOCION DE LA SALUD | D104: GRUPOS | E104: CONCENTRACION (DE ATENCION/PERSONA) SIN PROYECTO
C105: CONSEJERIA DE ITS/VIH/SIDA (> 18 años) | D105: 18 a 24 Años | E105: 1
D106: 25 a 34 Años | E106: 1
D107: 35 a 44 Años | E107: 1
D108: 45 a 54 Años | E108: 1
D109: 55 a 64 Años | E109: 1
D110: > 65 Años | E110: 1
C112: POBLACION SUJETO DE INTERVENCION (PERSONAS EN SUS DIFERENTES ETAPAS DE VIDA) | D112: PERIODO DE INVERSION | G112: PERIODO DE POST INVERSION
D113: 0 | G113: 1 | H113: 2 | I113: 3 | J113: 4 | K113: 5 | L113: 6 | M113: 7 | N113: 8 | O113: 9 | P113: 10
D114: =+D94 -> 2024 | E114: =+E94 -> 2025 | F114: =+F94 -> 2026 | G114: =+G94 -> 2027 | H114: =+H94 -> 2028 | I114: =+I94 -> 2029 | J114: =+J94 -> 2030 | K114: =+K94 -> 2031 | ... P114: =+P94 -> 2036
...

Sheet DEMANDA SERV. DE SALUD CN PY
C3: RATIO DE CONCENTRACION
C4: ATENCIONES PREVENTIVAS | D4: GRUPOS | E4: CONCENTRACION (DE ATENCION/PERSONA) CON PROYECTO
C5: MEDICINA GENERAL | D5: =+C11 -> 0 a 85 años a mas | E5: 3
C7: POBLACION SUJETO DE INTERVENCION (PERSONAS EN SUS DIFERENTES ETAPAS DE VIDA) | D7: PERIODO DE INVERSION | G7: PERIODO DE POST INVERSION
D8: 0 | G8: 1 | H8: 2 | I8: 3 | J8: 4 | K8: 5 | L8: 6 | M8: 7 | N8: 8 | O8: 9 | P8: 10
A9: =+Hoja1!D17 -> 0.0003 | D9: 2024 | E9: 2025 | F9: 2026 | G9: 2027 | H9: 2028 | I9: 2029 | J9: 2030 | K9: 2031 | L9: 2032 | M9: 2033 | N9: 2034 | O9: 2035 | P9: 2036
C10: Medicina General | D10: =+D11 -> 511.056 | E10: =+E11 -> 511 | F10: =+F11 -> 511 | G10: =+G11 -> 512 | H10: =+H11 -> 512 | I10: =+I11 -> 512 | J10: =+J11 -> 512 | K10: =+K11 -> 512 | ... P10: =+P11 -> 513
C11: 0 a 85 años a mas | D11: =+'POBLACION DEMANDANTE EFECTIVA'!D9*E5 -> 511.056 | E11: =ROUND(($D$11*(1+$A$9)^(E9-$D$9)),0) -> 511 | F11: =ROUND(($D$11*(1+$A$9)^(F9-$D$9)),0) -> 511 | G11: =ROUND(($D$11*(1+$A$9)^(G9-$D$9)),0) -> 512 | H11: =ROUND(($D$11*(1+$A$9)^(H9-$D$9)),0) -> 512 | I11: =ROUND(($D$11*(1+$A$9)^(I9-$D$9)),0) -> 512 | J11: =ROUND(($D$11*(1+$A$9)^(J9-$D$9)),0) -> 512 | K11: =ROUND(($D$11*(1+$A$9)^(K9-$D$9)),0) -> 512 | L11: =ROUND(($D$11*(1+$A$9)^(L9-$D$9)),0) -> 512 | ... P11: =ROUND(($D$11*(1+$A$9)^(P9-$D$9)),0) -> 513
C13: RATIO DE CONCENTRACION
C14: ATENCIONES PREVENTIVAS | D14: GRUPOS | E14: CONCENTRACION (DE ATENCION/PERSONA) CON PROYECTO
C15: TELECONSULTA MEDICA | D15: =+C21 -> 0 a 85 años a mas | E15: 2
C17: POBLACION SUJETO DE INTERVENCION (PERSONAS EN SUS DIFERENTES ETAPAS DE VIDA) | D17: PERIODO DE INVERSION | G17: PERIODO DE POST INVERSION
D18: 0 | G18: 1 | H18: 2 | I18: 3 | J18: 4 | K18: 5 | L18: 6 | M18: 7 | N18: 8 | O18: 9 | P18: 10
D19: 2024 | E19: 2025 | F19: 2026 | G19: 2027 | H19: 2028 | I19: 2029 | J19: 2030 | K19: 2031 | L19: 2032 | M19: 2033 | N19: 2034 | O19: 2035 | P19: 2036
C20: Teleconsulta medica | D20: =+D21 -> 340.704 | E20: =+E21 -> 341 | F20: =+F21 -> 341 | G20: =+G21 -> 341 | H20: =+H21 -> 341 | I20: =+I21 -> 341 | J20: =+J21 -> 341 | K20: =+K21 -> 341 | ... P20: =+P21 -> 342
C21: 0 a 85 años a mas | D21: =+'POBLACION DEMANDANTE EFECTIVA'!D15*E15 -> 340.704 | E21: =ROUND(($D$21*(1+$A$9)^(E19-$D$19)),0) -> 341 | F21: =ROUND(($D$21*(1+$A$9)^(F19-$D$19)),0) -> 341 | G21: =ROUND(($D$21*(1+$A$9)^(G19-$D$19)),0) -> 341 | H21: =ROUND(($D$21*(1+$A$9)^(H19-$D$19)),0) -> 341 | I21: =ROUND(($D$21*(1+$A$9)^(I19-$D$19)),0) -> 341 | J21: =ROUND(($D$21*(1+$A$9)^(J19-$D$19)),0) -> 341 | K21: =ROUND(($D$21*(1+$A$9)^(K19-$D$19)),0) -> 341 | L21: =ROUND(($D$21*(1+$A$9)^(L19-$D$19)),0) -> 342 | ... P21: =ROUND(($D$21*(1+$A$9)^(P19-$D$19)),0) -> 342
C23: RATIO DE CONCENTRACION - ATENCIONES PREVENTIVAS
C24: ATENCIONES PREVENTIVAS | D24: GRUPOS | E24: CONCENTRACION (DE ATENCION/PERSONA) CON PROYECTO
C25: CONTROLES DE CRECIMIENTO Y DESARROLLO (CRED) | D25: < de 29 dias | E25: 2
D26: < de 1 año | E26: 6
D27: 1 año | E27: 4
D28: 2 años | E28: 2
D29: 3 años | E29: 2
D30: 4 años | E30: 2
D31: 5 a 11 años | E31: 1
C33: POBLACION SUJETO DE INTERVENCION | D33: PERIODO DE INVERSION | G33: PERIODO DE POST INVERSION
D34: 0 | G34: 1 | H34: 2 | I34: 3 | J34: 4 | K34: 5 | L34: 6 | M34: 7 | N34: 8 | O34: 9 | P34: 10
D35: =+D19 -> 2024 | E35: =+E19 -> 2025 | F35: =+F19 -> 2026 | G35: =+G19 -> 2027 | H35: =+H19 -> 2028 | I35: =+I19 -> 2029 | J35: =+J19 -> 2030 | K35: =+K19 -> 2031 | ... P35: =+P19 -> 2036
C36: CRED (< de 11 años) | D36: =+SUM(D37:D43) -> 160.8 | E36: =+SUM(E37:E43) -> 162 | F36: =+SUM(F37:F43) -> 162 | G36: =+SUM(G37:G43) -> 162 | H36: =+SUM(H37:H43) -> 162 | I36: =+SUM(I37:I43) -> 162 | J36: =+SUM(J37:J43) -> 162 | K36: =+SUM(K37:K43) -> 162 | ... P36: =+SUM(P37:P43) -> 162
C37: < de 29 dias | D37: =+'POBLACION DEMANDANTE EFECTIVA'!D21*E25 -> 4.8 | E37: =ROUND(($D$37*(1+$A$9)^(E35-$D$35)),0) -> 5 | F37: =ROUND(($D$37*(1+$A$9)^(F35-$D$35)),0) -> 5 | G37: =ROUND(($D$37*(1+$A$9)^(G35-$D$35)),0) -> 5 | H37: =ROUND(($D$37*(1+$A$9)^(H35-$D$35)),0) -> 5 | I37: =ROUND(($D$37*(1+$A$9)^(I35-$D$35)),0) -> 5 | J37: =ROUND(($D$37*(1+$A$9)^(J35-$D$35)),0) -> 5 | K37: =ROUND(($D$37*(1+$A$9)^(K35-$D$35)),0) -> 5 | L37: =ROUND(($D$37*(1+$A$9)^(L35-$D$35)),0) -> 5 | ... P37: =ROUND(($D$37*(1+$A$9)^(P35-$D$35)),0) -> 5
C38: < de 1 año | D38: =+'POBLACION DEMANDANTE EFECTIVA'!D22*E26 -> 33.6 | E38: =ROUND(($D$38*(1+$A$9)^(E35-$D$35)),0) -> 34 | F38: =ROUND(($D$38*(1+$A$9)^(F35-$D$35)),0) -> 34 | G38: =ROUND(($D$38*(1+$A$9)^(G35-$D$35)),0) -> 34 | H38: =ROUND(($D$38*(1+$A$9)^(H35-$D$35)),0) -> 34 | I38: =ROUND(($D$38*(1+$A$9)^(I35-$D$35)),0) -> 34 | J38: =ROUND(($D$38*(1+$A$9)^(J35-$D$35)),0) -> 34 | K38: =ROUND(($D$38*(1+$A$9)^(K35-$D$35)),0) -> 34 | L38: =ROUND(($D$38*(1+$A$9)^(L35-$D$35)),0) -> 34 | ... P38: =ROUND(($D$38*(1+$A$9)^(P35-$D$35)),0) -> 34
C39: 1 año | D39: =+'POBLACION DEMANDANTE EFECTIVA'!D23*E27 -> 16 | E39: =ROUND(($D$39*(1+$A$9)^(E35-$D$35)),0) -> 16 | F39: =ROUND(($D$39*(1+$A$9)^(F35-$D$35)),0) -> 16 | G39: =ROUND(($D$39*(1+$A$9)^(G35-$D$35)),0) -> 16 | H39: =ROUND(($D$39*(1+$A$9)^(H35-$D$35)),0) -> 16 | I39: =ROUND(($D$39*(1+$A$9)^(I35-$D$35)),0) -> 16 | J39: =ROUND(($D$39*(1+$A$9)^(J35-$D$35)),0) -> 16 | K39: =ROUND(($D$39*(1+$A$9)^(K35-$D$35)),0) -> 16 | L39: =ROUND(($D$39*(1+$A$9)^(L35-$D$35)),0) -> 16 | ... P39: =ROUND(($D$39*(1+$A$9)^(P35-$D$35)),0) -> 16
C40: 2 años | D40: =+'POBLACION DEMANDANTE EFECTIVA'!D24*E28 -> 20.8 | E40: =ROUND(($D$40*(1+$A$9)^(E35-$D$35)),0) -> 21 | F40: =ROUND(($D$40*(1+$A$9)^(F35-$D$35)),0) -> 21 | G40: =ROUND(($D$40*(1+$A$9)^(G35-$D$35)),0) -> 21 | H40: =ROUND(($D$40*(1+$A$9)^(H35-$D$35)),0) -> 21 | I40: =ROUND(($D$40*(1+$A$9)^(I35-$D$35)),0) -> 21 | J40: =ROUND(($D$40*(1+$A$9)^(J35-$D$35)),0) -> 21 | K40: =ROUND(($D$40*(1+$A$9)^(K35-$D$35)),0) -> 21 | L40: =ROUND(($D$40*(1+$A$9)^(L35-$D$35)),0) -> 21 | ... P40: =ROUND(($D$40*(1+$A$9)^(P35-$D$35)),0) -> 21
C41: 3 años | D41: =+'POBLACION DEMANDANTE EFECTIVA'!D25*E29 -> 24 | E41: =ROUND(($D$41*(1+$A$9)^(E35-$D$35)),0) -> 24 | F41: =ROUND(($D$41*(1+$A$9)^(F35-$D$35)),0) -> 24 | G41: =ROUND(($D$41*(1+$A$9)^(G35-$D$35)),0) -> 24 | H41: =ROUND(($D$41*(1+$A$9)^(H35-$D$35)),0) -> 24 | I41: =ROUND(($D$41*(1+$A$9)^(I35-$D$35)),0) -> 24 | J41: =ROUND(($D$41*(1+$A$9)^(J35-$D$35)),0) -> 24 | K41: =ROUND(($D$41*(1+$A$9)^(K35-$D$35)),0) -> 24 | L41: =ROUND(($D$41*(1+$A$9)^(L35-$D$35)),0) -> 24 | ... P41: =ROUND(($D$41*(1+$A$9)^(P35-$D$35)),0) -> 24
C42: 4 años | D42: =+'POBLACION DEMANDANTE EFECTIVA'!D26*E30 -> 20.8 | E42: =ROUND(($D$42*(1+$A$9)^(E35-$D$35)),0) -> 21 | F42: =ROUND(($D$42*(1+$A$9)^(F35-$D$35)),0) -> 21 | G42: =ROUND(($D$42*(1+$A$9)^(G35-$D$35)),0) -> 21 | H42: =ROUND(($D$42*(1+$A$9)^(H35-$D$35)),0) -> 21 | I42: =ROUND(($D$42*(1+$A$9)^(I35-$D$35)),0) -> 21 | J42: =ROUND(($D$42*(1+$A$9)^(J35-$D$35)),0) -> 21 | K42: =ROUND(($D$42*(1+$A$9)^(K35-$D$35)),0) -> 21 | L42: =ROUND(($D$42*(1+$A$9)^(L35-$D$35)),0) -> 21 | ... P42: =ROUND(($D$42*(1+$A$9)^(P35-$D$35)),0) -> 21
C43: 5 a 11 años | D43: =+'POBLACION DEMANDANTE EFECTIVA'!D27*E31 -> 40.8 | E43: =ROUND(($D$43*(1+$A$9)^(E35-$D$35)),0) -> 41 | F43: =ROUND(($D$43*(1+$A$9)^(F35-$D$35)),0) -> 41 | G43: =ROUND(($D$43*(1+$A$9)^(G35-$D$35)),0) -> 41 | H43: =ROUND(($D$43*(1+$A$9)^(H35-$D$35)),0) -> 41 | I43: =ROUND(($D$43*(1+$A$9)^(I35-$D$35)),0) -> 41 | J43: =ROUND(($D$43*(1+$A$9)^(J35-$D$35)),0) -> 41 | K43: =ROUND(($D$43*(1+$A$9)^(K35-$D$35)),0) -> 41 | L43: =ROUND(($D$43*(1+$A$9)^(L35-$D$35)),0) -> 41 | ... P43: =ROUND(($D$43*(1+$A$9)^(P35-$D$35)),0) -> 41
C45: RATIO DE CONCENTRACION
C46: ATENCIONES PREVENTIVAS | D46: GRUPOS | E46: CONCENTRACION (DE ATENCION/PERSONA) CON PROYECTO
C47: ESTIMULACION TEMPRANA | D47: =+C57 -> < 29 dias | E47: 2
D48: =+C58 -> < 1 año | E48: 4
D49: =+C59 -> 1 años | E49: 3
D50: =+C60 -> 2 años | E50: 2
D51: =+C61 -> 3 años | E51: 2
C53: POBLACION SUJETO DE INTERVENCION | D53: PERIODO DE INVERSION | G53: PERIODO DE POST INVERSION
D54: 0 | G54: 1 | H54: 2 | I54: 3 | J54: 4 | K54: 5 | L54: 6 | M54: 7 | N54: 8 | O54: 9 | P54: 10
D55: =+D35 -> 2024 | E55: =+E35 -> 2025 | F55: =+F35 -> 2026 | G55: =+G35 -> 2027 | H55: =+H35 -> 2028 | I55: =+I35 -> 2029 | J55: =+J35 -> 2030 | K55: =+K35 -> 2031 | ... P55: =+P35 -> 2036
C56: ESTIMULACION TEMPRANA (< de 3 años) | D56: =+SUM(D57:D61) -> 84 | E56: =+SUM(E57:E61) -> 84 | F56: =+SUM(F57:F61) -> 84 | G56: =+SUM(G57:G61) -> 84 | H56: =+SUM(H57:H61) -> 84 | I56: =+SUM(I57:I61) -> 84 | J56: =+SUM(J57:J61) -> 84 | K56: =+SUM(K57:K61) -> 84 | ... P56: =+SUM(P57:P61) -> 84
C57: < 29 dias | D57: =+'POBLACION DEMANDANTE EFECTIVA'!D33*E47 -> 4.8 | E57: =ROUND(($D$57*(1+$A$9)^(E55-$D$55)),0) -> 5 | F57: =ROUND(($D$57*(1+$A$9)^(F55-$D$55)),0) -> 5 | G57: =ROUND(($D$57*(1+$A$9)^(G55-$D$55)),0) -> 5 | H57: =ROUND(($D$57*(1+$A$9)^(H55-$D$55)),0) -> 5 | I57: =ROUND(($D$57*(1+$A$9)^(I55-$D$55)),0) -> 5 | J57: =ROUND(($D$57*(1+$A$9)^(J55-$D$55)),0) -> 5 | K57: =ROUND(($D$57*(1+$A$9)^(K55-$D$55)),0) -> 5 | L57: =ROUND(($D$57*(1+$A$9)^(L55-$D$55)),0) -> 5 | ... P57: =ROUND(($D$57*(1+$A$9)^(P55-$D$55)),0) -> 5
C58: < 1 año | D58: =+'POBLACION DEMANDANTE EFECTIVA'!D34*E48 -> 22.4 | E58: =ROUND(($D$58*(1+$A$9)^(E55-$D$55)),0) -> 22 | F58: =ROUND(($D$58*(1+$A$9)^(F55-$D$55)),0) -> 22 | G58: =ROUND(($D$58*(1+$A$9)^(G55-$D$55)),0) -> 22 | H58: =ROUND(($D$58*(1+$A$9)^(H55-$D$55)),0) -> 22 | I58: =ROUND(($D$58*(1+$A$9)^(I55-$D$55)),0) -> 22 | J58: =ROUND(($D$58*(1+$A$9)^(J55-$D$55)),0) -> 22 | K58: =ROUND(($D$58*(1+$A$9)^(K55-$D$55)),0) -> 22 | L58: =ROUND(($D$58*(1+$A$9)^(L55-$D$55)),0) -> 22 | ... P58: =ROUND(($D$58*(1+$A$9)^(P55-$D$55)),0) -> 22
C59: 1 años | D59: =+'POBLACION DEMANDANTE EFECTIVA'!D35*E49 -> 12 | E59: =ROUND(($D$59*(1+$A$9)^(E55-$D$55)),0) -> 12 | F59: =ROUND(($D$59*(1+$A$9)^(F55-$D$55)),0) -> 12 | G59: =ROUND(($D$59*(1+$A$9)^(G55-$D$55)),0) -> 12 | H59: =ROUND(($D$59*(1+$A$9)^(H55-$D$55)),0) -> 12 | I59: =ROUND(($D$59*(1+$A$9)^(I55-$D$55)),0) -> 12 | J59: =ROUND(($D$59*(1+$A$9)^(J55-$D$55)),0) -> 12 | K59: =ROUND(($D$59*(1+$A$9)^(K55-$D$55)),0) -> 12 | L59: =ROUND(($D$59*(1+$A$9)^(L55-$D$55)),0) -> 12 | ... P59: =ROUND(($D$59*(1+$A$9)^(P55-$D$55)),0) -> 12
C60: 2 años | D60: =+'POBLACION DEMANDANTE EFECTIVA'!D36*E50 -> 20.8 | E60: =ROUND(($D$60*(1+$A$9)^(E55-$D$55)),0) -> 21 | F60: =ROUND(($D$60*(1+$A$9)^(F55-$D$55)),0) -> 21 | G60: =ROUND(($D$60*(1+$A$9)^(G55-$D$55)),0) -> 21 | H60: =ROUND(($D$60*(1+$A$9)^(H55-$D$55)),0) -> 21 | I60: =ROUND(($D$60*(1+$A$9)^(I55-$D$55)),0) -> 21 | J60: =ROUND(($D$60*(1+$A$9)^(J55-$D$55)),0) -> 21 | K60: =ROUND(($D$60*(1+$A$9)^(K55-$D$55)),0) -> 21 | L60: =ROUND(($D$60*(1+$A$9)^(L55-$D$55)),0) -> 21 | ... P60: =ROUND(($D$60*(1+$A$9)^(P55-$D$55)),0) -> 21
C61: 3 años | D61: =+'POBLACION DEMANDANTE EFECTIVA'!D37*E51 -> 24 | E61: =ROUND(($D$61*(1+$A$9)^(E55-$D$55)),0) -> 24 | F61: =ROUND(($D$61*(1+$A$9)^(F55-$D$55)),0) -> 24 | G61: =ROUND(($D$61*(1+$A$9)^(G55-$D$55)),0) -> 24 | H61: =ROUND(($D$61*(1+$A$9)^(H55-$D$55)),0) -> 24 | I61: =ROUND(($D$61*(1+$A$9)^(I55-$D$55)),0) -> 24 | J61: =ROUND(($D$61*(1+$A$9)^(J55-$D$55)),0) -> 24 | K61: =ROUND(($D$61*(1+$A$9)^(K55-$D$55)),0) -> 24 | L61: =ROUND(($D$61*(1+$A$9)^(L55-$D$55)),0) -> 24 | ... P61: =ROUND(($D$61*(1+$A$9)^(P55-$D$55)),0) -> 24
C63: RATIO DE CONCENTRACION
C64: ATENCIONES PREVENTIVAS | D64: GRUPOS | E64: CONCENTRACION (VACUNAS/PERSONA) CON PROYECTO
C65: INMUNIZACIONES | D65: < de 1 año | E65: 3
D66: 1 año | E66: 3
D67: 2 años | E67: 1
D68: 3 años | E68: 1
D69: 4 años | E69: 1
D70: Gestantes | E70: 2
C72: POBLACION SUJETO DE INTERVENCION | D72: PERIODO DE INVERSION | G72: PERIODO DE POST INVERSION
D73: 0 | G73: 1 | H73: 2 | I73: 3 | J73: 4 | K73: 5 | L73: 6 | M73: 7 | N73: 8 | O73: 9 | P73: 10
D74: 2024 | E74: 2025 | F74: 2026 | G74: 2027 | H74: 2028 | I74: 2029 | J74: 2030 | K74: 2031 | L74: 2032 | M74: 2033 | N74: 2034 | O74: 2035 | P74: 2036
C75: INMUNIZACIONES (< de 4 años, Gestantes) | D75: =+SUM(D76:D81) -> 90.4 | E75: =+SUM(E76:E81) -> 90 | F75: =+SUM(F76:F81) -> 90 | G75: =+SUM(G76:G81) -> 90 | H75: =+SUM(H76:H81) -> 90 | I75: =+SUM(I76:I81) -> 90 | J75: =+SUM(J76:J81) -> 90 | K75: =+SUM(K76:K81) -> 90 | ... P75: =+SUM(P76:P81) -> 90
C76: < 1 año | D76: =+'POBLACION DEMANDANTE EFECTIVA'!D43*E65 -> 16.8 | E76: =ROUND(($D$76*(1+$A$9)^(E74-$D$74)),0) -> 17 | F76: =ROUND(($D$76*(1+$A$9)^(F74-$D$74)),0) -> 17 | G76: =ROUND(($D$76*(1+$A$9)^(G74-$D$74)),0) -> 17 | H76: =ROUND(($D$76*(1+$A$9)^(H74-$D$74)),0) -> 17 | I76: =ROUND(($D$76*(1+$A$9)^(I74-$D$74)),0) -> 17 | J76: =ROUND(($D$76*(1+$A$9)^(J74-$D$74)),0) -> 17 | K76: =ROUND(($D$76*(1+$A$9)^(K74-$D$74)),0) -> 17 | L76: =ROUND(($D$76*(1+$A$9)^(L74-$D$74)),0) -> 17 | ... P76: =ROUND(($D$76*(1+$A$9)^(P74-$D$74)),0) -> 17
C77: 1 año | D77: =+'POBLACION DEMANDANTE EFECTIVA'!D44*E66 -> 12 | E77: =ROUND(($D$77*(1+$A$9)^(E74-$D$74)),0) -> 12 | F77: =ROUND(($D$77*(1+$A$9)^(F74-$D$74)),0) -> 12 | G77: =ROUND(($D$77*(1+$A$9)^(G74-$D$74)),0) -> 12 | H77: =ROUND(($D$77*(1+$A$9)^(H74-$D$74)),0) -> 12 | I77: =ROUND(($D$77*(1+$A$9)^(I74-$D$74)),0) -> 12 | J77: =ROUND(($D$77*(1+$A$9)^(J74-$D$74)),0) -> 12 | K77: =ROUND(($D$77*(1+$A$9)^(K74-$D$74)),0) -> 12 | L77: =ROUND(($D$77*(1+$A$9)^(L74-$D$74)),0) -> 12 | ... P77: =ROUND(($D$77*(1+$A$9)^(P74-$D$74)),0) -> 12
C78: 2 años | D78: =+'POBLACION DEMANDANTE EFECTIVA'!D45*E67 -> 10.4 | E78: =ROUND(($D$78*(1+$A$9)^(E74-$D$74)),0) -> 10 | F78: =ROUND(($D$78*(1+$A$9)^(F74-$D$74)),0) -> 10 | G78: =ROUND(($D$78*(1+$A$9)^(G74-$D$74)),0) -> 10 | H78: =ROUND(($D$78*(1+$A$9)^(H74-$D$74)),0) -> 10 | I78: =ROUND(($D$78*(1+$A$9)^(I74-$D$74)),0) -> 10 | J78: =ROUND(($D$78*(1+$A$9)^(J74-$D$74)),0) -> 10 | K78: =ROUND(($D$78*(1+$A$9)^(K74-$D$74)),0) -> 10 | L78: =ROUND(($D$78*(1+$A$9)^(L74-$D$74)),0) -> 10 | ... P78: =ROUND(($D$78*(1+$A$9)^(P74-$D$74)),0) -> 10
C79: 3 años | D79: =+'POBLACION DEMANDANTE EFECTIVA'!D46*E68 -> 12 | E79: =ROUND(($D$79*(1+$A$9)^(E74-$D$74)),0) -> 12 | F79: =ROUND(($D$79*(1+$A$9)^(F74-$D$74)),0) -> 12 | G79: =ROUND(($D$79*(1+$A$9)^(G74-$D$74)),0) -> 12 | H79: =ROUND(($D$79*(1+$A$9)^(H74-$D$74)),0) -> 12 | I79: =ROUND(($D$79*(1+$A$9)^(I74-$D$74)),0) -> 12 | J79: =ROUND(($D$79*(1+$A$9)^(J74-$D$74)),0) -> 12 | K79: =ROUND(($D$79*(1+$A$9)^(K74-$D$74)),0) -> 12 | L79: =ROUND(($D$79*(1+$A$9)^(L74-$D$74)),0) -> 12 | ... P79: =ROUND(($D$79*(1+$A$9)^(P74-$D$74)),0) -> 12
C80: 4 años | D80: =+'POBLACION DEMANDANTE EFECTIVA'!D47*E69 -> 10.4 | E80: =ROUND(($D$80*(1+$A$9)^(E74-$D$74)),0) -> 10 | F80: =ROUND(($D$80*(1+$A$9)^(F74-$D$74)),0) -> 10 | G80: =ROUND(($D$80*(1+$A$9)^(G74-$D$74)),0) -> 10 | H80: =ROUND(($D$80*(1+$A$9)^(H74-$D$74)),0) -> 10 | I80: =ROUND(($D$80*(1+$A$9)^(I74-$D$74)),0) -> 10 | J80: =ROUND(($D$80*(1+$A$9)^(J74-$D$74)),0) -> 10 | K80: =ROUND(($D$80*(1+$A$9)^(K74-$D$74)),0) -> 10 | L80: =ROUND(($D$80*(1+$A$9)^(L74-$D$74)),0) -> 10 | ... P80: =ROUND(($D$80*(1+$A$9)^(P74-$D$74)),0) -> 10
C81: Gestantes | D81: =+'POBLACION DEMANDANTE EFECTIVA'!D48*E70 -> 28.8 | E81: =ROUND(($D$81*(1+$A$9)^(E74-$D$74)),0) -> 29 | F81: =ROUND(($D$81*(1+$A$9)^(F74-$D$74)),0) -> 29 | G81: =ROUND(($D$81*(1+$A$9)^(G74-$D$74)),0) -> 29 | H81: =ROUND(($D$81*(1+$A$9)^(H74-$D$74)),0) -> 29 | I81: =ROUND(($D$81*(1+$A$9)^(I74-$D$74)),0) -> 29 | J81: =ROUND(($D$81*(1+$A$9)^(J74-$D$74)),0) -> 29 | K81: =ROUND(($D$81*(1+$A$9)^(K74-$D$74)),0) -> 29 | L81: =ROUND(($D$81*(1+$A$9)^(L74-$D$74)),0) -> 29 | ... P81: =ROUND(($D$81*(1+$A$9)^(P74-$D$74)),0) -> 29
C83: RATIO DE CONCENTRACION
C84: ATENCIONES DE PROMOCION DE LA SALUD | D84: GRUPOS | E84: CONCENTRACION (DE ATENCION/PERSONA) CON PROYECTO
C85: CONSEJERIA DE TBC | D85: 18 a 24 Años | E85: 1
D86: 25 a 34 Años | E86: 1
D87: 35 a 44 Años | E87: 1
D88: 45 a 54 Años | E88: 1
D89: 55 a 64 Años | E89: 1
D90: > 65 Años | E90: 1
C92: POBLACION SUJETO DE INTERVENCION (PERSONAS EN SUS DIFERENTES ETAPAS DE VIDA) | D92: PERIODO DE INVERSION | G92: PERIODO DE POST INVERSION
D93: 0 | G93: 1 | H93: 2 | I93: 3 | J93: 4 | K93: 5 | L93: 6 | M93: 7 | N93: 8 | O93: 9 | P93: 10
D94: 2024 | E94: 2025 | F94: 2026 | G94: 2027 | H94: 2028 | I94: 2029 | J94: 2030 | K94: 2031 | L94: 2032 | M94: 2033 | N94: 2034 | O94: 2035 | P94: 2036
C95: CONSEJERIA Y PREVENCION DE TBC (> 18 años) | D95: =+SUM(D96:D101) -> 291.2 | E95: =+SUM(E96:E101) -> 292 | F95: =+SUM(F96:F101) -> 292 | G95: =+SUM(G96:G101) -> 292 | H95: =+SUM(H96:H101) -> 292 | I95: =+SUM(I96:I101) -> 292 | J95: =+SUM(J96:J101) -> 292 | K95: =+SUM(K96:K101) -> 292 | ... P95: =+SUM(P96:P101) -> 292
C96: 18 a 24 Años | D96: =+'POBLACION DEMANDANTE EFECTIVA'!D56*E85 -> 43.2 | E96: =ROUND(($D$96*(1+$A$9)^(E94-$D$94)),0) -> 43 | F96: =ROUND(($D$96*(1+$A$9)^(F94-$D$94)),0) -> 43 | G96: =ROUND(($D$96*(1+$A$9)^(G94-$D$94)),0) -> 43 | H96: =ROUND(($D$96*(1+$A$9)^(H94-$D$94)),0) -> 43 | I96: =ROUND(($D$96*(1+$A$9)^(I94-$D$94)),0) -> 43 | J96: =ROUND(($D$96*(1+$A$9)^(J94-$D$94)),0) -> 43 | K96: =ROUND(($D$96*(1+$A$9)^(K94-$D$94)),0) -> 43 | L96: =ROUND(($D$96*(1+$A$9)^(L94-$D$94)),0) -> 43 | ... P96: =ROUND(($D$96*(1+$A$9)^(P94-$D$94)),0) -> 43
C97: 25 a 34 Años | D97: =+'POBLACION DEMANDANTE EFECTIVA'!D57*E86 -> 69.6 | E97: =ROUND(($D$97*(1+$A$9)^(E94-$D$94)),0) -> 70 | F97: =ROUND(($D$97*(1+$A$9)^(F94-$D$94)),0) -> 70 | G97: =ROUND(($D$97*(1+$A$9)^(G94-$D$94)),0) -> 70 | H97: =ROUND(($D$97*(1+$A$9)^(H94-$D$94)),0) -> 70 | I97: =ROUND(($D$97*(1+$A$9)^(I94-$D$94)),0) -> 70 | J97: =ROUND(($D$97*(1+$A$9)^(J94-$D$94)),0) -> 70 | K97: =ROUND(($D$97*(1+$A$9)^(K94-$D$94)),0) -> 70 | L97: =ROUND(($D$97*(1+$A$9)^(L94-$D$94)),0) -> 70 | ... P97: =ROUND(($D$97*(1+$A$9)^(P94-$D$94)),0) -> 70
C98: 35 a 44 Años | D98: =+'POBLACION DEMANDANTE EFECTIVA'!D58*E87 -> 52.8 | E98: =ROUND(($D$98*(1+$A$9)^(E94-$D$94)),0) -> 53 | F98: =ROUND(($D$98*(1+$A$9)^(F94-$D$94)),0) -> 53 | G98: =ROUND(($D$98*(1+$A$9)^(G94-$D$94)),0) -> 53 | H98: =ROUND(($D$98*(1+$A$9)^(H94-$D$94)),0) -> 53 | I98: =ROUND(($D$98*(1+$A$9)^(I94-$D$94)),0) -> 53 | J98: =ROUND(($D$98*(1+$A$9)^(J94-$D$94)),0) -> 53 | K98: =ROUND(($D$98*(1+$A$9)^(K94-$D$94)),0) -> 53 | L98: =ROUND(($D$98*(1+$A$9)^(L94-$D$94)),0) -> 53 | ... P98: =ROUND(($D$98*(1+$A$9)^(P94-$D$94)),0) -> 53
C99: 45 a 54 Años | D99: =+'POBLACION DEMANDANTE EFECTIVA'!D59*E88 -> 43.2 | E99: =ROUND(($D$99*(1+$A$9)^(E94-$D$94)),0) -> 43 | F99: =ROUND(($D$99*(1+$A$9)^(F94-$D$94)),0) -> 43 | G99: =ROUND(($D$99*(1+$A$9)^(G94-$D$94)),0) -> 43 | H99: =ROUND(($D$99*(1+$A$9)^(H94-$D$94)),0) -> 43 | I99: =ROUND(($D$99*(1+$A$9)^(I94-$D$94)),0) -> 43 | J99: =ROUND(($D$99*(1+$A$9)^(J94-$D$94)),0) -> 43 | K99: =ROUND(($D$99*(1+$A$9)^(K94-$D$94)),0) -> 43 | L99: =ROUND(($D$99*(1+$A$9)^(L94-$D$94)),0) -> 43 | ... P99: =ROUND(($D$99*(1+$A$9)^(P94-$D$94)),0) -> 43
C100: 55 a 64 Años | D100: =+'POBLACION DEMANDANTE EFECTIVA'!D60*E89 -> 36.8 | E100: =ROUND(($D$100*(1+$A$9)^(E94-$D$94)),0) -> 37 | F100: =ROUND(($D$100*(1+$A$9)^(F94-$D$94)),0) -> 37 | G100: =ROUND(($D$100*(1+$A$9)^(G94-$D$94)),0) -> 37 | H100: =ROUND(($D$100*(1+$A$9)^(H94-$D$94)),0) -> 37 | I100: =ROUND(($D$100*(1+$A$9)^(I94-$D$94)),0) -> 37 | J100: =ROUND(($D$100*(1+$A$9)^(J94-$D$94)),0) -> 37 | K100: =ROUND(($D$100*(1+$A$9)^(K94-$D$94)),0) -> 37 | L100: =ROUND(($D$100*(1+$A$9)^(L94-$D$94)),0) -> 37 | ... P100: =ROUND(($D$100*(1+$A$9)^(P94-$D$94)),0) -> 37
C101: > 65 Años | D101: =+'POBLACION DEMANDANTE EFECTIVA'!D61*E90 -> 45.6 | E101: =ROUND(($D$101*(1+$A$9)^(E94-$D$94)),0) -> 46 | F101: =ROUND(($D$101*(1+$A$9)^(F94-$D$94)),0) -> 46 | G101: =ROUND(($D$101*(1+$A$9)^(G94-$D$94)),0) -> 46 | H101: =ROUND(($D$101*(1+$A$9)^(H94-$D$94)),0) -> 46 | I101: =ROUND(($D$101*(1+$A$9)^(I94-$D$94)),0) -> 46 | J101: =ROUND(($D$101*(1+$A$9)^(J94-$D$94)),0) -> 46 | K101: =ROUND(($D$101*(1+$A$9)^(K94-$D$94)),0) -> 46 | L101: =ROUND(($D$101*(1+$A$9)^(L94-$D$94)),0) -> 46 | ... P101: =ROUND(($D$101*(1+$A$9)^(P94-$D$94)),0) -> 46
C103: RATIO DE CONCENTRACION
C104: ATENCIONES DE PROMOCION DE LA SALUD | D104: GRUPOS | E104: CONCENTRACION (DE ATENCION/PERSONA) CON PROYECTO
C105: CONSEJERIA DE ITS/VIH/SIDA (> 18 años) | D105: 18 a 24 Años | E105: 1
D106: 25 a 34 Años | E106: 1
D107: 35 a 44 Años | E107: 1
D108: 45 a 54 Años | E108: 1
D109: 55 a 64 Años | E109: 1
D110: > 65 Años | E110: 1
C112: POBLACION SUJETO DE INTERVENCION (PERSONAS EN SUS DIFERENTES ETAPAS DE VIDA) | D112: PERIODO DE INVERSION | G112: PERIODO DE POST INVERSION
D113: 0 | G113: 1 | H113: 2 | I113: 3 | J113: 4 | K113: 5 | L113: 6 | M113: 7 | N113: 8 | O113: 9 | P113: 10
D114: =+D94 -> 2024 | E114: =+E94 -> 2025 | F114: =+F94 -> 2026 | G114: =+G94 -> 2027 | H114: =+H94 -> 2028 | I114: =+I94 -> 2029 | J114: =+J94 -> 2030 | K114: =+K94 -> 2031 | ... P114: =+P94 -> 2036
C115: CONSEJERIA DE ITS/VIH/SIDA (> 18 años) | D115: =+SUM(D116:D121) -> 291.2 | E115: =+SUM(E116:E121) -> 292 | F115: =+SUM(F116:F121) -> 292 | G115: =+SUM(G116:G121) -> 292 | H115: =+SUM(H116:H121) -> 292 | I115: =+SUM(I116:I121) -> 292 | J115: =+SUM(J116:J121) -> 292 | K115: =+SUM(K116:K121) -> 292 | ... P115: =+SUM(P116:P121) -> 292
...

Sheet OFERTA ACTUAL 
B1: SERVICIOS PREVENTIVOS - CONTROL DE CRECIMIENTO Y DESARROLLO | E1: SERVICIOS PREVENTIVOS - CONTROL PRENATAL | H1: SERVICIOS PREVENTIVOS - CONSULTA EXTERNA (MEDICINA GENERAL)
B2: NRO. DE PERSONAL | C2: 1 | E2: NRO. DE PERSONAL | F2: 1 | H2: NRO. DE PERSONAL | I2: 1
B3: NUMERO HORAS ENFERMERO MENSUAL | C3: 150 HORAS (1.2 ES EL TIEMPO EFECTIVO | E3: NUMERO HORAS OBSTETRA MENSUAL | F3: 150 HORAS (1.2 ES EL TIEMPO EFECTIVO) | H3: NUMERO HORAS MEDICO MENSUAL | I3: 150 HORAS (0.7 h para consulta y 0.8 es de tiempo efectivo)
B4: NRO DE HORAS PROMEDIO DE ATENCION ANUAL DE CONSULTA EXTERNA (HORAS) | C4: =(150*11)*0.3 -> 495 | E4: NRO DE HORAS PROMEDIO DE ATENCION ANUAL DE CONSULTA EXTERNA (HORAS) | F4: =(150*12)*0.3 -> 540 | H4: NRO DE HORAS PROMEDIO DE ATENCION ANUAL DE CONSULTA EXTERNA (HORAS) | I4: =(150*12)*0.7 -> 1260
B5: NRO DE HORAS PROMEDIO DE ATENCION EFECTIVA ANUAL DE CONSULTA EXTERNA (3 HORAS DIARIAS) | C5: =C4*1.2 -> 594 | E5: NRO DE HORAS PROMEDIO DE ATENCION EFECTIVA ANUAL DE CONSULTA EXTERNA (3 HORAS DIARIAS) | F5: =F4*1.3 -> 702 | H5: NRO DE HORAS PROMEDIO DE ATENCION EFECTIVA ANUAL DE CONSULTA EXTERNA (4 HORAS DIARIAS) | I5: =I4*0.8 -> 1008
B6: ESTANDAR DE RENDIMIENTO HORA/PERSONAL | C6: 1 | E6: ESTANDAR DE RENDIMIENTO HORA/PERSONAL | F6: 2 | H6: ESTANDAR DE RENDIMIENTO HORA/PERSONAL | I6: 4
B8: OFERTA POR RECURSOS HUMANOS (NUMERO DE ATENCIONES/AÑO) | E8: OFERTA POR RECURSOS HUMANOS (NUMERO DE ATENCIONES/AÑO) | H8: OFERTA POR RECURSOS HUMANOS (NUMERO DE ATENCIONES/AÑO)
B9: OH= | C9: =C2*C5*C6 -> 594 | E9: OH= | F9: =F2*F5*F6 -> 1404 | H9: OH= | I9: =I2*I5*I6 -> 4032
B11: OFERTA POR RECURSO FISICO (NUMERO DE ATENCIONES/AÑO) | E11: OFERTA POR RECURSO FISICO (NUMERO DE ATENCIONES/AÑO) | H11: OFERTA POR RECURSO FISICO (NUMERO DE ATENCIONES/AÑO)
B12: OF= | C12: 0 | E12: OF= | F12: 0 | H12: OF= | I12: 0
B14: OFERTA OPTIMIZADA
B15: SERVICIOS | C15: POS INVERSION
C16: 1 | D16: 2 | E16: 3 | F16: 4 | G16: 5 | H16: 6 | I16: 7 | J16: 8 | K16: 9 | L16: 10
B17: =+'CART.SERVICIOS'!C4 -> Consultorio de medicina general | C17: 0 | D17: 0 | E17: 0 | F17: 0 | G17: 0 | H17: 0 | I17: 0 | J17: 0 | K17: 0 | L17: 0
B18: =+'CART.SERVICIOS'!C5 -> Teleconsultamedica | C18: 0 | D18: 0 | E18: 0 | F18: 0 | G18: 0 | H18: 0 | I18: 0 | J18: 0 | K18: 0 | L18: 0
B19: =+'CART.SERVICIOS'!C6 -> Consultorio CRED | C19: 0 | D19: 0 | E19: 0 | F19: 0 | G19: 0 | H19: 0 | I19: 0 | J19: 0 | K19: 0 | L19: 0
B20: =+'CART.SERVICIOS'!C7 -> Sala de estimulacion temprana | C20: 0 | D20: 0 | E20: 0 | F20: 0 | G20: 0 | H20: 0 | I20: 0 | J20: 0 | K20: 0 | L20: 0
B21: =+'CART.SERVICIOS'!C8 -> Sala de Inmunizaciones | C21: 0 | D21: 0 | E21: 0 | F21: 0 | G21: 0 | H21: 0 | I21: 0 | J21: 0 | K21: 0 | L21: 0
B22: =+'CART.SERVICIOS'!C9 -> Modulo para prevencion y consejeria de TBC | C22: 0 | D22: 0 | E22: 0 | F22: 0 | G22: 0 | H22: 0 | I22: 0 | J22: 0 | K22: 0 | L22: 0
B23: =+'CART.SERVICIOS'!C10 -> Consejeria y prevencion de ITS, VIH y SIDA | C23: 0 | D23: 0 | E23: 0 | F23: 0 | G23: 0 | H23: 0 | I23: 0 | J23: 0 | K23: 0 | L23: 0
B24: =+'CART.SERVICIOS'!C11 -> Atencíon integral y consejeria del Adolescente | C24: 0 | D24: 0 | E24: 0 | F24: 0 | G24: 0 | H24: 0 | I24: 0 | J24: 0 | K24: 0 | L24: 0
B25: =+'CART.SERVICIOS'!C12 -> Atencíon integral del Adulto Mayor | C25: 0 | D25: 0 | E25: 0 | F25: 0 | G25: 0 | H25: 0 | I25: 0 | J25: 0 | K25: 0 | L25: 0
B26: =+'CART.SERVICIOS'!C13 -> Consejería y prevención de Enf. No Transmisibles | C26: 0 | D26: 0 | E26: 0 | F26: 0 | G26: 0 | H26: 0 | I26: 0 | J26: 0 | K26: 0 | L26: 0
B27: =+'CART.SERVICIOS'!C14 -> Control Prenatal + 1/2 S.H. | C27: 0 | D27: 0 | E27: 0 | F27: 0 | G27: 0 | H27: 0 | I27: 0 | J27: 0 | K27: 0 | L27: 0
B28: =+'CART.SERVICIOS'!C15 -> Planificacíon Familiar | C28: 0 | D28: 0 | E28: 0 | F28: 0 | G28: 0 | H28: 0 | I28: 0 | J28: 0 | K28: 0 | L28: 0
... B37: =+'CART.SERVICIOS'!C24 -> Laboratorio | C37: 0 | D37: 0 | E37: 0 | F37: 0 | G37: 0 | H37: 0 | I37: 0 | J37: 0 | K37: 0 | L37: 0
B38: =+'CART.SERVICIOS'!C25 -> Ecografia | C38: 0 | D38: 0 | E38: 0 | F38: 0 | G38: 0 | H38: 0 | I38: 0 | J38: 0 | K38: 0 | L38: 0 | M38: 0
B39: =+'CART.SERVICIOS'!C26 -> Radiografia | C39: 0 | D39: 0 | E39: 0 | F39: 0 | G39: 0 | H39: 0 | I39: 0 | J39: 0 | K39: 0 | L39: 0

Sheet BALANCE OFERTA Y DEMANDA
A1: BLANCE OFERTA - DEMANDA
A2: SERVICIOS | B2: POST INVERSION
B3: 1 | C3: 2 | D3: 3 | E3: 4 | F3: 5 | G3: 6 | H3: 7 | I3: 8 | J3: 9 | K3: 10
A4: SERVICIOS PREVENTIVOS DE LA SALUD
A5: =+'DEMANDA SERV. DE SALUD CN PY'!C10 -> Medicina General
A6: Demanda efectiva con proyecto | B6: =+'DEMANDA SERV. DE SALUD CN PY'!G11 -> 512 | C6: =+'DEMANDA SERV. DE SALUD CN PY'!H11 -> 512 | D6: =+'DEMANDA SERV. DE SALUD CN PY'!I11 -> 512 | E6: =+'DEMANDA SERV. DE SALUD CN PY'!J11 -> 512 | F6: =+'DEMANDA SERV. DE SALUD CN PY'!K11 -> 512 | G6: =+'DEMANDA SERV. DE SALUD CN PY'!L11 -> 512 | H6: =+'DEMANDA SERV. DE SALUD CN PY'!M11 -> 512 | I6: =+'DEMANDA SERV. DE SALUD CN PY'!N11 -> 513 | ... K6: =+'DEMANDA SERV. DE SALUD CN PY'!P11 -> 513
A7: Oferta optimizada | B7: ='OFERTA ACTUAL '!C10 -> 0 | C7: ='OFERTA ACTUAL '!D10 -> 0 | D7: ='OFERTA ACTUAL '!E10 -> 0 | E7: ='OFERTA ACTUAL '!F10 -> 0 | F7: ='OFERTA ACTUAL '!G10 -> 0 | G7: ='OFERTA ACTUAL '!H10 -> 0 | H7: ='OFERTA ACTUAL '!I10 -> 0 | I7: ='OFERTA ACTUAL '!J10 -> 0 | ... K7: ='OFERTA ACTUAL '!L10 -> 0
A8: BRECHA (atenciones) | B8: =B7-B6 -> -512 | C8: =C7-C6 -> -512 | D8: =D7-D6 -> -512 | E8: =E7-E6 -> -512 | F8: =F7-F6 -> -512 | G8: =G7-G6 -> -512 | H8: =H7-H6 -> -512 | I8: =I7-I6 -> -513
A9: =+'DEMANDA SERV. DE SALUD CN PY'!C15 -> TELECONSULTA MEDICA
A10: Demanda efectiva con proyecto | B10: =+'DEMANDA SERV. DE SALUD CN PY'!E21 -> 341 | C10: =+'DEMANDA SERV. DE SALUD CN PY'!F21 -> 341 | D10: =+'DEMANDA SERV. DE SALUD CN PY'!G21 -> 341 | E10: =+'DEMANDA SERV. DE SALUD CN PY'!H21 -> 341 | F10: =+'DEMANDA SERV. DE SALUD CN PY'!I21 -> 341 | G10: =+'DEMANDA SERV. DE SALUD CN PY'!J21 -> 341 | H10: =+'DEMANDA SERV. DE SALUD CN PY'!K21 -> 341 | I10: =+'DEMANDA SERV. DE SALUD CN PY'!L21 -> 342 | ... K10: =+'DEMANDA SERV. DE SALUD CN PY'!N21 -> 342
A11: Oferta optimizada | B11: ='OFERTA ACTUAL '!C14 -> 0 | C11: ='OFERTA ACTUAL '!D14 -> 0 | D11: ='OFERTA ACTUAL '!E14 -> 0 | E11: ='OFERTA ACTUAL '!F14 -> 0 | F11: ='OFERTA ACTUAL '!G14 -> 0 | G11: ='OFERTA ACTUAL '!H14 -> 0 | H11: ='OFERTA ACTUAL '!I14 -> 0 | I11: ='OFERTA ACTUAL '!J14 -> 0 | ... K11: ='OFERTA ACTUAL '!L14 -> 0
A12: BRECHA (atenciones) | B12: =B11-B10 -> -341 | C12: =C11-C10 -> -341 | D12: =D11-D10 -> -341 | E12: =E11-E10 -> -341 | F12: =F11-F10 -> -341 | G12: =G11-G10 -> -341 | H12: =H11-H10 -> -341 | I12: =I11-I10 -> -342
A13: CONTROL DE CRECIMIENTO Y DESARROLLO
A14: Demanda efectiva con proyecto | B14: =+'DEMANDA SERV. DE SALUD CN PY'!G36 -> 162 | C14: =+'DEMANDA SERV. DE SALUD CN PY'!H36 -> 162 | D14: =+'DEMANDA SERV. DE SALUD CN PY'!I36 -> 162 | E14: =+'DEMANDA SERV. DE SALUD CN PY'!J36 -> 162 | F14: =+'DEMANDA SERV. DE SALUD CN PY'!K36 -> 162 | G14: =+'DEMANDA SERV. DE SALUD CN PY'!L36 -> 162 | H14: =+'DEMANDA SERV. DE SALUD CN PY'!M36 -> 162 | I14: =+'DEMANDA SERV. DE SALUD CN PY'!N36 -> 162 | ... K14: =+'DEMANDA SERV. DE SALUD CN PY'!P36 -> 162
A15: Oferta optimizada | B15: ='OFERTA ACTUAL '!C17 -> 0 | C15: ='OFERTA ACTUAL '!D17 -> 0 | D15: ='OFERTA ACTUAL '!E17 -> 0 | E15: ='OFERTA ACTUAL '!F17 -> 0 | F15: ='OFERTA ACTUAL '!G17 -> 0 | G15: ='OFERTA ACTUAL '!H17 -> 0 | H15: ='OFERTA ACTUAL '!I17 -> 0 | I15: ='OFERTA ACTUAL '!J17 -> 0 | ... K15: ='OFERTA ACTUAL '!L17 -> 0
A16: BRECHA (atenciones) | B16: =B15-B14 -> -162 | C16: =C15-C14 -> -162 | D16: =D15-D14 -> -162 | E16: =E15-E14 -> -162 | F16: =F15-F14 -> -162 | G16: =G15-G14 -> -162 | H16: =H15-H14 -> -162 | I16: =I15-I14 -> -162
A17: ESTIMULACION TEMPRANA
A18: Demanda efectiva con proyecto | B18: =+'DEMANDA SERV. DE SALUD CN PY'!G56 -> 84 | C18: =+'DEMANDA SERV. DE SALUD CN PY'!H56 -> 84 | D18: =+'DEMANDA SERV. DE SALUD CN PY'!I56 -> 84 | E18: =+'DEMANDA SERV. DE SALUD CN PY'!J56 -> 84 | F18: =+'DEMANDA SERV. DE SALUD CN PY'!K56 -> 84 | G18: =+'DEMANDA SERV. DE SALUD CN PY'!L56 -> 84 | H18: =+'DEMANDA SERV. DE SALUD CN PY'!M56 -> 84 | I18: =+'DEMANDA SERV. DE SALUD CN PY'!N56 -> 84 | ... K18: =+'DEMANDA SERV. DE SALUD CN PY'!P56 -> 84
A19: Oferta optimizada | B19: ='OFERTA ACTUAL '!C21 -> 0 | C19: ='OFERTA ACTUAL '!D21 -> 0 | D19: ='OFERTA ACTUAL '!E21 -> 0 | E19: ='OFERTA ACTUAL '!F21 -> 0 | F19: ='OFERTA ACTUAL '!G21 -> 0 | G19: ='OFERTA ACTUAL '!H21 -> 0 | H19: ='OFERTA ACTUAL '!I21 -> 0 | I19: ='OFERTA ACTUAL '!J21 -> 0 | ... K19: ='OFERTA ACTUAL '!L21 -> 0
A20: BRECHA (atenciones) | B20: =B19-B18 -> -84 | C20: =C19-C18 -> -84 | D20: =D19-D18 -> -84 | E20: =E19-E18 -> -84 | F20: =F19-F18 -> -84 | G20: =G19-G18 -> -84 | H20: =H19-H18 -> -84 | I20: =I19-I18 -> -84 | ... K20: =K19-K18 -> -84
A21: INMUNIZACIONES
A22: Demanda efectiva con proyecto | B22: =+'DEMANDA SERV. DE SALUD CN PY'!G75 -> 90 | C22: =+'DEMANDA SERV. DE SALUD CN PY'!H75 -> 90 | D22: =+'DEMANDA SERV. DE SALUD CN PY'!I75 -> 90 | E22: =+'DEMANDA SERV. DE SALUD CN PY'!J75 -> 90 | F22: =+'DEMANDA SERV. DE SALUD CN PY'!K75 -> 90 | G22: =+'DEMANDA SERV. DE SALUD CN PY'!L75 -> 90 | H22: =+'DEMANDA SERV. DE SALUD CN PY'!M75 -> 90 | I22: =+'DEMANDA SERV. DE SALUD CN PY'!N75 -> 90 | ... K22: =+'DEMANDA SERV. DE SALUD CN PY'!P75 -> 90
A23: Oferta optimizada | B23: ='OFERTA ACTUAL '!C25 -> 0 | C23: ='OFERTA ACTUAL '!D25 -> 0 | D23: ='OFERTA ACTUAL '!E25 -> 0 | E23: ='OFERTA ACTUAL '!F25 -> 0 | F23: ='OFERTA ACTUAL '!G25 -> 0 | G23: ='OFERTA ACTUAL '!H25 -> 0 | H23: ='OFERTA ACTUAL '!I25 -> 0 | I23: ='OFERTA ACTUAL '!J25 -> 0 | J23: 0 | K23: 0
A24: BRECHA (atenciones) | B24: =B23-B22 -> -90 | C24: =C23-C22 -> -90 | D24: =D23-D22 -> -90 | E24: =E23-E22 -> -90 | F24: =F23-F22 -> -90 | G24: =G23-G22 -> -90 | H24: =H23-H22 -> -90 | I24: =I23-I22 -> -90 | ... K24: =K23-K22 -> -90
A25: TBC
A26: Demanda efectiva con proyecto | B26: =+'DEMANDA SERV. DE SALUD CN PY'!G95 -> 292 | C26: =+'DEMANDA SERV. DE SALUD CN PY'!H95 -> 292 | D26: =+'DEMANDA SERV. DE SALUD CN PY'!I95 -> 292 | E26: =+'DEMANDA SERV. DE SALUD CN PY'!J95 -> 292 | F26: =+'DEMANDA SERV. DE SALUD CN PY'!K95 -> 292 | G26: =+'DEMANDA SERV. DE SALUD CN PY'!L95 -> 292 | H26: =+'DEMANDA SERV. DE SALUD CN PY'!M95 -> 292 | I26: =+'DEMANDA SERV. DE SALUD CN PY'!N95 -> 292 | ... K26: =+'DEMANDA SERV. DE SALUD CN PY'!P95 -> 292
A27: Oferta optimizada | B27: ='OFERTA ACTUAL '!C29 -> 0 | C27: ='OFERTA ACTUAL '!D29 -> 0 | D27: ='OFERTA ACTUAL '!E29 -> 0 | E27: ='OFERTA ACTUAL '!F29 -> 0 | F27: ='OFERTA ACTUAL '!G29 -> 0 | G27: ='OFERTA ACTUAL '!H29 -> 0 | H27: ='OFERTA ACTUAL '!I29 -> 0 | I27: ='OFERTA ACTUAL '!J29 -> 0 | J27: 0 | K27: 0
A28: BRECHA (atenciones) | B28: =B27-B26 -> -292 | C28: =C27-C26 -> -292 | D28: =D27-D26 -> -292 | E28: =E27-E26 -> -292 | F28: =F27-F26 -> -292 | G28: =G27-G26 -> -292 | H28: =H27-H26 -> -292 | I28: =I27-I26 -> -292 | ... K28: =K27-K26 -> -292
A29: ITS, VIH/SIDA
A30: Demanda efectiva con proyecto | B30: =+'DEMANDA SERV. DE SALUD CN PY'!G115 -> 292 | C30: =+'DEMANDA SERV. DE SALUD CN PY'!H115 -> 292 | D30: =+'DEMANDA SERV. DE SALUD CN PY'!I115 -> 292 | E30: =+'DEMANDA SERV. DE SALUD CN PY'!J115 -> 292 | F30: =+'DEMANDA SERV. DE SALUD CN PY'!K115 -> 292 | G30: =+'DEMANDA SERV. DE SALUD CN PY'!L115 -> 292 | H30: =+'DEMANDA SERV. DE SALUD CN PY'!M115 -> 292 | I30: =+'DEMANDA SERV. DE SALUD CN PY'!N115 -> 292 | ... K30: =+'DEMANDA SERV. DE SALUD CN PY'!P115 -> 292
A31: Oferta optimizada | B31: ='OFERTA ACTUAL '!C33 -> 0 | C31: ='OFERTA ACTUAL '!D33 -> 0 | D31: ='OFERTA ACTUAL '!E33 -> 0 | E31: ='OFERTA ACTUAL '!F33 -> 0 | F31: ='OFERTA ACTUAL '!G33 -> 0 | G31: ='OFERTA ACTUAL '!H33 -> 0 | H31: ='OFERTA ACTUAL '!I33 -> 0 | I31: ='OFERTA ACTUAL '!J33 -> 0 | J31: 0 | K31: 0
A32: BRECHA (atenciones) | B32: =B31-B30 -> -292 | C32: =C31-C30 -> -292 | D32: =D31-D30 -> -292 | E32: =E31-E30 -> -292 | F32: =F31-F30 -> -292 | G32: =G31-G30 -> -292 | H32: =H31-H30 -> -292 | I32: =I31-I30 -> -292 | ... K32: =K31-K30 -> -292
A33: ADOLESCENTE
A34: Demanda efectiva con proyecto | B34: =+'DEMANDA SERV. DE SALUD CN PY'!G135 -> 32 | C34: =+'DEMANDA SERV. DE SALUD CN PY'!H135 -> 32 | D34: =+'DEMANDA SERV. DE SALUD CN PY'!I135 -> 32 | E34: =+'DEMANDA SERV. DE SALUD CN PY'!J135 -> 32 | F34: =+'DEMANDA SERV. DE SALUD CN PY'!K135 -> 32 | G34: =+'DEMANDA SERV. DE SALUD CN PY'!L135 -> 32 | H34: =+'DEMANDA SERV. DE SALUD CN PY'!M135 -> 32 | I34: =+'DEMANDA SERV. DE SALUD CN PY'!N135 -> 32 | ... K34: =+'DEMANDA SERV. DE SALUD CN PY'!P135 -> 32
A35: Oferta optimizada | B35: ='OFERTA ACTUAL '!C37 -> 0 | C35: ='OFERTA ACTUAL '!D37 -> 0 | D35: ='OFERTA ACTUAL '!E37 -> 0 | E35: ='OFERTA ACTUAL '!F37 -> 0 | F35: ='OFERTA ACTUAL '!G37 -> 0 | G35: ='OFERTA ACTUAL '!H37 -> 0 | H35: ='OFERTA ACTUAL '!I37 -> 0 | I35: ='OFERTA ACTUAL '!J37 -> 0 | J35: 0 | K35: 0
A36: BRECHA (atenciones) | B36: =B35-B34 -> -32 | C36: =C35-C34 -> -32 | D36: =D35-D34 -> -32 | E36: =E35-E34 -> -32 | F36: =F35-F34 -> -32 | G36: =G35-G34 -> -32 | H36: =H35-H34 -> -32 | I36: =I35-I34 -> -32 | ... K36: =K35-K34 -> -32
A37: ADULTO MAYOR
A38: Demanda efectiva con proyecto | B38: =+'DEMANDA SERV. DE SALUD CN PY'!G155 -> 292 | C38: =+'DEMANDA SERV. DE SALUD CN PY'!H155 -> 292 | D38: =+'DEMANDA SERV. DE SALUD CN PY'!I155 -> 292 | E38: =+'DEMANDA SERV. DE SALUD CN PY'!J155 -> 292 | F38: =+'DEMANDA SERV. DE SALUD CN PY'!K155 -> 292 | G38: =+'DEMANDA SERV. DE SALUD CN PY'!L155 -> 292 | H38: =+'DEMANDA SERV. DE SALUD CN PY'!M155 -> 292 | I38: =+'DEMANDA SERV. DE SALUD CN PY'!N155 -> 292 | ... K38: =+'DEMANDA SERV. DE SALUD CN PY'!P155 -> 292
A39: Oferta optimizada | B39: 0 | C39: 0 | D39: 0 | E39: 0 | F39: 0 | G39: 0 | H39: 0 | I39: 0 | J39: 0 | K39: 0
A40: BRECHA (atenciones) | B40: =B39-B38 -> -292 | C40: =C39-C38 -> -292 | D40: =D39-D38 -> -292 | E40: =E39-E38 -> -292 | F40: =F39-F38 -> -292 | G40: =G39-G38 -> -292 | H40: =H39-H38 -> -292 | I40: =I39-I38 -> -292 | ... K40: =K39-K38 -> -292
A41: ENFERMEDADES NO TRASMISIBLES
A42: Demanda efectiva con proyecto | B42: =+'DEMANDA SERV. DE SALUD CN PY'!G175 -> 292 | C42: =+'DEMANDA SERV. DE SALUD CN PY'!H175 -> 292 | D42: =+'DEMANDA SERV. DE SALUD CN PY'!I175 -> 292 | E42: =+'DEMANDA SERV. DE SALUD CN PY'!J175 -> 292 | F42: =+'DEMANDA SERV. DE SALUD CN PY'!K175 -> 292 | G42: =+'DEMANDA SERV. DE SALUD CN PY'!L175 -> 292 | H42: =+'DEMANDA SERV. DE SALUD CN PY'!M175 -> 292 | I42: =+'DEMANDA SERV. DE SALUD CN PY'!N175 -> 292 | ... K42: =+'DEMANDA SERV. DE SALUD CN PY'!P175 -> 292
A43: Oferta optimizada | B43: 0 | C43: 0 | D43: 0 | E43: 0 | F43: 0 | G43: 0 | H43: 0 | I43: 0 | J43: 0 | K43: 0
A44: BRECHA (atenciones) | B44: =B43-B42 -> -292 | C44: =C43-C42 -> -292 | D44: =D43-D42 -> -292 | E44: =E43-E42 -> -292 | F44: =F43-F42 -> -292 | G44: =G43-G42 -> -292 | H44: =H43-H42 -> -292 | I44: =I43-I42 -> -292 | ... K44: =K43-K42 -> -292
A45: CONSTROL PRE NATAL
A46: Demanda efectiva con proyecto | B46: =+'DEMANDA SERV. DE SALUD CN PY'!G190 -> 115 | C46: =+'DEMANDA SERV. DE SALUD CN PY'!H190 -> 115 | D46: =+'DEMANDA SERV. DE SALUD CN PY'!I190 -> 115 | E46: =+'DEMANDA SERV. DE SALUD CN PY'!J190 -> 115 | F46: =+'DEMANDA SERV. DE SALUD CN PY'!K190 -> 115 | G46: =+'DEMANDA SERV. DE SALUD CN PY'!L190 -> 115 | H46: =+'DEMANDA SERV. DE SALUD CN PY'!M190 -> 116 | I46: =+'DEMANDA SERV. DE SALUD CN PY'!N190 -> 116 | ... K46: =+'DEMANDA SERV. DE SALUD CN PY'!P190 -> 116
A47: Oferta optimizada | B47: 0 | C47: 0 | D47: 0 | E47: 0 | F47: 0 | G47: 0 | H47: 0 | I47: 0 | J47: 0 | K47: 0
A48: BRECHA (atenciones) | B48: =B47-B46 -> -115 | C48: =C47-C46 -> -115 | D48: =D47-D46 -> -115 | E48: =E47-E46 -> -115 | F48: =F47-F46 -> -115 | G48: =G47-G46 -> -115 | H48: =H47-H46 -> -116 | I48: =I47-I46 -> -116 | ... K48: =K47-K46 -> -116
A49: PLANIFICACION FAMILIAR
A50: Demanda efectiva con proyecto | B50: =+'DEMANDA SERV. DE SALUD CN PY'!G201 -> 807 | C50: =+'DEMANDA SERV. DE SALUD CN PY'!H201 -> 807 | D50: =+'DEMANDA SERV. DE SALUD CN PY'!I201 -> 808 | E50: =+'DEMANDA SERV. DE SALUD CN PY'!J201 -> 808 | F50: =+'DEMANDA SERV. DE SALUD CN PY'!K201 -> 808 | G50: =+'DEMANDA SERV. DE SALUD CN PY'!L201 -> 808 | H50: =+'DEMANDA SERV. DE SALUD CN PY'!M201 -> 809 | I50: =+'DEMANDA SERV. DE SALUD CN PY'!N201 -> 809 | ... K50: =+'DEMANDA SERV. DE SALUD CN PY'!P201 -> 809
A51: Oferta optimizada | B51: ='OFERTA ACTUAL '!C41 -> 0 | C51: ='OFERTA ACTUAL '!D41 -> 0 | D51: ='OFERTA ACTUAL '!E41 -> 0 | E51: ='OFERTA ACTUAL '!F41 -> 0 | F51: ='OFERTA ACTUAL '!G41 -> 0 | G51: ='OFERTA ACTUAL '!H41 -> 0 | H51: ='OFERTA ACTUAL '!I41 -> 0 | I51: ='OFERTA ACTUAL '!J41 -> 0 | J51: 0 | K51: 0
A52: BRECHA (atenciones) | B52: =B51-B50 -> -807 | C52: =C51-C50 -> -807 | D52: =D51-D50 -> -808 | E52: =E51-E50 -> -808 | F52: =F51-F50 -> -808 | G52: =G51-G50 -> -808 | H52: =H51-H50 -> -809 | I52: =I51-I50 -> -809 | ... K52: =K51-K50 -> -809
A53: CANCER
A54: Demanda efectiva con proyecto | B54: =+'DEMANDA SERV. DE SALUD CN PY'!G217 -> 292 | C54: =+'DEMANDA SERV. DE SALUD CN PY'!H217 -> 292 | D54: =+'DEMANDA SERV. DE SALUD CN PY'!I217 -> 292 | E54: =+'DEMANDA SERV. DE SALUD CN PY'!J217 -> 292 | F54: =+'DEMANDA SERV. DE SALUD CN PY'!K217 -> 292 | G54: =+'DEMANDA SERV. DE SALUD CN PY'!L217 -> 292 | H54: =+'DEMANDA SERV. DE SALUD CN PY'!M217 -> 292 | I54: =+'DEMANDA SERV. DE SALUD CN PY'!N217 -> 292 | ... K54: =+'DEMANDA SERV. DE SALUD CN PY'!P217 -> 292
A55: Oferta optimizada | B55: ='OFERTA ACTUAL '!C41 -> 0 | C55: ='OFERTA ACTUAL '!D41 -> 0 | D55: ='OFERTA ACTUAL '!E41 -> 0 | E55: ='OFERTA ACTUAL '!F41 -> 0 | F55: ='OFERTA ACTUAL '!G41 -> 0 | G55: ='OFERTA ACTUAL '!H41 -> 0 | H55: ='OFERTA ACTUAL '!I41 -> 0 | I55: ='OFERTA ACTUAL '!J41 -> 0 | J55: 0 | K55: 0
A56: BRECHA (atenciones) | B56: =B55-B54 -> -292 | C56: =C55-C54 -> -292 | D56: =D55-D54 -> -292 | E56: =E55-E54 -> -292 | F56: =F55-F54 -> -292 | G56: =G55-G54 -> -292 | H56: =H55-H54 -> -292 | I56: =I55-I54 -> -292 | ... K56: =K55-K54 -> -292
A57: PSICOPROFILAXIS
A58: Demanda efectiva con proyecto | B58: =+'DEMANDA SERV. DE SALUD CN PY'!G232 -> 86 | C58: =+'DEMANDA SERV. DE SALUD CN PY'!H232 -> 87 | D58: =+'DEMANDA SERV. DE SALUD CN PY'!I232 -> 87 | E58: =+'DEMANDA SERV. DE SALUD CN PY'!J232 -> 87 | F58: =+'DEMANDA SERV. DE SALUD CN PY'!K232 -> 87 | G58: =+'DEMANDA SERV. DE SALUD CN PY'!L232 -> 87 | H58: =+'DEMANDA SERV. DE SALUD CN PY'!M232 -> 87 | I58: =+'DEMANDA SERV. DE SALUD CN PY'!N232 -> 87 | ... K58: =+'DEMANDA SERV. DE SALUD CN PY'!P232 -> 87
A59: Oferta optimizada | B59: ='OFERTA ACTUAL '!C45 -> 0 | C59: ='OFERTA ACTUAL '!D45 -> 0 | D59: ='OFERTA ACTUAL '!E45 -> 0 | E59: ='OFERTA ACTUAL '!F45 -> 0 | F59: ='OFERTA ACTUAL '!G45 -> 0 | G59: ='OFERTA ACTUAL '!H45 -> 0 | H59: ='OFERTA ACTUAL '!I45 -> 0 | I59: ='OFERTA ACTUAL '!J45 -> 0 | J59: 0 | K59: 0
A60: BRECHA (atenciones) | B60: =B59-B58 -> -86 | C60: =C59-C58 -> -87 | D60: =D59-D58 -> -87 | E60: =E59-E58 -> -87 | F60: =F59-F58 -> -87 | G60: =G59-G58 -> -87 | H60: =H59-H58 -> -87 | I60: =I59-I58 -> -87 | ... K60: =K59-K58 -> -87
A61: ODONTOLOGIA
A62: Demanda efectiva con proyecto | B62: =+'DEMANDA SERV. DE SALUD CN PY'!G242 -> 314 | C62: =+'DEMANDA SERV. DE SALUD CN PY'!H242 -> 314 | D62: =+'DEMANDA SERV. DE SALUD CN PY'!I242 -> 314 | E62: =+'DEMANDA SERV. DE SALUD CN PY'!J242 -> 314 | F62: =+'DEMANDA SERV. DE SALUD CN PY'!K242 -> 314 | G62: =+'DEMANDA SERV. DE SALUD CN PY'!L242 -> 315 | H62: =+'DEMANDA SERV. DE SALUD CN PY'!M242 -> 315 | I62: =+'DEMANDA SERV. DE SALUD CN PY'!N242 -> 315 | ... K62: =+'DEMANDA SERV. DE SALUD CN PY'!P242 -> 315
A63: Oferta optimizada | B63: ='OFERTA ACTUAL '!C49 -> 0 | C63: ='OFERTA ACTUAL '!D49 -> 0 | D63: ='OFERTA ACTUAL '!E49 -> 0 | E63: ='OFERTA ACTUAL '!F49 -> 0 | F63: ='OFERTA ACTUAL '!G49 -> 0 | G63: ='OFERTA ACTUAL '!H49 -> 0 | H63: ='OFERTA ACTUAL '!I49 -> 0 | I63: ='OFERTA ACTUAL '!J49 -> 0 | J63: 0 | K63: 0
A64: BRECHA (atenciones) | B64: =B63-B62 -> -314 | C64: =C63-C62 -> -314 | D64: =D63-D62 -> -314 | E64: =E63-E62 -> -314 | F64: =F63-F62 -> -314 | G64: =G63-G62 -> -315 | H64: =H63-H62 -> -315 | I64: =I63-I62 -> -315 | ... K64: =K63-K62 -> -315
A65: =+'DEMANDA SERV. DE SALUD CN PY'!C247 -> PSICOLOGIA
A66: Demanda efectiva con proyecto | B66: =+'DEMANDA SERV. DE SALUD CN PY'!G252 -> 675 | C66: =+'DEMANDA SERV. DE SALUD CN PY'!H252 -> 676 | D66: =+'DEMANDA SERV. DE SALUD CN PY'!I252 -> 676 | E66: =+'DEMANDA SERV. DE SALUD CN PY'!J252 -> 676 | F66: =+'DEMANDA SERV. DE SALUD CN PY'!K252 -> 676 | G66: =+'DEMANDA SERV. DE SALUD CN PY'!L252 -> 676 | H66: =+'DEMANDA SERV. DE SALUD CN PY'!M252 -> 677 | I66: =+'DEMANDA SERV. DE SALUD CN PY'!N252 -> 677 | ... K66: =+'DEMANDA SERV. DE SALUD CN PY'!P252 -> 677
A67: Oferta optimizada | B67: ='OFERTA ACTUAL '!C49 -> 0 | C67: ='OFERTA ACTUAL '!D49 -> 0 | D67: ='OFERTA ACTUAL '!E49 -> 0 | E67: ='OFERTA ACTUAL '!F49 -> 0 | F67: ='OFERTA ACTUAL '!G49 -> 0 | G67: ='OFERTA ACTUAL '!H49 -> 0 | H67: ='OFERTA ACTUAL '!I49 -> 0 | I67: ='OFERTA ACTUAL '!J49 -> 0 | J67: 0 | K67: 0
A68: BRECHA (atenciones) | B68: =B67-B66 -> -675 | C68: =C67-C66 -> -676 | D68: =D67-D66 -> -676 | E68: =E67-E66 -> -676 | F68: =F67-F66 -> -676 | G68: =G67-G66 -> -676 | H68: =H67-H66 -> -677 | I68: =I67-I66 -> -677 | ... K68: =K67-K66 -> -677
A69: =+'DEMANDA SERV. DE SALUD CN PY'!C257 -> URGENCIAS Y EMERGENCIAS
A70: Demanda efectiva con proyecto | B70: =+'DEMANDA SERV. DE SALUD CN PY'!G262 -> 171 | C70: =+'DEMANDA SERV. DE SALUD CN PY'!H262 -> 171 | D70: =+'DEMANDA SERV. DE SALUD CN PY'!I262 -> 171 | E70: =+'DEMANDA SERV. DE SALUD CN PY'!J262 -> 171 | F70: =+'DEMANDA SERV. DE SALUD CN PY'!K262 -> 171 | G70: =+'DEMANDA SERV. DE SALUD CN PY'!L262 -> 171 | H70: =+'DEMANDA SERV. DE SALUD CN PY'!M262 -> 171 | I70: =+'DEMANDA SERV. DE SALUD CN PY'!N262 -> 171 | ... K70: =+'DEMANDA SERV. DE SALUD CN PY'!P262 -> 171
A71: Oferta optimizada | B71: ='OFERTA ACTUAL '!C53 -> 0 | C71: ='OFERTA ACTUAL '!D53 -> 0 | D71: ='OFERTA ACTUAL '!E53 -> 0 | E71: ='OFERTA ACTUAL '!F53 -> 0 | F71: ='OFERTA ACTUAL '!G53 -> 0 | G71: ='OFERTA ACTUAL '!H53 -> 0 | H71: ='OFERTA ACTUAL '!I53 -> 0 | I71: ='OFERTA ACTUAL '!J53 -> 0 | J71: 0 | K71: 0
A72: BRECHA (atenciones) | B72: =B71-B70 -> -171 | C72: =C71-C70 -> -171 | D72: =D71-D70 -> -171 | E72: =E71-E70 -> -171 | F72: =F71-F70 -> -171 | G72: =G71-G70 -> -171 | H72: =H71-H70 -> -171 | I72: =I71-I70 -> -171 | ... K72: =K71-K70 -> -171
A73: =+'DEMANDA SERV. DE SALUD CN PY'!C267 -> EMERGENCIAS
A74: Demanda efectiva con proyecto | B74: =+'DEMANDA SERV. DE SALUD CN PY'!G273 -> 171 | C74: =+'DEMANDA SERV. DE SALUD CN PY'!H273 -> 171 | D74: =+'DEMANDA SERV. DE SALUD CN PY'!I273 -> 171 | E74: =+'DEMANDA SERV. DE SALUD CN PY'!J273 -> 171 | F74: =+'DEMANDA SERV. DE SALUD CN PY'!K273 -> 171 | G74: =+'DEMANDA SERV. DE SALUD CN PY'!L273 -> 171 | H74: =+'DEMANDA SERV. DE SALUD CN PY'!M273 -> 171 | I74: =+'DEMANDA SERV. DE SALUD CN PY'!N273 -> 171 | ... K74: =+'DEMANDA SERV. DE SALUD CN PY'!P273 -> 171
A75: Oferta optimizada | B75: ='OFERTA ACTUAL '!C45 -> 0 | C75: ='OFERTA ACTUAL '!D45 -> 0 | D75: ='OFERTA ACTUAL '!E45 -> 0 | E75: ='OFERTA ACTUAL '!F45 -> 0 | F75: ='OFERTA ACTUAL '!G45 -> 0 | G75: ='OFERTA ACTUAL '!H45 -> 0 | H75: ='OFERTA ACTUAL '!I45 -> 0 | I75: ='OFERTA ACTUAL '!J45 -> 0 | J75: 0 | K75: 0
A76: BRECHA (atenciones) | B76: =B75-B74 -> -171 | C76: =C75-C74 -> -171 | D76: =D75-D74 -> -171 | E76: =E75-E74 -> -171 | F76: =F75-F74 -> -171 | G76: =G75-G74 -> -171 | H76: =H75-H74 -> -171 | I76: =I75-I74 -> -171 | ... K76: =K75-K74 -> -171
A77: =+'DEMANDA SERV. DE SALUD CN PY'!C278 -> LABORATORIO
A78: Demanda efectiva con proyecto | B78: =+'DEMANDA SERV. DE SALUD CN PY'!G283 -> 853 | C78: =+'DEMANDA SERV. DE SALUD CN PY'!H283 -> 853 | D78: =+'DEMANDA SERV. DE SALUD CN PY'!I283 -> 853 | E78: =+'DEMANDA SERV. DE SALUD CN PY'!J283 -> 853 | F78: =+'DEMANDA SERV. DE SALUD CN PY'!K283 -> 854 | G78: =+'DEMANDA SERV. DE SALUD CN PY'!L283 -> 854 | H78: =+'DEMANDA SERV. DE SALUD CN PY'!M283 -> 854 | I78: =+'DEMANDA SERV. DE SALUD CN PY'!N283 -> 854 | ... K78: =+'DEMANDA SERV. DE SALUD CN PY'!P283 -> 855
A79: Oferta optimizada | B79: ='OFERTA ACTUAL '!C49 -> 0 | C79: ='OFERTA ACTUAL '!D49 -> 0 | D79: ='OFERTA ACTUAL '!E49 -> 0 | E79: ='OFERTA ACTUAL '!F49 -> 0 | F79: ='OFERTA ACTUAL '!G49 -> 0 | G79: ='OFERTA ACTUAL '!H49 -> 0 | H79: ='OFERTA ACTUAL '!I49 -> 0 | I79: ='OFERTA ACTUAL '!J49 -> 0 | J79: 0 | K79: 0
A80: BRECHA (atenciones) | B80: =B79-B78 -> -853 | C80: =C79-C78 -> -853 | D80: =D79-D78 -> -853 | E80: =E79-E78 -> -853 | F80: =F79-F78 -> -854 | G80: =G79-G78 -> -854 | H80: =H79-H78 -> -854 | I80: =I79-I78 -> -854 | ... K80: =K79-K78 -> -855
A81: =+'DEMANDA SERV. DE SALUD CN PY'!C293 -> ECOGRAFIA
A82: Demanda efectiva con proyecto | B82: =+'DEMANDA SERV. DE SALUD CN PY'!G293 -> 341 | C82: =+'DEMANDA SERV. DE SALUD CN PY'!H293 -> 341 | D82: =+'DEMANDA SERV. DE SALUD CN PY'!I293 -> 341 | E82: =+'DEMANDA SERV. DE SALUD CN PY'!J293 -> 341 | F82: =+'DEMANDA SERV. DE SALUD CN PY'!K293 -> 341 | G82: =+'DEMANDA SERV. DE SALUD CN PY'!L293 -> 342 | H82: =+'DEMANDA SERV. DE SALUD CN PY'!M293 -> 342 | I82: =+'DEMANDA SERV. DE SALUD CN PY'!N293 -> 342 | ... K82: =+'DEMANDA SERV. DE SALUD CN PY'!P293 -> 342
A83: Oferta optimizada | B83: ='OFERTA ACTUAL '!C53 -> 0 | C83: ='OFERTA ACTUAL '!D53 -> 0 | D83: ='OFERTA ACTUAL '!E53 -> 0 | E83: ='OFERTA ACTUAL '!F53 -> 0 | F83: ='OFERTA ACTUAL '!G53 -> 0 | G83: ='OFERTA ACTUAL '!H53 -> 0 | H83: ='OFERTA ACTUAL '!I53 -> 0 | I83: ='OFERTA ACTUAL '!J53 -> 0 | J83: 0 | K83: 0
A84: BRECHA (atenciones) | B84: =B83-B82 -> -341 | C84: =C83-C82 -> -341 | D84: =D83-D82 -> -341 | E84: =E83-E82 -> -341 | F84: =F83-F82 -> -341 | G84: =G83-G82 -> -342 | H84: =H83-H82 -> -342 | I84: =I83-I82 -> -342 | ... K84: =K83-K82 -> -342
A85: =+'DEMANDA SERV. DE SALUD CN PY'!C298 -> RADIOGRAFIA
A86: Demanda efectiva con proyecto | B86: =+'DEMANDA SERV. DE SALUD CN PY'!G303 -> 341 | C86: =+'DEMANDA SERV. DE SALUD CN PY'!H303 -> 341 | D86: =+'DEMANDA SERV. DE SALUD CN PY'!I303 -> 341 | E86: =+'DEMANDA SERV. DE SALUD CN PY'!J303 -> 341 | F86: =+'DEMANDA SERV. DE SALUD CN PY'!K303 -> 341 | G86: =+'DEMANDA SERV. DE SALUD CN PY'!L303 -> 342 | H86: =+'DEMANDA SERV. DE SALUD CN PY'!M303 -> 342 | I86: =+'DEMANDA SERV. DE SALUD CN PY'!N303 -> 342 | ... K86: =+'DEMANDA SERV. DE SALUD CN PY'!P303 -> 342
A87: Oferta optimizada | B87: ='OFERTA ACTUAL '!C57 -> 0 | C87: ='OFERTA ACTUAL '!D57 -> 0 | D87: ='OFERTA ACTUAL '!E57 -> 0 | E87: ='OFERTA ACTUAL '!F57 -> 0 | F87: ='OFERTA ACTUAL '!G57 -> 0 | G87: ='OFERTA ACTUAL '!H57 -> 0 | H87: ='OFERTA ACTUAL '!I57 -> 0 | I87: ='OFERTA ACTUAL '!J57 -> 0 | J87: 0 | K87: 0
A88: BRECHA (atenciones) | B88: =B87-B86 -> -341 | C88: =C87-C86 -> -341 | D88: =D87-D86 -> -341 | E88: =E87-E86 -> -341 | F88: =F87-F86 -> -341 | G88: =G87-G86 -> -342 | H88: =H87-H86 -> -342 | I88: =I87-I86 -> -342 | ... K88: =K87-K86 -> -342

Sheet COSTOS A PRECIOS MERCADO
A1: PRESUPUESTO DE INVERSION A PRECIOS DE MERCADO - C.S RAHUAPAMPA
A2: ALTERNATIVA UNICA | N2: 0.1170327 | O2: =2170922.69/21709226.93 -> 0.1
A3: COMPONENTE | B3: ACTIVIDADES | C3: TIPO DE FACTOR PRODUCTIVO | D3: UNIDAD FISICA | F3: UM | G3: META | H3: COSTOS DIRECTOS | I3: GASTOS GENERALES | J3: UTILIDAD | K3: IGV | L3: COSTOS A PRECIOS DE MERCADO | N3: =2540689.41/21709226.93 -> 0.1170327 | O3: 0.1
D4: UM | E4: META | I4: 0.1170327 | J4: 0.1 | K4: 0.18
A5: INFRAESTRUCTURA ADECUADA PARA LA PRESTACION DE LOS SERVICIOS DE SALUD | B5: CONSTRUCCION SALA DE PROCEDIMIENTOS AMBULATORIOS | C5: Infraestructura | D5: Ambientes | E5: 1 | F5: m2 | G5: 18 | H5: 187622.91 | I5: =+H5*$I$4 -> 21958.015 | J5: =+H5*$J$4 -> 18762.291 | K5: =+(H5+I5+J5)*$K$4 -> 41101.778 | L5: =+H5+I5+J5+K5 -> 269444.99 | N5: =+SUM(G5:G28) -> 1659.12 | O5: =+N31/N5 -> 15719.623
B6: CONSTRUCCION DE CONSULTORIO CRED | C6: Infraestructura | D6: Ambientes | E6: 1 | F6: m2 | G6: 17.16 | H6: 178867.17 | I6: =+H6*$I$4 -> 20933.308 | J6: =+H6*$J$4 -> 17886.717 | K6: =+(H6+I6+J6)*$K$4 -> 39183.695 | L6: =+H6+I6+J6+K6 -> 256870.89 | M6: =+G5/$N$5 -> 0.010849125 | N6: =+M6*$N$31 -> 282953.21 | O6: 187622.91
B7: CONSTRUCCION DE SALA DE INMUNIZACIONES | C7: Infraestructura | D7: Ambientes | E7: 1 | F7: m2 | G7: 19.43 | H7: 202528.5 | I7: =+H7*$I$4 -> 23702.457 | J7: =+H7*$J$4 -> 20252.85 | K7: =+(H7+I7+J7)*$K$4 -> 44367.086 | L7: =+H7+I7+J7+K7 -> 290850.9 | M7: =+G6/$N$5 -> 0.010342832 | N7: =+M7*$N$31 -> 269748.73 | O7: 178867.17
B8: CONSTRUCCION DE AMBIENTE DE ACOMPAÑAMIENTO Y/O CONSEJERIA | C8: Infraestructura | D8: Ambientes | E8: 2 | F8: m2 | G8: =18.78+24.62 -> 43.4 | H8: 452379.68 | I8: =+H8*$I$4 -> 52943.214 | J8: =+H8*$J$4 -> 45237.967 | K8: =+(H8+I8+J8)*$K$4 -> 99100.954 | L8: =+H8+I8+J8+K8 -> 649661.81 | M8: =+G7/$N$5 -> 0.011711028 | N8: =+M8*$N$31 -> 305432.27 | O8: 202528.5
B9: CONSTRUCCION DE CONSULTORIO | C9: Infraestructura | D9: Ambientes | E9: 1 | F9: m2 | G9: =17.73+26.11+18.69+35.84 -> 98.37 | H9: 1025359.2 | I9: =+H9*$I$4 -> 120000.55 | J9: =+H9*$J$4 -> 102535.92 | K9: =+(H9+I9+J9)*$K$4 -> 224621.22 | L9: =+H9+I9+J9+K9 -> 1472516.9 | M9: =+G8/$N$5 -> 0.026158445 | N9: =+M9*$N$31 -> 682231.63 | O9: 452379.68
B10: CONTRUCCION AMBIENTE COMPLEMENTARIO | C10: Infraestructura | D10: Ambientes | E10: 1 | F10: m2 | G10: =91.6+126.97+8.93+30.66 -> 258.16 | H10: 2690929.4 | I10: =+H10*$I$4 -> 314926.73 | J10: =+H10*$J$4 -> 269092.94 | K10: =+(H10+I10+J10)*$K$4 -> 589490.84 | L10: =+H10+I10+J10+K10 -> 3864439.9 | M10: =+G9/$N$5 -> 0.059290467 | N10: =+M10*$N$31 -> 1546339.3 | O10: 1025359.2
B11: CONSTRUCCION DE LABORATORIO GENERAL | C11: Infraestructura | D11: Ambientes | E11: 1 | F11: m2 | G11: =10.04+24.05+30.21+37.97+5.13+2.69+4.9+9.86+11.13+4.56+15.38+14.74+7.23+6.86+9.11+7.44+6.5 -> 207.8 | H11: 2166002.2 | I11: =+H11*$I$4 -> 253493.09 | J11: =+H11*$J$4 -> 216600.22 | K11: =+(H11+I11+J11)*$K$4 -> 474497.2 | L11: =+H11+I11+J11+K11 -> 3110592.7 | M11: =+G10/$N$5 -> 0.15560056 | N11: =+M11*$N$31 -> 4058177.8 | O11: 2690929.4
B12: CONSTRUCCION AMBIENTE DE DISPENSACION Y EXPENDIO | C12: Infraestructura | D12: Ambientes | E12: 1 | F12: m2 | G12: 39.05 | H12: 407037.47 | I12: =+H12*$I$4 -> 47636.694 | J12: =+H12*$J$4 -> 40703.747 | K12: =+(H12+I12+J12)*$K$4 -> 89168.024 | L12: =+H12+I12+J12+K12 -> 584545.94 | M12: =+G11/$N$5 -> 0.12524712 | N12: =+M12*$N$31 -> 3266537.6 | O12: 2166002.2
B13: CONSTRUCCION DE TOPICO DE URGENCIAS Y EMERGENCIAS | C13: Infraestructura | D13: Ambientes | E13: 1 | F13: m2 | G13: 33.7 | H13: 351271.78 | I13: =+H13*$I$4 -> 41110.284 | J13: =+H13*$J$4 -> 35127.177 | K13: =+(H13+I13+J13)*$K$4 -> 76951.663 | L13: =+H13+I13+J13+K13 -> 504460.9 | M13: =+G12/$N$5 -> 0.023536574 | N13: =+M13*$N$31 -> 613851.27 | O13: 407037.47
B14: CONSTRUCCION SALA DE EMERGENCIA | C14: Infraestructura | D14: Ambientes | E14: 1 | F14: m2 | G14: 30 | H14: 312704.84 | I14: =+H14*$I$4 -> 36596.692 | J14: =+H14*$J$4 -> 31270.484 | K14: =+(H14+I14+J14)*$K$4 -> 68502.964 | L14: =+H14+I14+J14+K14 -> 449074.98 | M14: =+G13/$N$5 -> 0.020311973 | N14: =+M14*$N$31 -> 529751.28 | O14: 351271.78
B15: CONSTRUCCION DE SALA DE RADIOGRAFIA | C15: Infraestructura | D15: Ambientes | E15: 1 | F15: m2 | G15: 25.26 | H15: 263297.48 | I15: =+H15*$I$4 -> 30814.414 | J15: =+H15*$J$4 -> 26329.748 | K15: =+(H15+I15+J15)*$K$4 -> 57679.495 | L15: =+H15+I15+J15+K15 -> 378121.14 | M15: =+G14/$N$5 -> 0.018081875 | N15: =+M15*$N$31 -> 471588.68 | O15: 312704.84
B16: CONSTRUCCION DE SALA DE ECOGRAFIA | C16: Infraestructura | D16: Ambientes | E16: 1 | F16: m2 | G16: 24.76 | H16: 258085.73 | I16: =+H16*$I$4 -> 30204.47 | J16: =+H16*$J$4 -> 25808.573 | K16: =+(H16+I16+J16)*$K$4 -> 56537.779 | L16: =+H16+I16+J16+K16 -> 370636.55 | M16: =+G15/$N$5 -> 0.015224939 | N16: =+M16*$N$31 -> 397077.67 | O16: 263297.48
B17: CONSTRUCCION DE AREA DE DESINFECCION | C17: Infraestructura | D17: Ambientes | E17: 1 | F17: m2 | G17: 48.11 | H17: 501474.34 | I17: =+H17*$I$4 -> 58688.895 | J17: =+H17*$J$4 -> 50147.433 | K17: =+(H17+I17+J17)*$K$4 -> 109855.92 | L17: =+H17+I17+J17+K17 -> 720166.58 | M17: =+G16/$N$5 -> 0.014923574 | N17: =+M17*$N$31 -> 389217.86 | O17: 258085.73
B18: CONSTRUCCION DE AREA DE SERVICIOS COMPLEMENTARIOS | C18: Infraestructura | D18: Ambientes | E18: 1 | F18: m2 | G18: 74.32 | H18: 774674.13 | I18: =+H18*$I$4 -> 90662.204 | J18: =+H18*$J$4 -> 77467.413 | K18: =+(H18+I18+J18)*$K$4 -> 169704.68 | L18: =+H18+I18+J18+K18 -> 1112508.4 | M18: =+G17/$N$5 -> 0.0289973 | N18: =+M18*$N$31 -> 756271.05 | O18: 501474.34
B19: CONSTRUCCION DE AMBIENTE ADMINISTRATIVO | C19: Infraestructura | D19: Ambientes | E19: 2 | F19: m2 | G19: =109.49+124.01+32 -> 265.5 | H19: 2767437.9 | I19: =+H19*$I$4 -> 323880.72 | J19: =+H19*$J$4 -> 276743.79 | K19: =+(H19+I19+J19)*$K$4 -> 606251.23 | L19: =+H19+I19+J19+K19 -> 3974313.6 | M19: =+G18/$N$5 -> 0.044794831 | N19: =+M19*$N$31 -> 1168282.4 | O19: 774674.13
B20: CONSTRUCCION DE DEPOSITO VEHICULAR | C20: Infraestructura | D20: Ambientes | E20: 1 | F20: m2 | G20: 136.29 | H20: 1420618.1 | I20: =+H20*$I$4 -> 166258.77 | J20: =+H20*$J$4 -> 142061.81 | K20: =+(H20+I20+J20)*$K$4 -> 311208.96 | L20: =+H20+I20+J20+K20 -> 2040147.7 | M20: =+G19/$N$5 -> 0.16002459 | N20: =+M20*$N$31 -> 4173559.8 | O20: 2767437.9
B21: CONSTRUCCION DE CASA DE FUERZA | C21: Infraestructura | D21: Ambientes | E21: 1 | F21: m2 | G21: 139.9 | H21: 1458246.9 | I21: =+H21*$I$4 -> 170662.57 | J21: =+H21*$J$4 -> 145824.69 | K21: =+(H21+I21+J21)*$K$4 -> 319452.15 | L21: =+H21+I21+J21+K21 -> 2094186.3 | M21: =+G20/$N$5 -> 0.082145957 | N21: =+M21*$N$31 -> 2142427.4 | O21: 1420618.1
B22: CONSTRUCCION DE CADENA DE FRIO | C22: Infraestructura | D22: Ambientes | E22: 1 | F22: m2 | G22: 19.44 | H22: 202632.74 | I22: =+H22*$I$4 -> 23714.656 | J22: =+H22*$J$4 -> 20263.274 | K22: =+(H22+I22+J22)*$K$4 -> 44389.92 | L22: =+H22+I22+J22+K22 -> 291000.59 | M22: =+G21/$N$5 -> 0.084321809 | N22: =+M22*$N$31 -> 2199175.2 | O22: 1458246.9
B23: CONSTRUCCION DE CENTRAL DE GASES | C23: Infraestructura | D23: Ambientes | E23: 1 | F23: m2 | G23: 13.48 | H23: 140508.71 | I23: =+H23*$I$4 -> 16444.114 | J23: =+H23*$J$4 -> 14050.871 | K23: =+(H23+I23+J23)*$K$4 -> 30780.665 | L23: =+H23+I23+J23+K23 -> 201784.36 | M23: =+G22/$N$5 -> 0.011717055 | N23: =+M23*$N$31 -> 305589.47 | O23: 202632.74
B24: CONSTRUCCION DE ALMACEN | C24: Infraestructura | D24: Ambientes | E24: 1 | F24: m2 | G24: 24 | H24: 250163.88 | I24: =+H24*$I$4 -> 29277.353 | J24: =+H24*$J$4 -> 25016.388 | K24: =+(H24+I24+J24)*$K$4 -> 54802.371 | L24: =+H24+I24+J24+K24 -> 359259.99 | M24: =+G23/$N$5 -> 0.008124789 | N24: =+M24*$N$31 -> 211900.51 | O24: 140508.71
B25: CONSTRUCCION DE AREA DE MANTENIMIENTO | C25: Infraestructura | D25: Ambientes | E25: 1 | F25: m2 | G25: 10.32 | H25: 107570.47 | I25: =+H25*$I$4 -> 12589.262 | J25: =+H25*$J$4 -> 10757.047 | K25: =+(H25+I25+J25)*$K$4 -> 23565.02 | L25: =+H25+I25+J25+K25 -> 154481.79 | M25: =+G24/$N$5 -> 0.0144655 | N25: =+M25*$N$31 -> 377270.94 | O25: 250163.88
B26: CONSTRUCCION DE DEPOSITO DE RESIDUOS SOLIDOS | C26: Infraestructura | D26: Ambientes | E26: 1 | F26: m2 | G26: 15.82 | H26: 164899.69 | I26: =+H26*$I$4 -> 19298.655 | J26: =+H26*$J$4 -> 16489.969 | K26: =+(H26+I26+J26)*$K$4 -> 36123.896 | L26: =+H26+I26+J26+K26 -> 236812.21 | M26: =+G25/$N$5 -> 0.0062201649 | N26: =+M26*$N$31 -> 162226.51 | O26: 107570.47
B27: CONSTRUCCION AMBIENTE DE RESIDENCIA | C27: Infraestructura | D27: Ambientes | E27: 1 | F27: m2 | G27: 82.16 | H27: 856394.33 | I27: =+H27*$I$4 -> 100226.14 | J27: =+H27*$J$4 -> 85639.433 | K27: =+(H27+I27+J27)*$K$4 -> 187606.78 | L27: =+H27+I27+J27+K27 -> 1229866.7 | M27: =+G26/$N$5 -> 0.0095351753 | N27: =+M27*$N$31 -> 248684.43 | O27: 164899.69
B28: CONSTRUCCION DE CENTRTAL DE VIGILANCIA Y SEGURIDAD | C28: Infraestructura | D28: Ambientes | E28: 1 | F28: m2 | G28: 14.69 | H28: 153121.14 | I28: =+H28*$I$4 -> 17920.18 | J28: =+H28*$J$4 -> 15312.114 | K28: =+(H28+I28+J28)*$K$4 -> 33543.618 | L28: =+H28+I28+J28+K28 -> 219897.05 | M28: =+G27/$N$5 -> 0.049520228 | N28: =+M28*$N$31 -> 1291524.2 | O28: 856394.33
B29: OTRAS ACCIONES DE INFRAESTRUCTURA (PLAN DE CONTINGENCIA) | C29: Infraestructura | D29: Numero de estrtucturas fisicas | E29: 1 | F29: m2 | G29: 400 | H29: 867000 | I29: =+H29*$I$4 -> 101467.35 | J29: =+H29*$J$4 -> 86700 | K29: =+(H29+I29+J29)*$K$4 -> 189930.12 | L29: =+H29+I29+J29+K29 -> 1245097.5 | M29: =+G28/$N$5 -> 0.0088540913 | N29: =+M29*$N$31 -> 230921.26 | O29: 153121.14
A30: EQUIPAMIENTO SUFICIENTE Y ADECUADO | B30: EQUIPAMIENTO DE AMBIENTES COMPLEMENTARIOS | C30: Equipamiento | D30: Numero de equipamiento | E30: kit de equipamiento | G30: 1 | H30: 3548398.2 | I30: =+H30*$I$4 -> 415278.62 | J30: =+H30*$J$4 -> 354839.82 | K30: =+(H30+I30+J30)*$K$4 -> 777333 | L30: =+H30+I30+J30+K30 -> 5095849.6 | M30: =+SUM(M6:M29) -> 1 | N30: =+M30*$N$31 -> 26080740
A31: PRESUPUESTO DE EJECUCION | L31: =+SUM(L5:L30) -> 31176590 | N31: =+SUM(L5:L29) -> 26080740 | P31: =+SUM(N6:N30) -> 52161481 | Q31: =+P31+3548398.21 -> 55709879
A32: EXPEDIENTE TECNICO | L32: =300000+60000 -> 360000 | N32: =+SUM(N6:N30) -> 52161481 | O32: =+SUM(O6:O30) -> 17293829
A33: GESTION DE PROYECTO | L33: 150000
A34: SUPERVISION | L34: 1167203.3 | N34: 5095849.6
A35: COSTO DEL PROYECTO | L35: =+L31+L32+L33+L34 -> 32853793
A36: CONTROL CONCURRENTE (2%) | L36: =+L35*2% -> 657075.87
A37: INVERSION TOTAL | L37: =+L35+L36 -> 33510869
A52: =$A$42*A46 -> 0 | B52: 8581.1208
A53: =$A$42*A47 -> 0 | B53: 8581.1208
A54: =$A$42*A48 -> 0 | B54: 37454.069
A55: =$A$42*A49 -> 0 | B55: 4060.2739
A56: =$A$42*A50 -> 0 | B56: 20839.326

Sheet COSTOS A PRECIOS SOCIALES
B1: PRESUPUESTO DE INVERSION A PRECIOS SOCIALES - C.S RAHUAPAMPA (S/.)
B2: ALTERNATIVA UNICA
B3: COMPONENTE | C3: ACTIVIDADES | D3: COSTOS A PRECIOS DE MERCADO | E3: FACTOR DE CORRECCION | F3: PRECIOS A PRECIOS SOCIALES
B4: INFRAESTRUCTURA ADECUADA PARA LA PRESTACION DE LOS SERVICIOS DE SALUD | C4: =+'COSTOS A PRECIOS MERCADO'!B5 -> CONSTRUCCION SALA DE PROCEDIMIENTOS AMBULATORIOS | D4: =+'COSTOS A PRECIOS MERCADO'!L5 -> 269444.99 | F4: =SUM(F5:F8) -> 178543.47 | H4: 0.1 | I4: =+$D$125*H4 -> 124509.75 | J4: 124509.75
C5: Mano de Obra calificada | D5: 28295.321 | E5: 0.79 | F5: =+D5*E5 -> 22353.303 | H5: 0.5 | I5: =+$D$125*H5 -> 622548.74 | J5: 622548.74 | L5: 282953.21
C6: Mano de obra no calificada | D6: 141476.6 | E6: 0.42 | F6: =+D6*E6 -> 59420.174 | H6: 0.15 | I6: =+$D$125*H6 -> 186764.62 | J6: 186764.62 | L6: 269748.73
C7: Materiales importados | D7: 42442.981 | E7: 0.8675 | F7: =+D7*E7 -> 36819.286 | H7: 0.25 | I7: =+$D$125*H7 -> 311274.37 | J7: 311274.37 | L7: 305432.27
C8: Servicios y otros bienes de origen nacional | D8: 70738.302 | E8: 0.8475 | F8: =+D8*E8 -> 59950.711 | L8: 682231.63
C9: =+'COSTOS A PRECIOS MERCADO'!B6 -> CONSTRUCCION DE CONSULTORIO CRED | D9: =+'COSTOS A PRECIOS MERCADO'!L6 -> 256870.89 | F9: =SUM(F10:F13) -> 170211.45 | H9: =+D4+D9+D14+D19 -> 1466828.6 | L9: 1546339.3
C10: Mano de Obra calificada | D10: 26974.873 | E10: 0.79 | F10: =+D10*E10 -> 21310.149 | L10: 4058177.8
C11: Mano de obra no calificada | D11: 134874.36 | E11: 0.42 | F11: =+D11*E11 -> 56647.232 | L11: 3266537.6
C12: Materiales importados | D12: 40462.309 | E12: 0.8675 | F12: =+D12*E12 -> 35101.053 | L12: 613851.27
C13: Servicios y otros bienes de origenn acional | D13: 67437.181 | E13: 0.8475 | F13: =+D13*E13 -> 57153.011 | L13: 529751.28
C14: =+'COSTOS A PRECIOS MERCADO'!B7 -> CONSTRUCCION DE SALA DE INMUNIZACIONES | D14: =+'COSTOS A PRECIOS MERCADO'!L7 -> 290850.9 | F14: =SUM(F15:F18) -> 192727.76 | L14: 397077.67
C15: Mano de Obra calificada | D15: 30543.227 | E15: 0.79 | F15: =D15*E15 -> 24129.149 | L15: 389217.86
C16: Mano de obra no calificada | D16: 152716.13 | E16: 0.42 | F16: =D16*E16 -> 64140.776 | L16: 756271.05
C17: Materiales importados | D17: 45814.84 | E17: 0.8675 | F17: =D17*E17 -> 39744.374 | L17: 1168282.4
C18: Servicios y otros bienes de origen nacional | D18: 76358.067 | E18: 0.8475 | F18: =D18*E18 -> 64713.462 | L18: 3670531.9
C19: =+'COSTOS A PRECIOS MERCADO'!B8 -> CONSTRUCCION DE AMBIENTE DE ACOMPAÑAMIENTO Y/O CONSEJERIA | D19: =+'COSTOS A PRECIOS MERCADO'!L8 -> 649661.81 | F19: =SUM(F20:F23) -> 430488.16 | L19: 503027.93
C20: Mano de Obra calificada | D20: 68223.163 | E20: 0.79 | F20: =D20*E20 -> 53896.298 | L20: 2199175.2
C21: Mano de obra no calificada | D21: 341115.81 | E21: 0.42 | F21: =D21*E21 -> 143268.64 | L21: 305589.47
C22: Materiales importados | D22: 102334.74 | E22: 0.8675 | F22: =D22*E22 -> 88775.39 | L22: 211900.51
C23: Servicios y otros bienes de origen nacional | D23: 170557.91 | E23: 0.8475 | F23: =D23*E23 -> 144547.83 | L23: 377270.94
C24: =+'COSTOS A PRECIOS MERCADO'!B9 -> CONSTRUCCION DE CONSULTORIO | D24: =+'COSTOS A PRECIOS MERCADO'!L9 -> 1472516.9 | F24: =SUM(F25:F28) -> 975740.09 | H24: =+SUM(#REF!) -> #REF! | L24: 248684.43
C25: Mano de Obra calificada | D25: 154633.93 | E25: 0.79 | F25: =+D25*E25 -> 122160.8 | L25: 1291524.2
C26: Mano de obra no calificada | D26: 773169.64 | E26: 0.42 | F26: =+D26*E26 -> 324731.25 | L26: 230921.26
C27: Materiales importados | D27: 231950.89 | E27: 0.8675 | F27: =+D27*E27 -> 201217.4 | L27: 5095849.6
C28: Servicios y otros bienes de origen nacional | D28: 386584.82 | E28: 0.8475 | F28: =+D28*E28 -> 327630.64
C29: =+'COSTOS A PRECIOS MERCADO'!B10 -> CONTRUCCION AMBIENTE COMPLEMENTARIO | D29: =+'COSTOS A PRECIOS MERCADO'!L10 -> 3864439.9 | F29: =SUM(F30:F33) -> 2560710.2 | H29: =+D24+D29+D34+D39 -> 9032095.5
C30: Mano de Obra calificada | D30: 405817.78 | E30: 0.79 | F30: =+D30*E30 -> 320596.05
C31: Mano de obra no calificada | D31: 2029088.9 | E31: 0.42 | F31: =+D31*E31 -> 852217.34
C32: Materiales importados | D32: 608726.67 | E32: 0.8675 | F32: =+D32*E32 -> 528070.39
C33: Servicios y otros bienes de origenn acional | D33: 1014544.4 | E33: 0.8475 | F33: =+D33*E33 -> 859826.42
C34: =+'COSTOS A PRECIOS MERCADO'!B11 -> CONSTRUCCION DE LABORATORIO GENERAL | D34: =+'COSTOS A PRECIOS MERCADO'!L11 -> 3110592.7 | F34: =SUM(F35:F38) -> 2061185.2
C35: Mano de Obra calificada | D35: 326653.76 | E35: 0.79 | F35: =D35*E35 -> 258056.47
C36: Mano de obra no calificada | D36: 1633268.8 | E36: 0.42 | F36: =D36*E36 -> 685972.9
C37: Materiales importados | D37: 489980.64 | E37: 0.8675 | F37: =D37*E37 -> 425058.2
C38: Servicios y otros bienes de origen nacional | D38: 816634.4 | E38: 0.8475 | F38: =D38*E38 -> 692097.65
C39: =+'COSTOS A PRECIOS MERCADO'!B12 -> CONSTRUCCION AMBIENTE DE DISPENSACION Y EXPENDIO | D39: =+'COSTOS A PRECIOS MERCADO'!L12 -> 584545.94 | F39: =SUM(F40:F43) -> 387340.15
C40: Mano de Obra calificada | D40: 61385.127 | E40: 0.79 | F40: =D40*E40 -> 48494.25
C41: Mano de obra no calificada | D41: 306925.63 | E41: 0.42 | F41: =D41*E41 -> 128908.77
C42: Materiales importados | D42: 92077.69 | E42: 0.8675 | F42: =D42*E42 -> 79877.396
C43: Servicios y otros bienes de origen nacional | D43: 153462.82 | E43: 0.8475 | F43: =D43*E43 -> 130059.74
C44: =+'COSTOS A PRECIOS MERCADO'!B13 -> CONSTRUCCION DE TOPICO DE URGENCIAS Y EMERGENCIAS | D44: =+'COSTOS A PRECIOS MERCADO'!L13 -> 504460.9 | F44: =SUM(F45:F48) -> 334273.06 | H44: =+SUM(#REF!) -> #REF!
C45: Mano de Obra calificada | D45: 52975.128 | E45: 0.79 | F45: =+D45*E45 -> 41850.352
C46: Mano de obra no calificada | D46: 264875.64 | E46: 0.42 | F46: =+D46*E46 -> 111247.77
C47: Materiales importados | D47: 79462.693 | E47: 0.8675 | F47: =+D47*E47 -> 68933.886
C48: Servicios y otros bienes de origen nacional | D48: 132437.82 | E48: 0.8475 | F48: =+D48*E48 -> 112241.05
C49: =+'COSTOS A PRECIOS MERCADO'!B14 -> CONSTRUCCION SALA DE EMERGENCIA | D49: =+'COSTOS A PRECIOS MERCADO'!L14 -> 449074.98 | F49: =SUM(F50:F53) -> 297572.46 | H49: =+D44+D49+D54+D59 -> 1702293.6
C50: Mano de Obra calificada | D50: 47158.868 | E50: 0.79 | F50: =+D50*E50 -> 37255.506
C51: Mano de obra no calificada | D51: 235794.34 | E51: 0.42 | F51: =+D51*E51 -> 99033.623
C52: Materiales importados | D52: 70738.302 | E52: 0.8675 | F52: =+D52*E52 -> 61365.477
C53: Servicios y otros bienes de origenn acional | D53: 117897.17 | E53: 0.8475 | F53: =+D53*E53 -> 99917.852
C54: =+'COSTOS A PRECIOS MERCADO'!B15 -> CONSTRUCCION DE SALA DE RADIOGRAFIA | D54: =+'COSTOS A PRECIOS MERCADO'!L15 -> 378121.14 | F54: =SUM(F55:F58) -> 250556.01
C55: Mano de Obra calificada | D55: 39707.767 | E55: 0.79 | F55: =D55*E55 -> 31369.136
C56: Mano de obra no calificada | D56: 198538.83 | E56: 0.42 | F56: =D56*E56 -> 83386.311
C57: Materiales importados | D57: 59561.65 | E57: 0.8675 | F57: =D57*E57 -> 51669.732
C58: Servicios y otros bienes de origen nacional | D58: 99269.417 | E58: 0.8475 | F58: =D58*E58 -> 84130.831
C59: =+'COSTOS A PRECIOS MERCADO'!B16 -> CONSTRUCCION DE SALA DE ECOGRAFIA | D59: =+'COSTOS A PRECIOS MERCADO'!L16 -> 370636.55 | F59: =SUM(F60:F63) -> 245596.47
C60: Mano de Obra calificada | D60: 38921.786 | E60: 0.79 | F60: =D60*E60 -> 30748.211
C61: Mano de obra no calificada | D61: 194608.93 | E61: 0.42 | F61: =D61*E61 -> 81735.75
C62: Materiales importados | D62: 58382.679 | E62: 0.8675 | F62: =D62*E62 -> 50646.974
C63: Servicios y otros bienes de origen nacional | D63: 97304.464 | E63: 0.8475 | F63: =D63*E63 -> 82465.534
C64: =+'COSTOS A PRECIOS MERCADO'!B17 -> CONSTRUCCION DE AREA DE DESINFECCION | D64: =+'COSTOS A PRECIOS MERCADO'!L17 -> 720166.58 | F64: =SUM(F65:F68) -> 477207.03 | H64: =+SUM(#REF!) -> #REF!
C65: Mano de Obra calificada | D65: 75627.105 | E65: 0.79 | F65: =+D65*E65 -> 59745.413
C66: Mano de obra no calificada | D66: 378135.52 | E66: 0.42 | F66: =+D66*E66 -> 158816.92
C67: Materiales importados | D67: 113440.66 | E67: 0.8675 | F67: =+D67*E67 -> 98409.77
C68: Servicios y otros bienes de origen nacional | D68: 189067.76 | E68: 0.8475 | F68: =+D68*E68 -> 160234.93
C69: =+'COSTOS A PRECIOS MERCADO'!B18 -> CONSTRUCCION DE AREA DE SERVICIOS COMPLEMENTARIOS | D69: =+'COSTOS A PRECIOS MERCADO'!L18 -> 1112508.4 | F69: =SUM(F70:F73) -> 737186.17 | H69: =+D64+D69+D74+D79 -> 7847136.3
C70: Mano de Obra calificada | D70: 116828.24 | E70: 0.79 | F70: =+D70*E70 -> 92294.306
C71: Mano de obra no calificada | D71: 584141.18 | E71: 0.42 | F71: =+D71*E71 -> 245339.3
C72: Materiales importados | D72: 175242.35 | E72: 0.8675 | F72: =+D72*E72 -> 152022.74
C73: Servicios y otros bienes de origenn acional | D73: 292070.59 | E73: 0.8475 | F73: =+D73*E73 -> 247529.82
C74: =+'COSTOS A PRECIOS MERCADO'!B19 -> CONSTRUCCION DE AMBIENTE ADMINISTRATIVO | D74: =+'COSTOS A PRECIOS MERCADO'!L19 -> 3974313.6 | F74: =SUM(F75:F78) -> 2633516.3
C75: Mano de Obra calificada | D75: 417355.98 | E75: 0.79 | F75: =D75*E75 -> 329711.23
C76: Mano de obra no calificada | D76: 2086779.9 | E76: 0.42 | F76: =D76*E76 -> 876447.56
C77: Materiales importados | D77: 626033.97 | E77: 0.8675 | F77: =D77*E77 -> 543084.47
C78: Servicios y otros bienes de origen nacional | D78: 1043390 | E78: 0.8475 | F78: =D78*E78 -> 884272.99
C79: =+'COSTOS A PRECIOS MERCADO'!B20 -> CONSTRUCCION DE DEPOSITO VEHICULAR | D79: =+'COSTOS A PRECIOS MERCADO'!L20 -> 2040147.7 | F79: =SUM(F80:F83) -> 1351871.7
C80: Mano de Obra calificada | D80: 214242.74 | E80: 0.79 | F80: =D80*E80 -> 169251.76
C81: Mano de obra no calificada | D81: 1071213.7 | E81: 0.42 | F81: =D81*E81 -> 449909.75
C82: Materiales importados | D82: 321364.11 | E82: 0.8675 | F82: =D82*E82 -> 278783.36
C83: Servicios y otros bienes de origen nacional | D83: 535606.84 | E83: 0.8475 | F83: =D83*E83 -> 453926.8
C84: =+'COSTOS A PRECIOS MERCADO'!B21 -> CONSTRUCCION DE CASA DE FUERZA | D84: =+'COSTOS A PRECIOS MERCADO'!L21 -> 2094186.3 | F84: =SUM(F85:F88) -> 1387679.6 | H84: =+#REF!+D84+D89+D94 -> #REF!
C85: Mano de Obra calificada | D85: 219917.52 | E85: 0.79 | F85: =+D85*E85 -> 173734.84
C86: Mano de obra no calificada | D86: 1099587.6 | E86: 0.42 | F86: =+D86*E86 -> 461826.8
C87: Materiales importados | D87: 329876.28 | E87: 0.8675 | F87: =+D87*E87 -> 286167.67
C88: Servicios y otros bienes de origenn acional | D88: 549793.8 | E88: 0.8475 | F88: =+D88*E88 -> 465950.25
C89: =+'COSTOS A PRECIOS MERCADO'!B22 -> CONSTRUCCION DE CADENA DE FRIO | D89: =+'COSTOS A PRECIOS MERCADO'!L22 -> 291000.59 | F89: =SUM(F90:F93) -> 192826.95
C90: Mano de Obra calificada | D90: 30558.947 | E90: 0.79 | F90: =D90*E90 -> 24141.568
C91: Mano de obra no calificada | D91: 152794.73 | E91: 0.42 | F91: =D91*E91 -> 64173.788
C92: Materiales importados | D92: 45838.42 | E92: 0.8675 | F92: =D92*E92 -> 39764.829
C93: Servicios y otros bienes de origen nacional | D93: 76397.366 | E93: 0.8475 | F93: =D93*E93 -> 64746.768
C94: =+'COSTOS A PRECIOS MERCADO'!B23 -> CONSTRUCCION DE CENTRAL DE GASES | D94: =+'COSTOS A PRECIOS MERCADO'!L23 -> 201784.36 | F94: =SUM(F95:F98) -> 133709.22
C95: Mano de Obra calificada | D95: 21190.051 | E95: 0.79 | F95: =D95*E95 -> 16740.141
C96: Mano de obra no calificada | D96: 105950.26 | E96: 0.42 | F96: =D96*E96 -> 44499.108
C97: Materiales importados | D97: 31785.077 | E97: 0.8675 | F97: =D97*E97 -> 27573.554
C98: Servicios y otros bienes de origen nacional | D98: 52975.128 | E98: 0.8475 | F98: =D98*E98 -> 44896.421
C99: =+'COSTOS A PRECIOS MERCADO'!B24 -> CONSTRUCCION DE ALMACEN | D99: =+'COSTOS A PRECIOS MERCADO'!L24 -> 359259.99 | F99: =SUM(F100:F103) -> 238057.97 | H99: =+SUM(#REF!) -> #REF!
C100: Mano de Obra calificada | D100: 37727.094 | E100: 0.79 | F100: =+D100*E100 -> 29804.405
...

Sheet OyM CON PY Y SIN PY
B2: COSTO DE OPERACIÓN Y MANTENIMIENTO A PRECIOS DE MERCADO EN EL CENTRO DE SALUD RAHUAPAMPA EN LA SITUACION SIN PROYECTO | H2: COSTO DE OPERACIÓN Y MANTENIMIENTO A PRECIOS SOCIALES DEL CENTRO DE SALUD DE RAHUAPAMPA EN LA SITUACION SIN PROYECTO
B3: DESCRIPCION | C3: UNIDAD DE MEDIDA | D3: CANTIDAD | E3: COSTO UNITARIO MENSUAL S/. | F3: COSTO ANUAL S/. | H3: DESCRIPCION | I3: UNIDAD DE MEDIDA | J3: CANTIDAD | K3: COSTO UNITARIO MENSUAL S/. | L3: PRECIOS PRIVADOS S/. | M3: F.C | N3: PRECIOS SOCIALES S/.
B4: COSTOS DE OPERACIÓN | F4: =F5+F10+F13+F15 -> 150800 | H4: COSTOS DE OPERACIÓN | L4: =L5+L10+L13+L15 -> 150800 | N4: =N5+N10+N13+N15 -> 120558
B5: REMUNERACIONES (Recurso Humano) | F5: =SUM(F7:F9) -> 126000 | H5: REMUNERACIONES (Recurso Humano) | L5: =SUM(L7:L9) -> 126000 | N5: =SUM(N7:N9) -> 99540
B6: MEDICO GENERAL | C6: GLB | D6: 1 | E6: 6500 | F6: =+D6*E6*12 -> 78000 | H6: MEDICO GENERAL | I6: GLB | J6: 1 | K6: 6500 | L6: =+K6*J6*12 -> 78000 | M6: 0.79 | N6: =+L6*M6 -> 61620
B7: 1 OBTETRA SERUMS | C7: GLB | D7: 1 | E7: 3500 | F7: =E7*12 -> 42000 | H7: 1 OBTETRA SERUMS | I7: GLB | J7: 1 | K7: 3500 | L7: =K7*12 -> 42000 | M7: 0.79 | N7: =L7*M7 -> 33180
B8: 1 ENFERMERA | C8: GLB | D8: 1 | E8: =2800 -> 2800 | F8: =E8*12 -> 33600 | H8: 1 ENFERMERA | I8: GLB | J8: 1 | K8: 2800 | L8: =K8*12 -> 33600 | M8: 0.79 | N8: =L8*M8 -> 26544
B9: 1 TECNICO ENFERMERO | C9: GLB | D9: 2 | E9: 2100 | F9: =E9*12*D9 -> 50400 | H9: 1 TECNICO ENFERMERO | I9: GLB | J9: 2 | K9: 2100 | L9: =K9*12*2 -> 50400 | M9: 0.79 | N9: =L9*M9 -> 39816
B10: SERVICIOS | F10: =SUM(F11:F12) -> 600 | H10: SERVICIOS | L10: =SUM(L11:L12) -> 600 | N10: =SUM(N11:N12) -> 508.5
B11: SERVICIO DE AGUA | C11: COSTO MENSUAL | D11: 12 | E11: 0 | F11: =D11*E11 -> 0 | H11: SERVICIO DE AGUA | I11: COSTO MENSUAL | J11: 12 | K11: 0 | L11: =J11*K11 -> 0 | M11: 0.8475 | N11: =L11*M11 -> 0
B12: SERVICIO DE ENERGIA ELECTRICA | C12: COSTO MENSUAL | D12: 12 | E12: 50 | F12: =D12*E12 -> 600 | H12: SERVICIO DE ENERGIA ELECTRICA | I12: COSTO MENSUAL | J12: 12 | K12: 50 | L12: =J12*K12 -> 600 | M12: 0.8475 | N12: =L12*M12 -> 508.5
B13: INSUMOS | F13: =F14 -> 18000 | H13: INSUMOS | L13: =L14 -> 18000 | N13: =N14 -> 15255
B14: INSUMOS MEDICOS | C14: ANUAL | D14: 1 | E14: 18000 | F14: =D14*E14 -> 18000 | H14: INSUMOS MEDICOS | I14: ANUAL | J14: 1 | K14: 18000 | L14: =J14*K14 -> 18000 | M14: 0.8475 | N14: =L14*M14 -> 15255
B15: OTROS | F15: =SUM(F16:F17) -> 6200 | H15: OTROS | L15: =SUM(L16:L17) -> 6200 | N15: =SUM(N16:N17) -> 5254.5
B16: UTILES DE OFICINA | C16: COSTO TRIMESTRAL | D16: 4 | E16: 200 | F16: =D16*E16 -> 800 | H16: UTILES DE OFICINA | I16: COSTO TRIMESTRAL | J16: 4 | K16: 200 | L16: =J16*K16 -> 800 | M16: 0.8475 | N16: =L16*M16 -> 678
B17: COMBUSTIBLE | C17: COSTO MENSUAL | D17: 12 | E17: 450 | F17: =D17*E17 -> 5400 | H17: COMBUSTIBLE | I17: COSTO MENSUAL | J17: 12 | K17: 450 | L17: =J17*K17 -> 5400 | M17: 0.8475 | N17: =L17*M17 -> 4576.5
B18: COSTOS DE MANTENIMIENTO | F18: =SUM(F19+F21) -> 0 | H18: COSTOS DE MANTENIMIENTO | L18: =L19+L21 -> 0 | N18: =N19+N21 -> 0
B19: INFRAESTRUCTURA | F19: 0 | H19: INFRAESTRUCTURA | L19: 0 | N19: 0
B20: ARQUITECTURA | C20: SERVICIO | D20: 1 | E20: 0 | H20: ARQUITECTURA | I20: SERVICIO | J20: 1 | K20: 0 | L20: 0
B21: EQUIPOS | F21: 0 | H21: EQUIPOS | L21: 0 | N21: 0
B22: EQUIPOS DE ESTABLECIMIENTO DE SALUD | C22: SERVICIO | D22: 1 | E22: 0 | H22: EQUIPOS DE ESTABLECIMIENTO DE SALUD | I22: SERVICIO | J22: 1 | K22: 0 | L22: 0
B23: TOTAL ANUAL | F23: =F18+F4 -> 150800 | H23: TOTAL ANUAL | L23: =L4+L18 -> 150800 | M23: =M4+M18 -> 0 | N23: =N4+N18 -> 120558
B26: COSTO DE OPERACIÓN Y MANTENIMIENTO A PRECIOS DE MERCADO DEL CENTRO DE SALUD DE RAHUAPAMPA EN LA SITUACION CON PROYECTO | H26: COSTO DE OPERACIÓN Y MANTENIMIENTO A PRECIOS SOCIALES DEL CENTRO DE SALUD DE RAHUAPAMPA EN LA SITUACION CON PROYECTO
B27: DESCRIPCION | C27: UNIDAD DE MEDIDA | D27: CANTIDAD | E27: COSTO UNITARIO MENSUAL S/. | F27: COSTO ANUAL S/. | H27: DESCRIPCION | I27: UNIDAD DE MEDIDA | J27: CANTIDAD | K27: COSTO UNITARIO MENSUAL S/. | L27: COSTO ANUAL S/. | M27: COSTO ANUAL S/. | N27: COSTO ANUAL S/.
B28: COSTOS DE OPERACIÓN | F28: =F29+F34+F37+F39 -> 150800 | H28: COSTOS DE OPERACIÓN | L28: =L29+L34+L37+L39 -> 150800 | N28: =N29+N34+N37+N39 -> 120558
B29: REMUNERACIONES (Recurso Humano) | F29: =SUM(F31:F33) -> 126000 | H29: REMUNERACIONES (Recurso Humano) | L29: =SUM(L31:L33) -> 126000 | N29: =SUM(N31:N33) -> 99540
B30: =+B6 -> MEDICO GENERAL | C30: GLB | D30: 1 | E30: =+E6 -> 6500 | F30: =+E30*12 -> 78000 | H30: =+B30 -> MEDICO GENERAL | I30: GLB | J30: 1 | K30: 6500 | L30: =+K30*12 -> 78000 | M30: 0.79 | N30: =L30*M30 -> 61620
B31: 1 OBTETRA SERUMS | C31: GLB | D31: 1 | E31: 3500 | F31: =E31*12 -> 42000 | H31: 1 OBTETRA SERUMS | I31: GLB | J31: 1 | K31: 3500 | L31: =K31*12*J31 -> 42000 | M31: 0.79 | N31: =L31*M31 -> 33180
B32: 1 ENFERMERA | C32: GLB | D32: 1 | E32: =2800 -> 2800 | F32: =E32*12 -> 33600 | H32: 1 ENFERMERA | I32: GLB | J32: 1 | K32: 2800 | L32: =K32*12 -> 33600 | M32: 0.79 | N32: =L32*M32 -> 26544
B33: 1 TECNICO ENFERMERO | C33: GLB | D33: 2 | E33: 2100 | F33: =E33*12*D33 -> 50400 | H33: 1 TECNICO ENFERMERO | I33: GLB | J33: 2 | K33: 2100 | L33: =K33*12*2 -> 50400 | M33: 0.79 | N33: =L33*M33 -> 39816
B34: SERVICIOS | F34: =SUM(F35:F36) -> 600 | H34: SERVICIOS | L34: =SUM(L35:L36) -> 600 | N34: =SUM(N35:N36) -> 508.5
B35: SERVICIO DE AGUA | C35: COSTO MENSUAL | D35: 12 | E35: 0 | F35: =D35*E35 -> 0 | H35: SERVICIO DE AGUA | I35: COSTO MENSUAL | J35: 12 | K35: 0 | L35: =J35*K35 -> 0 | M35: 0.8475 | N35: =L35*M35 -> 0
B36: SERVICIO DE ENERGIA ELECTRICA | C36: COSTO MENSUAL | D36: 12 | E36: 50 | F36: =D36*E36 -> 600 | H36: SERVICIO DE ENERGIA ELECTRICA | I36: COSTO MENSUAL | J36: 12 | K36: 50 | L36: =J36*K36 -> 600 | M36: 0.8475 | N36: =L36*M36 -> 508.5
B37: INSUMOS | F37: =F38 -> 18000 | H37: INSUMOS | L37: =L38 -> 18000 | N37: =N38 -> 15255
B38: INSUMOS MEDICOS | C38: COSTO ANUAL | D38: 1 | E38: 18000 | F38: =D38*E38 -> 18000 | H38: INSUMOS MEDICOS | I38: COSTO ANUAL | J38: 1 | K38: 18000 | L38: =J38*K38 -> 18000 | M38: 0.8475 | N38: =L38*M38 -> 15255
B39: OTROS | F39: =SUM(F40:F41) -> 6200 | H39: OTROS | L39: =SUM(L40:L41) -> 6200 | N39: =SUM(N40:N41) -> 5254.5
B40: UTILES DE OFICINA | C40: COSTO TRIMESTRAL | D40: 4 | E40: 200 | F40: =D40*E40 -> 800 | H40: UTILES DE OFICINA | I40: COSTO TRIMESTRAL | J40: 4 | K40: 200 | L40: =J40*K40 -> 800 | M40: 0.8475 | N40: =L40*M40 -> 678
B41: COMBUSTIBLE | C41: COSTO MENSUAL | D41: 1 | E41: 450 | F41: =E41*12 -> 5400 | H41: COMBUSTIBLE | I41: COSTO MENSUAL | J41: 1 | K41: 450 | L41: =K41*12 -> 5400 | M41: 0.8475 | N41: =L41*M41 -> 4576.5
B42: COSTOS DE MANTENIMIENTO | F42: =F43+F45 -> 13500 | H42: COSTOS DE MANTENIMIENTO | L42: =L43+L45 -> 13500 | N42: =N43+N45 -> 11441.25
B43: INFRAESTRUCTURA | F43: =F44 -> 5000 | H43: INFRAESTRUCTURA | L43: =L44 -> 5000 | N43: =N44 -> 4237.5
B44: INFRAESTRUCTURA | C44: COSTO POR AÑO | D44: 1 | E44: 5000 | F44: =+D44*E44 -> 5000 | H44: ARQUITECTURA | I44: COSTO POR AÑO | J44: 1 | K44: 5000 | L44: =+J44*K44 -> 5000 | M44: 0.8475 | N44: =L44*M44 -> 4237.5
B45: EQUIPOS | F45: =F46 -> 8500 | H45: EQUIPOS | L45: =L46 -> 8500 | N45: =N46 -> 7203.75
B46: EQUIPOS DE ESTABLECIMIENTO DE SALUD | C46: COSTO POR AÑO | D46: 1 | E46: 8500 | F46: =+E46 -> 8500 | H46: EQUIPOS DE ESTABLECIMIENTO DE SALUD | I46: COSTO POR AÑO | J46: 1 | K46: 8500 | L46: =+J46*K46 -> 8500 | M46: 0.8475 | N46: =L46*M46 -> 7203.75
B47: TOTAL ANUAL | F47: =F28+F42 -> 164300 | H47: TOTAL ANUAL | L47: =L28+L42 -> 164300 | N47: =N28+N42 -> 131999.25
